Workbook

Sheet 01_Ofertas_Originales
A1: ID | B1: → NLP | C1: Título | D1: Empresa | E1: Ubicación | F1: Fecha Publicación | G1: Portal | H1: Descripción Completa | I1: URL
A2: 1118026700 | B2: → NLP | C2: VENDEDOR DE REPUESTOS AUTOMOTOR | D2: SERVICE CARS SA | E2: Capital Federal, Buenos Aires | F2: 29-10-2025 | G2: bumeran | H2: Buscamos sumar a nuestro equipo de trabajo un REPUESTERO / VENDEDOR AUTOMOTOR CON EXPERIENCIA COMPROBABLESomos un post venta de reconocidas marcas líderes del mercado en constante expansión y buscamos el siguiente perfil: conocimiento EXCLUYENTE en mecánica y repuestos de autos, manejo básico o intermedio de paquete oficce, canales de venta online y computación en general.Buscamos una persona DINAMICA, Y CON AMBICION DE VENTAS. Que sepa trabajar en equipo y pueda manejar una excelente comunicación con las distintas áreas del taller, contribuyendo al excelente funcionamiento del mismo.Como empresa, trabajamos todos los días para darle al cliente una experiencia cálida y distinguida, buscamos un perfil que además de poseer las habilidades propias del puesto, cuente con marcada vocación de servicio y quiera sumarse a nuestro lema, que es, brindarle una experiencia de lujo al cliente en todo momento.Ofrecemos excelente clima laboral, comedor en planta, sueldo acorde al puesto, entre otros beneficios | I2: https://www.bumeran.com.ar/empleos/1118026700.html
A3: 1118026729 | B3: → NLP | C3: Responsable de Deposito | D3: Manpower | E3: Capital Federal, Buenos Aires | F3: 29-10-2025 | G3: bumeran | H3: ¡Te estamos buscando!Importante empresa internaciónal dedicada a la fabricación y comercialización de colchones, estructuras de cama, almohadas y productos de bienestar busca incorporar un/a Encargado/a de Depósito para la apertura de su nuevo local y centro de distribución en Argentina . Responsabilidades principales: • Organización integral del depósito y del nuevo punto de venta. • Control de inventarios y manejo de stocks. • Ejecución de rutinas administrativas y financieras (cierres de caja, conciliaciones bancarias, pagos). • Gestión de facturación y documentación comercial. • Coordinación y liderazgo del equipo operativo. • Entrega de mercadería y coordinación con RRHH. • Comunicación directa con directivos en Paraguay y Brasil. • Viajes ocasionales al exterior (Paraguay/Brasil) para reuniones o capacitaciones. Requisitos: • Experiencia previa en puestos similares (depósito, administración o logística). • Conocimientos sólidos en inventarios, facturación y cierres administrativos. • Habilidad para liderar y motivar equipos. • Buenas capacidades de comunicación y autogestión. • Licencia de conducir vigente (auto). • Disponibilidad para viajar. • Perfil proactivo, autogestivo, con ganas de aprender, preguntar y asumir responsabilidades. Condiciones: • Horario: lunes a viernes de 8 a 18 hs (no se trabaja feriados). Ubicación: Capital Federal, Buenos Aires. | I3: https://www.bumeran.com.ar/empleos/1118026729.html
A4: 1118027243 | B4: → NLP | C4: Abogado/a - Impuestos | D4: LAWARD Recursos Humanos para Abogados | E4: Capital Federal, Buenos Aires | F4: 30-10-2025 | G4: bumeran | H4: LAWARD seleccionará un Abogado/a para el Departamento de Impuestos de Estudio Jurídico de primera línea.Requisitos: Profesional con hasta 4 años de experiencia en Derecho Tributario, con foco en litigios y asesoramiento, incluyendo sólida gestión de casos contencioso-tributarios, manejo de casos en sede administrativa y judicial, y planificación de estrategias; Inglés, dominio oral y escrito.Se valorará a quienes cuenten con Posgrados y/o Maestrías en Derecho Tributario.Se ofrece desarrollo y crecimiento profesional así como excelente paquete de beneficios.Modalidad: Híbrida. Zona: Retiro. CABALos interesados en aplicar a la búsqueda podrán postularse enviando sin omitir remuneración bruta pretendida y promedio académico | I4: https://www.bumeran.com.ar/empleos/1118027243.html
A5: 1118027261 | B5: → NLP | C5: Supervisor de Limpieza | D5: Ceta Capital Humano | E5: San Fernando, Buenos Aires | F5: 30-10-2025 | G5: bumeran | H5: En Ceta Capital Humano nos encontramos en la búsqueda de Supervisor de Limpieza para importante frigorífico de San Fernando Zona NorteResponsabilidades: Coordinar y supervisar las tareas diarias de limpieza Planificar cronograma de trabajo y limpiezas profundas Asignar tareas y controlar el desempeño del personal a cargo Llevar control de inventario de uso de insumos Capacitar al equipo en técnicas, protocolos y seguridadRequisitos: Experiencia de 2 años en posiciones similares Experiencia en manejo de personal y control de insumos Secundario Completo Dominio de paquete office | I5: https://www.bumeran.com.ar/empleos/1118027261.html
A6: 1118027276 | B6: → NLP | C6: Ejecutivo de Cuentas SSR/SR - Presencial | D6: StaffRock IT | E6: Munro, Buenos Aires | F6: 30-10-2025 | G6: bumeran | H6: En StaffRock IT, empresa especializada en servicios de Staff Augmentation y Búsqueda y Selección de profesionales de tecnología, nos encontramos en búsqueda de un Ejecutivo de Cuentas para sumarse al equipo de una empresa del rubro eléctrico industrial.Buscamos profesionales con perfil ejecutivo y orientación a resultados, con excelentes habilidades de comunicación y autonomía, capaces de gestionar y dar seguimiento a procesos comerciales con orden y estrategia, y de comprender las necesidades del cliente para diseñar soluciones a medida.¿Cuál será tu misión?Sumarte al equipo de nuestro cliente para captar y desarrollar cuentas industriales medianas y grandes, impulsando ventas técnicas consultivas de productos y servicios críticos de energía (UPS, baterías, estabilizadores, rectificadores, grupos electrógenos) y obras eléctricas industriales y de puesta a tierra. El rol combina prospección activa (hunter) con seguimiento y expansión de cuentas (farmer), dentro de una gestión comercial estructurada con CRM (Táctica Soft).Tareas y Responsabilidades Prospección activa de clientes industriales en sectores como industria pesada, manufactura, salud, energía, laboratorios, etc. Generación de oportunidades de venta para productos y servicios técnicos. Seguimiento del pipeline comercial y actualización del CRM (Táctica Soft). Armado y presentación de propuestas técnico-comerciales. Coordinación con áreas técnicas para armado de soluciones a medida. Cumplimiento de objetivos mensuales de prospección, cotización y cierre. Mantenimiento y desarrollo de relaciones de largo plazo con cuentas claves.¿Qué skills y experiencia buscamos? Más de 3 años de experiencia comercial comprobable en venta técnica B2B Experiencia en industrias y conocimiento de sus dinámicas de compra. Perfil hunter, con energía y autonomía para salir a buscar negocio. Buen manejo de CRM (ideal si usó Táctica Soft o similar). Capacidad de redacción técnica y presentación a clientes. Conocimientos básicos de sistemas eléctricos, energía y obras eléctricas y de PAT Formación técnica (electromecánica, electrónica, electricidad, etc.). Se valorará contar con experiencia en empresas de servicios técnicos o en instalaciones/obras eléctricas, así como experiencia en la gestión de negocios a largo plazo. Nivel de inglés técnico (deseable). Preferentemente residir en zona norte (GBA) o acceso fácil a Munro.¿Qué ofrecemos? Contratación bajo Relación de Dependencia. Modalidad Full-Time y Presencial en Munro (Provincia de Buenos Aires). Excelente clima de trabajo. | I6: https://www.bumeran.com.ar/empleos/1118027276.html
A7: 1118027662 | B7: → NLP | C7: Farmacéutico/a para farmacias en Rio Cuarto | D7: Farmacity | E7: Río Cuarto, Córdoba | F7: 30-10-2025 | G7: bumeran | H7: Somos Farmacity un ecosistema de negocios compuesto por nuestra red de farmacias, Simplicity, Get The Look y The Food MarketDedicado a generar oportunidades y experiencias de bienestar que mejoran la vida de las personas a través de la salud, la belleza y la alimentación saludable.En Farmacity, valoramos la actitud protagonista de nuestros/as colaboradores/as, quienes son los verdaderos motores de nuestra organización, creando una cultura donde el bienestar, la inclusión y el crecimiento personal sean pilares fundamentales. Te invitamos a ser parte de nuestro equipo, donde podrás aplicar tus habilidades mientras aprendes y te desarrollas en un entorno laboral diverso, inclusivo y respetuoso.Estamos en búsqueda de farmacéuticos/as en Rio Cuarto que compartan nuestra visión de una atención sanitaria innovadora, dedicados y que deseen marcar la diferencia en la vida de nuestros pacientes.Si la vocación de servicio te apasiona en la farmacia, ¡esta es TU oportunidad para hacer lo que más te gusta y disfrutar cada día!🔎 ¿A quiénes buscamos? A personas que sientan la vocación de servicio con el otro. Profesionales comprometidos con la excelencia y el cuidado del paciente. A quienes siendo tal cual son, saben respetar las diferencias.📝¿Qué te proponemos? La posibilidad de unirte a una empresa que pone en el centro a sus colaboradores. No solo cuidamos la salud, sino también el bienestar de quienes forman parte de nuestro equipo, mientras seguimos creciendo y mejorando continuamente como compañía.¿Qué valoramos? Valoramos la habilidad para liderar y la capacidad de generar ideas innovadoras para estructurar equipos Dispensa de medicamentos. Control y orden de stock. Participación como agente de salud en campañas de vacunación y/o acciones destinadas a promover la salud. Garantizar la correcta trazabilidad de los medicamentos y la actualización de los libros.💡¿Qué te pediriamos? Matricula habilitada para ejercicio profesional Bloqueo de tituloLo mejor para el final: priorizamos TU Bienestar⚕️ Medicina prepaga (Swiss Medical) para vos y tu grupo familiar🙌 Pago de matrícula, colegiatura y seguro de mala praxis a cargo de la compañía🎈 Día de cumpleaños libre💌 Descuentos en nuestras sucursales y compra online de Farmacity, Get The Look, Simplicity y The Food Market📌 Descuentos corporativos en gimnasios, cines, teatros, viajes, restaurantes, spas y otros rubros.¡Postulate y empezá a vivir la #ExperienciaFarmacity! 🚀 #TuMejorVersión #DesafiateConNosotros #ExperienciaFarmacity #vocacióndeservicio#Farmaceuticos | I7: https://www.bumeran.com.ar/empleos/1118027662.html
A8: 1118027834 | B8: → NLP | C8: Vendedora Digital / Atención al Cliente | D8: metalúrgica | E8: Lomas de Zamora, Buenos Aires | F8: 30-10-2025 | G8: bumeran | H8: Vendedora Digital / Atención al Cliente OnlineResumen del PuestoEstamos buscando una Vendedora Digital / Atención al Cliente Online con un fuerte enfoque en ventas y servicio al cliente para unirse a nuestro equipo. El candidato ideal será responsable de brindar asesoramiento, seguimiento y gestión de pedidos a través de canales digitales.Responsabilidades Asesorar y atender consultas de clientes a través de medios digitales (WhatsApp, correo electrónico, redes sociales, CRM). Realizar seguimiento de presupuestos, cotizaciones y pedidos. Cargar y actualizar información en el sistema. Coordinar internamente con las áreas de logística y administración para asegurar la correcta entrega de productos. Horario de Lun a Vier de 8: 0 0 a 1 8: 0 0 Sab de 8: 0 0 a 1 3: 0 0Requisitos Experiencia en atención al cliente o ventas digitales. Manejo de herramientas informáticas. Conocimientos en sistemas CRM (deseable). Habilidades de comunicación y negociación. Orientación al cliente y capacidad de resolución de problemas. Residir en Lanus o Lomas de Zamora. | I8: https://www.bumeran.com.ar/empleos/1118027834.html
A9: 1118027941 | B9: → NLP | C9: Dibujante Tecnico | D9: Bombas y Sistemas Industriales | E9: Lomas del Mirador, Buenos Aires | F9: 30-10-2025 | G9: bumeran | H9: Empresa metalúrgica dedicada a la fabricación de repuestos, reparación y fabricación de bombas, incorpora Dibujante Técnico.Se requiere perfil Técnico con dominio de AutoCAD o herramientas de diseño similar para desempeñarse en el sector de diseño y desarrollo. Su principal responsabilidad será la realización de planos de piezas propias y el relevamiento de piezas varias y la realización de los planos correspondientes.Requisitos:Estudios: Secundario completo - Titulo Técnico Mecánico o Electromecánico.Estudiante de los primeros años de Ingeniería ( no excluyente )Conocimientos de Autocad, Solidworks 2D y 3D.Horario de trabajo: Lunes a Viernes de 8 a 16hsRemuneración pretendida. | I9: https://www.bumeran.com.ar/empleos/1118027941.html
A10: 1118028027 | B10: → NLP | C10: OPERADOR DE AUTOELEVADORES | D10: Asoko Tempo SA | E10: Villa Luzuriaga, Buenos Aires | F10: 30-10-2025 | G10: bumeran | H10: Importante Logistica busca ingresar un operador de autoelevadores con carnet habilitante para nuestra sede ubicada en Villa Luzuriaga.El ingreso es totalmente inmediato e ingresará por convenio colectivo de camioneros, categoria operador de autoelevadores.EXCLUYENTE: - Poseer carnet habilitante de conductor de autoelevadores.- ANALITICO DEL SECUNDARIO.- ANTECEDENTE PENALES ACTUALIZADOS.Turno de trabajo: TURNO TARDE (13 A 22HS) de Lunes a Viernes!Aguardamos sus postulaciones! | I10: https://www.bumeran.com.ar/empleos/1118028027.html
A11: 1118028038 | B11: → NLP | C11: Ejecutiva/o Comercial de Cuentas - GBA Norte | D11: GRUPO MASCHWITZ Hn | E11: San Isidro, Buenos Aires | F11: 30-10-2025 | G11: bumeran | H11: Ejecutiva/o Comercial de Cuentas - GBA Norte.La organización que nos encomienda esta búsqueda tiene presencia en todos los segmentos del mercado de soluciones gráficas y documentales, abarcando desde equipos de oficina de bajo/medio/alto volumen, equipos de impresión digital, grandes formatos, impresión de packaging y en diversos tipos de papel, software, etc., brindando soporte integral en lo referido a Servicio Técnico, con provisión de insumos, partes y repuestos en modalidades de venta y alquiler.El proyecto que encara en la actualidad se enfoca en el desarrollo del segmento corporativo en directa y para su red de Distribuidores a nivel nacional, buscando ampliar la presencia de sus marcas en las cuentas actuales, y creciendo en el mercado general a través de una focalizada e intensa actividad de relevamiento que permita diagnosticar y proponer soluciones racionales que generen beneficios a los clientes y permitan desplazar a la competencia. Para este fin buscamos personas con decidida vocación y formación profesional en lo comercial, orientada al trabajo relacional en las cuentas que permita contar con información clave para la preparación de propuestas competitivas.Requisitos de la posición Modalidad presencial de Lunes a Viernes. Disponibilidad para visitas a las cuentas. Trabajo por objetivos mensuales/trimestrales/anuales por línea y segmento de mercado. Capacidad de planificación del territorio asignado. Movilidad propia (no excluyente en CABA, excluyente en AMBA y Provincias). Licencia de conducir tipo B1/B2 al día. Conocimiento del mercado de equipos de oficina y gráficos, gran formato (no excluyente). Conocimiento del mercado de papel obra, coated, adhesivos, textil, etiquetas. Capacidad para orientar estrategias comerciales a los diferentes segmentos objetivo de clientes. Conocimiento de MS Office y uso de software ERP (Tango o equivalente) para carga de informes. Remuneración fija + variable en función de objetivos (comisiones) + premios + viáticos contra comprobantes.Requisitos de la persona. Estudios secundarios completos (deseables universitarios o tecnicaturas en áreas comerciales /marketing, o bien estudios de base técnica con experiencia en el trato con clientes). Experiencia comercial atendiendo cuentas en modalidad BTB de bienes o servicios. Orientación a la venta profesional en modalidad consultiva/relacional para desarrollo de cuentas en ciclo de compra. Capacidad analítica de relevamiento en cada cuenta y detección de oportunidades. Capacidad de Organización y planificación presentando informes a la Gerencia. Actitud claramente orientada a resultados. Capacidad de resiliencia y esfuerzo constante por superarse, superando obstáculos. Residencia en zonas Capital Federal o GBA Norte.La posición busca lograr objetivos cualitativos y cuantitativos a ser definidos según cada territorio en función del potencial, con acompañamiento durante los primeros meses de inducción en la parte de remuneración variable.La presente búsqueda es una oportunidad muy interesante de desarrollo profesional para quienes acepten el desafío, en un momento de expansión del negocio. Enviar CV a la dirección grupomaschwitz at gmail.com sin omitir remuneración deseada. | I11: https://www.bumeran.com.ar/empleos/1118028038.html
A12: 1118028201 | B12: → NLP | C12: 671SI Operarios ind. ALIMENTICIA c/ Tit. secundario - pres 31/10 de 10 a 1130 NUEVA Suc. SAN ISIDRO | D12: CONA CONSULTORES EN RRHH | E12: Tortuguitas, Buenos Aires | F12: 30-10-2025 | G12: bumeran | H12: CONA Consultores se encuentra en la búsqueda de OPERARIOS DE PRODUCCIÓN ALIMENTICIA con experiencia en tareas de manipulación de alimentos y producción continua. conocimiento de BPM.Importante industria ubicada en tortuguitas. DEBERÁ CONTAR CON SECUNDARIO COMPLETO Y CERTIFICADO DE ANTECEDENTES PENALES.Deberá presentarse VIERNES 31/10 de 10:00 a 11:30hs. NUEVA SUCURSAL SAN ISIDRO :EDIFICIO PANECO GOLF - LAPRIDA 3278 BLANCO OFICINA 42 - SAN ISIDROAsistir con la siguiente documentación:CV EN MANO ACTUALIZADOTITULO SECUNDARIO ORIGINAL + COPIAResidir en la zona TORTUGUITASA/ GARIN / Presentar certificado de buena conducta/ Contar con disponibilidad para turnos ROTATIVOS – (Mañana / Tarde / Noche) DISPONIBILIDAD PARA REALIZAR HS EXTRAS.Experiencia mínima de 1 año en posiciones similares.CERTIFICADO DE ANTECEDENTES PENALESResponsabilidades del puesto:Fraccionamiento y envasado de productos alimenticios.Empaque de los mismos, llenado, cierre y precintado de envases , conocimiento packaging termocontraible.Etiquetado y control de calidad de los productos envasados.cumplir con los objetivos de producción y BPMPreparación de pedidos.Mantenimiento del orden y limpieza del área de trabajo.Cumplimiento de normas de higiene y seguridad alimentaria.recepción de mercadería y materia prima.Se ofrece:Se ofrece :Trabajo full timeTM : lunes viernes de 6 a 14hs y Sab de 6 a 13hs..TT: de lunes a viernes de 13 aa 22hsPago quincenal según convenio alimentos CCT 244/94.buen clima laboral y equipo colaborativo.Ingreso eventual inmediato con posibilidad de efectivizaciónZona TORTUGUITAS¡Postula y sumate a esta gran oportunidad en la industria alimenticia.CUIDATE DE LOS AVISOS LABORALES FALSOS –En CONA siempre te postularas por plataformas de empleo directas y mails corporativos NO A PERSONAS INDIVIDUALES, nunca te pediremos que envíes fotos del DNI ni documentación personal.El empleador solo podrá solicitarle la información estrictamente necesaria para el desempeño en el trabajo que se ofrece. Ley 6471-21 GCBA | I12: https://www.bumeran.com.ar/empleos/1118028201.html
A13: 1118028376 | B13: → NLP | C13: Analista administrativo/a | D13: Randstad Argentina | E13: Capital Federal, Buenos Aires | F13: 30-10-2025 | G13: bumeran | H13: ¡Esta propuesta te puede interesar! Para importante empresa Multinacional ubicada en Nuñez, CABA, estamos en la búsqueda de un/a Analista administrativo/a. Serán sus principales tareas: Analizar y controlar los costos operativos de importación/exportación. Realizar tareas administrativas, contables, financieras de las actividades comercio internacional. Creación de ordenes de compra, solicitud de pedidos, control y seguimiento de gastos de las operaciones de comercio exterior Colaborar con equipos interdisciplinarios para optimizar la eficiencia de las operaciones comerciales (Finanzas, Contabilidad, Impuestos) Serán requisitos: Ser estudiante universitario de carreras como Administración de Empresas, Finanzas, Contador público o carreras afines. Habilidades analíticas y capacidad para interpretar datos complejos Buenas habilidades de comunicación e interpersonales Atención al detalle, precisión y enfoque en la exactitud Dominio de paquete MS Office (Principalmente Excel) Preferentemente con conocimiento del idioma Portugües. Se ofrece: Trabajo Híbrido (3 home office y 2 presencial) Medicina Prepaga Osde 210 Reintegro de gastos de conectividad Reintegro de gastos por refrigerio Capacitación continua y la oportunidad de incorporarse en una empresa muy destacada a nivel internacional Se valorarán perfiles: Con actitud proactiva y dinamismo Con buena comunicación y trabajo en equipo Con capacidad de análisis, Planificación y Organización Si consideras que reunís los requisitos para el puesto y te gustan los desafíos, no lo dudes…. ¡Postulate! Sobre Randstad En Randstad nos moviliza ayudar a las personas y a las organizaciones a desarrollar todo su potencial. Ese es el compromiso que asumimos como compañía en todo el mundo, un compromiso que nos impulsa a ir más allá para lograr que nuestros clientes y candidatos alcancen el éxito. ¿Cómo lo hacemos?, combinando nuestra pasión por las personas con el poder de la tecnología, creando experiencias más humanas, que nos permitan ser una fuente de inspiración y apoyo para quienes nos eligen. Porque estamos convencidos de que mejores personas hacen mejores. | I13: https://www.bumeran.com.ar/empleos/1118028376.html
A14: 1118028657 | B14: → NLP | C14: Recepcionista zona CABA (Eventual) | D14: Grupo Gestión | E14: Capital Federal, Buenos Aires | F14: 31-10-2025 | G14: bumeran | H14: Importante empresa se encuentra en la búsqueda de un/a recepcionista eventual.Responsabilidades del puesto: Atención personalizada a clientes y proveedores de manera presencial; telefónica o virtual Manejo de documentación Tareas administrativasHorario: lunes a viernes de 08 a 17hsZona de trabajo: Puerto MaderoSe trata de una propuesta eventual.¡Esperamos tu postulación! | I14: https://www.bumeran.com.ar/empleos/1118028657.html
... A50: 1118009703 | B50: → NLP | C50: Asesor Comercial E Commerce - Manager de redes sociales | D50: Confidencial | E50: Capital Federal, Buenos Aires | F50: 16-10-2025 | G50: bumeran | H50: Empresa de Servicios Corporativos con 30 años en el mercado está en búsqueda de un ejecutivo con experiencia en maquinaria y equipo, equipamientos de cafetería y comedores, mobiliario y decoración, equipamiento de seguridad, soluciones de automatización, refrigeración en freezer y heladeras, equipamiento de oficinas, entre otros. Atención a emprendedores, empresas, comerciantes, tiendas minoristas, cafeterías y especial atención en el segmento HORECA (restaurantes, hotelería, paradores). Tareas y funciones del puesto • Asesoramiento comercial a prospectos y emprendedores • Manejo de venta de máquinas automatizadas o tecnología de producción, especialmente en el rubro gastronómico y hotelero. • Manejo de e-commerce (Mercado Libre, Tienda web y Market Place). Creación y actualización de anuncios • Creación de diseños e iniciativas comerciales para redes sociales, crosselling y promociones • Armado de diseños personalizados para clientes o prospectos • Supervisión a la agencia de marketing digital en cuanto a funcionamiento de campañas (Meta y Google Adwords), mailing, creación de contenido y sitio web • Manejo de CRM y sistemas de gestión Manejo de herramientas y conocimientos • Paquete Office (Excel, Word, Powerpoint). • CRM Hubspot • Photoshop o afín • Canva o afín Sus Responsabilidades y Objetivos • Cumplir con los Objetivos de Ventas mensuales y anuales • Manejo de cuentas de redes sociales • Desarrollar nuevas carteras de clientes y potenciar a los clientes existentes. • Armado y gestión de publicaciones en redes sociales • Soporte en el diseño de presentaciones y material gráfico de baja y media definición • Aumentar los niveles de Facturación y participación del mercado. Amplia experiencia en • Ventas de equipamiento • Manejo de e-commerce • Google My Business y redes sociales • Manejo de objetivos de ventas Requisitos • Experiencia no menor a 3 años. Viva cerca de CABA • Sexo indistinto • Edad: Desde los 25 a 43 años Competencias • Manejo de prioridades, tiempos y seguimientos • Proactividad, entusiasmo e iniciativa • Manejo de presupuestos • Toleración a la presión del resultado y medición por objetivos • Adaptabilidad y flexibilidad • Trabajo en equipo y colaboración Ofrecemos: • Entorno laboral dinámico y motivador • Formar parte de un equipo sólido y con trayectoria en el mercado • Formación y capacitaciones constantes • Bonificaciones por desempeño y cumplimiento de objetivos Interesados • Enviar CV con pretensiones salariales • Con referencias comprobables • Horario y días: De lunes a Viernes de 8 a 17 hs • Modalidad: Presencial • Lugar de Trabajo: CAB | I50: https://www.bumeran.com.ar/empleos/1118009703.html

Sheet 02_NLP_Extraccion
A1: ID | B1: → Oferta | C1: → Match | D1: titulo_limpio | E1: provincia | F1: localidad | G1: modalidad | H1: zona_residencia_req | I1: requiere_movilidad_propia | J1: sector_empresa | K1: rubro_empresa | L1: es_tercerizado | M1: area_funcional | N1: nivel_seniority | O1: tiene_gente_cargo | P1: mision_rol | Q1: tareas_explicitas | R1: tareas_inferidas | S1: experiencia_min_anios | T1: experiencia_max_anios | U1: nivel_educativo | V1: carrera_especifica | W1: titulo_requerido | X1: skills_tecnicas_list | Y1: soft_skills_list | Z1: tecnologias_list | AA1: herramientas_list | AB1: idioma_principal | AC1: nivel_idioma_principal | AD1: jornada_laboral | AE1: tipo_contrato | AF1: salario_min | AG1: salario_max | AH1: moneda | AI1: beneficios_list | AJ1: tiene_cobertura_salud | AK1: licencia_conducir | AL1: tipo_licencia | AM1: tipo_oferta | AN1: calidad_texto | AO1: tiene_requisitos_discriminatorios | AP1: nlp_version | AQ1: nlp_confidence_score
A2: 1118026700 | B2: → Oferta | C2: → Match | D2: VENDEDOR DE REPUESTOS AUTOMOTOR | J2: Automotriz | L2: 0 | P2: vendedor automotor y repuestero | X2: ["paquete office", "canales de venta online", "computación en general"] | Y2: ["trabajo en equipo", "comunicacion"] | AI2: ["excelente clima laboral", "comedor en planta"] | AK2: 0 | AM2: demanda_real | AN2: media | AO2: 0 | AP2: 10.0.0 | AQ2: 6
A3: 1118026729 | B3: → Oferta | C3: → Match | D3: Responsable de Deposito | E3: FALSO Capital Federal | F3: FALSE | G3: presencial | J3: Manufactura/Industria | L3: 0 | M3: Operaciones/Logistica | O3: 1 | P3: Encargado/a de Depósito para la apertura de su nuevo local y centro de distribución en Argentina | Q3: [{"valor": "Organización integral del depósito y del nuevo punto de venta", "texto_original": "Organización integral del depósito y del nuevo punto de venta"}, {"valor": "Control de inventarios y manejo de stocks", "texto_original": "Control de inventarios y manejo de stocks"}, {"valor": "Ejecución de rutinas administrativas y financieras (cierres de caja, conciliaciones bancarias, pagos)", "texto_original": "Ejecución de rutinas administrativas y financieras (cierres de caja, conciliaciones bancarias, pagos)"}, {"valor": "Gestión de facturación y documentación comercial", "texto_original": "Gestión de facturación y documentación comercial"}, {"valor": "Coordinación y liderazgo del equipo operativo", "texto_original": "Coordinación y liderazgo del equipo operativo"}, {"valor": "Entrega de mercadería y coordinación con RRHH", "texto_original": "Entrega de mercadería y coordinación con RRHH"}, {"valor": "Comunicación directa con directivos en Paraguay y Brasil", "texto_original": "Comunicación directa con directivos en Paraguay y Brasil"}] | S3: 1 | X3: ["inventarios", "facturación", "cierres administrativos"] | Y3: ["liderar y motivar equipos", "buenas capacidades de comunicación", "autogestivo"] | AD3: full_time | AK3: 1 | AM3: demanda_real | AN3: alta | AO3: 0 | AP3: 10.0.0 | AQ3: 6
A4: 1118027243 | B4: → Oferta | C4: → Match | D4: Abogado/a - Impuestos | E4: TRUE | F4: TRUE | G4: TRUE | H4: TRUE | I4: TRUE | J4: TRUE | K4: TRUE | L4: TRUE | M4: TRUE | N4: junior | S4: 4 | T4: 4 | U4: universitario | W4: Abogado/a | AB4: ingles | AC4: intermedio | AD4: full_time | AI4: ["desarrollo y crecimiento profesional", "excelente paquete de beneficios"] | AK4: 0 | AM4: demanda_real | AN4: alta | AO4: 0 | AP4: 10.0.0 | AQ4: 6
A5: 1118027261 | B5: → Oferta | C5: → Match | D5: Supervisor de Limpieza | E5: Buenos Aires | F5: San Fernando | G5: presencial | J5: Manufactura/Industria | L5: 0 | M5: Operaciones/Logistica | O5: 1 | P5: Supervisar y coordinar tareas de limpieza | Q5: [{"valor": "coordinar y supervisar las tareas diarias de limpieza", "texto_original": "Coordinar y supervisar las tareas diarias de limpieza"}, {"valor": "planificar cronograma de trabajo y limpiezas profundas", "texto_original": "Planificar cronograma de trabajo y limpiezas profundas"}, {"valor": "asignar tareas y controlar el desempeño del personal a cargo", "texto_original": "Asignar tareas y controlar el desempeño del personal a cargo"}, {"valor": "llevar control de inventario de uso de insumos", "texto_original": "Llevar control de inventario de uso de insumos"}, {"valor": "capacitar al equipo en técnicas, protocolos y seguridad", "texto_original": "Capacitar al equipo en técnicas, protocolos y seguridad"}] | S5: 2 | U5: secundario | X5: ["paquete office"] | AK5: 0 | AM5: demanda_real | AN5: alta | AO5: 0 | AP5: 10.0.0 | AQ5: 6
A6: 1118027276 | B6: → Oferta | C6: → Match | D6: Ejecutivo de Cuentas SSR/SR | E6: Buenos Aires | F6: Munro | G6: presencial | H6: Preferentemente residir en zona norte (GBA) o acceso fácil a Munro | J6: Tecnologia/Software | K6: Staff Augmentation y Búsqueda y Selección | L6: 1 | M6: Ventas/Comercial | N6: semisenior | O6: 0 | P6: Captar y desarrollar cuentas industriales medianas y grandes | Q6: [{"valor": "prospección activa de clientes industriales en sectores como industria pesada, manufactura, salud, energía, laboratorios", "texto_original": "prospección activa de clientes industriales en sectores como industria pesada, manufactura, salud, energía, laboratorios"}, {"valor": "generación de oportunidades de venta para productos y servicios técnicos", "texto_original": "Generación de oportunidades de venta para productos y servicios técnicos"}, {"valor": "seguimiento del pipeline comercial y actualización del CRM (Táctica Soft)", "texto_original": "seguimiento del pipeline comercial y actualización del CRM (Táctica Soft)"}, {"valor": "armado y presentación de propuestas técnico-comerciales", "texto_original": "Armado y presentación de propuestas técnico-comerciales"}, {"valor": "coordinación con áreas técnicas para armado de soluciones a medida", "texto_original": "Coordinación con áreas técnicas para armado de soluciones a medida"}, {"valor": "cumplimiento de objetivos mensuales de prospección, cotización y cierre", "texto_original": "Cumplimiento de objetivos mensuales de prospección, cotización y cierre"}, {"valor": "mantenimiento y desarrollo de relaciones de largo plazo con cuentas claves", "texto_original": "Mantenimiento y desarrollo de relaciones de largo plazo con cuentas claves"}] | S6: 3 | U6: terciario | V6: Formación técnica (electromecánica, electrónica, electricidad) | X6: ["CRM", "Táctica Soft"] | Y6: ["comunicación", "autonomía"] | AB6: ingles | AC6: intermedio | AD6: full_time | AE6: indeterminado | AI6: ["Excelente clima de trabajo"] | AK6: 0 | AM6: demanda_real | AN6: alta | AO6: 0 | AP6: 10.0.0 | AQ6: 6
A7: 1118027662 | B7: → Oferta | C7: → Match | D7: Farmacéutico/a para farmacias en Rio Cuarto | E7: Cordoba | F7: Rio Cuarto | G7: presencial | J7: Salud/Farmaceutica | K7: farmacias | L7: 0 | M7: Salud | N7: junior | O7: 0 | P7: farmacéutico/a en Farmacity | Q7: [{"valor": "dispensa de medicamentos", "texto_original": "Dispensa de medicamentos"}, {"valor": "control y orden de stock", "texto_original": "Control y orden de stock"}, {"valor": "participación como agente de salud en campañas de vacunación", "texto_original": "Participación como agente de salud en campañas de vacunación"}] | S7: 0 | U7: universitario | W7: farmacéutico/a | Y7: ["vocación de servicio", "compromiso con la excelencia y el cuidado del paciente"] | AD7: full_time | AI7: ["Medicina prepaga (Swiss Medical) para vos y tu grupo familiar", "Pago de matrícula, colegiatura y seguro de mala praxis a cargo de la compañía", "Día de cumpleaños libre", "Descuentos en nuestras sucursales y compra online de Farmacity, Get The Look, Simplicity y The Food Market", "Descuentos corporativos en gimnasios, cines, teatros, viajes, restaurantes, spas y otros rubros"] | AJ7: 1 | AK7: 0 | AM7: demanda_real | AN7: alta | AO7: 0 | AP7: 10.0.0 | AQ7: 4
A8: 1118027834 | B8: → Oferta | C8: → Match | D8: Vendedora Digital / Atención al Cliente | E8: Buenos Aires | F8: Lanus o Lomas de Zamora | G8: presencial | H8: residir en Lanus o Lomas de Zamora | L8: 0 | M8: Ventas/Comercial | N8: junior | O8: 0 | P8: Brindar asesoramiento y seguimiento de pedidos a través de medios digitales | Q8: [{"valor": "asesorar y atender consultas", "texto_original": "Asesorar y atender consultas de clientes"}, {"valor": "realizar seguimiento de presupuestos, cotizaciones y pedidos", "texto_original": "Realizar seguimiento de presupuestos, cotizaciones y pedidos"}, {"valor": "cargar y actualizar información en el sistema", "texto_original": "Cargar y actualizar información en el sistema"}, {"valor": "coordinar internamente con áreas de logística y administración", "texto_original": "Coordinar internamente con las áreas de logística y administración para asegurar la correcta entrega de productos"}] | S8: 0 | X8: ["herramientas informáticas", "sistema CRM"] | Y8: ["comunicación", "negociación", "resolución de problemas"] | AA8: ["WhatsApp", "correo electrónico", "redes sociales"] | AD8: full_time | AK8: 0 | AM8: demanda_real | AN8: alta | AO8: 0 | AP8: 10.0.0 | AQ8: 5
A9: 1118027941 | B9: → Oferta | C9: → Match | D9: Dibujante Tecnico | G9: presencial | J9: Manufactura/Industria | K9: metalurgia | L9: 0 | M9: Operaciones/Logistica | N9: junior | O9: 0 | P9: Realización de planos de piezas propias y relevamiento de piezas varias | Q9: [{"valor": "realización de planos", "texto_original": "la realización de planos de piezas propias"}, {"valor": "relevamiento de piezas", "texto_original": "el relevamiento de piezas varias"}] | S9: 0 | U9: universitario | V9: los primeros años de Ingeniería | W9: Título Técnico Mecánico o Electromecánico | X9: ["AutoCAD", "Solidworks 2D y 3D"] | AA9: ["AutoCAD", "Solidworks 2D y 3D"] | AD9: full_time | AK9: 0 | AM9: demanda_real | AN9: media | AO9: 0 | AP9: 10.0.0 | AQ9: 5
A10: 1118028027 | B10: → Oferta | C10: → Match | D10: OPERADOR DE AUTOELEVADORES | E10: Buenos Aires | F10: Villa Luzuriaga | G10: presencial | J10: Transporte/Logistica | L10: 0 | M10: Operaciones/Logistica | N10: junior | O10: 0 | P10: Operador de autoelevadores | R10: ["manejo de autoelevadores", "trabajo en logistica"] | S10: 0 | U10: secundario | AD10: full_time | AK10: 1 | AL10: O | AM10: demanda_real | AN10: media | AO10: 0 | AP10: 10.0.0 | AQ10: 5
A11: 1118028038 | B11: → Oferta | C11: → Match | D11: Ejecutiva/o Comercial de Cuentas - GBA Norte | E11: Buenos Aires | F11: GBA Norte | G11: presencial | H11: Capital Federal o GBA Norte | I11: 1 | J11: Tecnologia/Software | K11: soluciones gráficas y documentales | L11: 0 | M11: Ventas/Comercial | N11: junior | O11: 0 | P11: Desarrollar el segmento corporativo en directa y para su red de Distribuidores a nivel nacional | Q11: [{"valor": "visitas a las cuentas", "texto_original": "Disponibilidad para visitas a las cuentas"}, {"valor": "preparación de propuestas competitivas", "texto_original": "Capacidad analítica de relevamiento en cada cuenta y detección de oportunidades"}] | R11: [{"valor": "presentar informes a la Gerencia", "texto_original": "Capacidad de Organización y planificación presentando informes a la Gerencia"}] | S11: 1 | U11: secundario | X11: ["MS Office"] | Y11: ["trabajo en equipo", "comunicacion"] | AA11: ["Tango o equivalente"] | AD11: full_time | AI11: ["viáticos contra comprobantes"] | AK11: 1 | AL11: B1 | AM11: demanda_real | AN11: alta | AO11: 0 | AP11: 10.0.0 | AQ11: 6
A12: 1118028201 | B12: → Oferta | C12: → Match | D12: 671SI Operarios ind. ALIMENTICIA c/ Tit. secundario - pres 31/10 de 10 a 1130 NUEVA Suc. SAN ISIDRO | E12: Buenos Aires | F12: San Isidro | G12: presencial | H12: Tortuguitas / GARIN | J12: Alimentacion | L12: 1 | M12: Produccion/Manufactura | N12: junior | O12: 0 | P12: Asistir en la producción y manipulación de alimentos | Q12: [{"valor": "fraccionamiento y envasado", "texto_original": "Fraccionamiento y envasado de productos alimenticios"}, {"valor": "empaque, llenado, cierre y precintado", "texto_original": "Empaque de los mismos, llenado, cierre y precintado de envases"}, {"valor": "etiquetado y control de calidad", "texto_original": "Etiquetado y control de calidad de los productos envasados"}, {"valor": "preparación de pedidos", "texto_original": "Preparación de pedidos"}, {"valor": "mantenimiento del orden y limpieza", "texto_original": "Mantenimiento del orden y limpieza del área de trabajo"}] | S12: 1 | U12: secundario | X12: ["BPM"] | AD12: full_time | AE12: eventual | AI12: ["buen clima laboral y equipo colaborativo"] | AK12: 0 | AM12: demanda_real | AN12: alta | AO12: 0 | AP12: 10.0.0 | AQ12: 6
A13: 1118028376 | B13: → Oferta | C13: → Match | D13: Analista administrativo/a | E13: CABA | F13: Nuñez | G13: hibrido | J13: Servicios Financieros | L13: 1 | M13: Administracion/Finanzas | N13: junior | O13: 0 | P13: Analizar y controlar los costos operativos de importación/exportación | Q13: [{"valor": "Realizar tareas administrativas, contables, financieras", "texto_original": "Realizar tareas administrativas, contables, financieras de las actividades comercio internacional"}, {"valor": "Colaborar con equipos interdisciplinarios para optimizar la eficiencia de las operaciones comerciales", "texto_original": "Colaborar con equipos interdisciplinarios para optimizar la eficiencia de las operaciones comerciales (Finanzas, Contabilidad, Impuestos)"}] | S13: 1 | U13: universitario | V13: universitario de carreras como Administración | X13: ["Excel"] | AA13: ["MS Office"] | AB13: ingles | AC13: intermedio | AD13: full_time | AI13: ["Medicina Prepaga Osde", "Reintegro de gastos de conectividad", "Reintegro de gastos por refrigerio"] | AJ13: 1 | AK13: 0 | AM13: demanda_real | AN13: alta | AO13: 0 | AP13: 10.0.0 | AQ13: 6
A14: 1118028657 | B14: → Oferta | C14: → Match | D14: Recepcionista | F14: Puerto Madero | G14: presencial | L14: 0 | M14: Atencion al Cliente | N14: junior | O14: 0 | P14: Atención personalizada a clientes y proveedores | Q14: [{"valor": "atención personalizada", "texto_original": "Atención personalizada a clientes y proveedores"}, {"valor": "manejo de documentación", "texto_original": "Manejo de documentación"}, {"valor": "tareas administrativas", "texto_original": "Tareas administrativas"}] | S14: 0 | AD14: full_time | AE14: eventual | AK14: 0 | AM14: demanda_real | AN14: alta | AO14: 0 | AP14: 10.0.0 | AQ14: 5
A15: 1118028681 | B15: → Oferta | C15: → Match | D15: ADMINISTRATIVA/O | E15: Buenos Aires | F15: Canning | G15: presencial | H15: Canning o zonas aledañas | I15: 1 | J15: Alimentacion | L15: 0 | M15: Administracion/Finanzas | N15: semisenior | O15: 0 | P15: Responsable del ingreso de mercadería al sistema, actualizar costos y precios de venta de los productos en el sistema, actualizar los precios de los productos en diferentes plataformas e-commerce, pago a proveedores, generar pedidos a proveedores, liquidación de sueldos | Q15: [{"valor": "ingreso de mercadería al sistema", "texto_original": "Responsable del ingreso de mercadería al sistema"}, {"valor": "actualizar costos y precios de venta en el sistema", "texto_original": "actualizar costos y precios de venta de los productos en el sistema"}, {"valor": "actualizar precios en plataformas e-commerce", "texto_original": "actualizar los precios de los productos en diferentes plataformas e-commerce"}, {"valor": "pago a proveedores", "texto_original": "pago a proveedores"}, {"valor": "generar pedidos a proveedores", "texto_original": "generar pedidos a proveedores"}, {"valor": "liquidación de sueldos", "texto_original": "liquidación de sueldos"}] | S15: 5 | X15: ["Paquete Office"] | AD15: full_time | AI15: ["excelentes condiciones de contratación"] | AK15: 0 | AM15: demanda_real | AN15: alta | AO15: 0 | AP15: 10.0.0 | AQ15: 6
A16: 1118028828 | B16: → Oferta | C16: → Match | D16: Búsqueda Laboral: Modelista – Vicente López (Florida Oeste) | E16: Buenos Aires | F16: Vicente López | G16: presencial | H16: AMBA, preferentemente cercana a Vicente López | L16: 0 | M16: Produccion/Manufactura | N16: semisenior | O16: 0 | P16: Desarrollar la moldería, prototipo y muestras de los productos de nuestras colecciones | Q16: [{"valor": "desarrollar moldería según la definición del diseño", "texto_original": "Desarrollar moldería según la definición del diseño"}, {"valor": "participar en las pruebas de calce junto al equipo de Producto", "texto_original": "Participar en las pruebas de calce junto al equipo de Producto"}, {"valor": "realizar ajustes necesarios", "texto_original": "realizando los ajustes necesarios"}, {"valor": "desarrollar progresiones de la moldería aprobada", "texto_original": "Desarrollar progresiones de la moldería aprobada"}, {"valor": "especificar avíos según género y prototipo", "texto_original": "Especificar avíos (entretelas, hilos, hombreras, etc.) según género y prototipo"}, {"valor": "realizar pruebas de comportamiento de géneros y registrar resultados", "texto_original": "Realizar pruebas de comportamiento de géneros y registrar resultados"}, {"valor": "entregar progresiones, prototipos, tablas de medidas y fichas técnicas a Producción en tiempo y forma", "texto_original": "Entregar progresiones, prototipos, tablas de medidas y fichas técnicas a Producción en tiempo y forma"}, {"valor": "colaborar en el armado del muestrario para el área Comercial", "texto_original": "Colaborar en el armado del muestrario para el área Comercial"}] | S16: 3 | U16: terciario | W16: Modelista | X16: ["Lectra"] | Y16: ["trabajo en equipo"] | AD16: full_time | AK16: 0 | AM16: demanda_real | AN16: alta | AO16: 0 | AP16: 10.0.0 | AQ16: 5
A17: 1118028833 | B17: → Oferta | C17: → Match | D17: Asesor Comercial Plan de Ahorro - Volkswagen | G17: presencial | J17: Automotriz | L17: 0 | M17: Ventas/Comercial | N17: junior | O17: 0 | P17: Asesor de ventas en concesionario automotriz | Q17: [{"valor": "optimización de los datos que se brindan para la concreción de la venta", "texto_original": "optimización de los datos que se brindan para la concreción de la venta"}, {"valor": "detección de oportunidades de nuevos negocios", "texto_original": "detección de oportunidades de nuevos negocios"}, {"valor": "cumplimiento de objetivos comerciales", "texto_original": "cumplimiento de objetivos comerciales"}] | S17: 0 | U17: secundario | Y17: ["iniciativa", "orientación al resultado", "excelencia en lo que hacemos", "orientación al cliente", "trabajo en equipo"] | AD17: full_time | AI17: ["descuento en Sport Club", "50% en todos los talleres", "15% en Repuestos", "12 cuotas S/Interés Bridgestone/Firestone 30%", "Seguros de la Caja", "Planes Adjudicados", "Descuentos en Malcriado (Shopping Tom)", "Descuentos en Samsung", "Descuentos en Bimbo"] | AK17: 0 | AM17: demanda_real | AN17: alta | AO17: 1 | AP17: 10.0.0 | AQ17: 4
A18: 1118028887 | B18: → Oferta | C18: → Match | D18: Account Executive (Hunter) | E18: Capital Federal | F18: Capital Federal | G18: hibrido | J18: Tecnologia/Software | L18: 0 | M18: Ventas/Comercial | N18: junior | O18: 0 | P18: Prospección y captación de nuevos clientes | Q18: [{"valor": "identificar oportunidades de negocio", "texto_original": "identificar oportunidades de negocio"}, {"valor": "elaborar propuestas comerciales", "texto_original": "elaborar propuestas comerciales"}, {"valor": "mantener una constante comunicación con los clientes", "texto_original": "mantener una constante comunicación con los clientes"}] | S18: 0 | T18: 2 | U18: universitario | Y18: ["mentalidad orientada a resultados", "habilidades de negociación"] | AD18: full_time | AK18: 0 | AM18: demanda_real | AN18: alta | AO18: 0 | AP18: 10.0.0 | AQ18: 5
A19: 1118028891 | B19: → Oferta | C19: → Match | D19: auxiliar contable | E19: Buenos Aires | F19: Munro | G19: hibrido | I19: 0 | L19: 0 | M19: Administracion/Finanzas | N19: junior | O19: 0 | P19: Administrativo Contable | Q19: [{"valor": "Gestión integral de caja diaria y fondos fijos", "texto_original": "Gestión integral de caja diaria y fondos fijos"}, {"valor": "Administración de cobranzas, pagos y depósitos bancarios", "texto_original": "Administración de cobranzas, pagos y depósitos bancarios"}, {"valor": "Control y registro de facturas, proveedores y padrones", "texto_original": "Control y registro de facturas, proveedores y padrones"}, {"valor": "Análisis de cuentas contables para cierres y balances", "texto_original": "Análisis de cuentas contables para cierres y balances"}, {"valor": "Emisión de pagos, notas de débito y planillas de descuentos", "texto_original": "Emisión de pagos, notas de débito y planillas de descuentos"}, {"valor": "Conciliaciones bancarias", "texto_original": "Conciliaciones bancarias"}, {"valor": "Manejo de cheques (depósito, rechazos, devoluciones)", "texto_original": "Manejo de cheques (depósito, rechazos, devoluciones)"}] | S19: 2 | T19: 2 | U19: universitario | V19: Contabilidad o un campo de | Y19: ["proactivo", "iniciativa"] | AD19: full_time | AI19: ["Bono anual por objetivos", "Celular"] | AK19: 0 | AM19: demanda_real | AN19: alta | AO19: 0 | AP19: 10.0.0 | AQ19: 6
A20: 2162667 | B20: → Oferta | C20: → Match | D20: Gerente de Operaciones | L20: 0 | M20: Operaciones/Logistica | N20: lead/manager | O20: 1 | P20: Dirigir la gestión operativa de todas las áreas de servicio | Q20: [{"valor": "Definir, implementar y supervisar estrategias operativas", "texto_original": "Definir, implementar y supervisar estrategias operativas"}, {"valor": "Dirigir equipos de coordinadores/as y supervisores/as", "texto_original": "Dirigir equipos de coordinadores/as y supervisores/as"}, {"valor": "Asegurar el cumplimiento de normas de calidad, higiene y seguridad en todas las operaciones", "texto_original": "Asegurar el cumplimiento de normas de calidad, higiene y seguridad en todas las operaciones"}, {"valor": "Monitorear indicadores clave (KPIs) de desempeño y liderar planes de mejora continua", "texto_original": "Monitorear indicadores clave (KPIs) de desempeño y liderar planes de mejora continua"}, {"valor": "Gestionar presupuestos operativos y recursos con foco en rentabilidad y sostenibilidad", "texto_original": "Gestionar presupuestos operativos y recursos con foco en rentabilidad y sostenibilidad"}, {"valor": "Mantener relaciones cercanas con clientes corporativos, promoviendo la satisfacción y fidelización", "texto_original": "Mantener relaciones cercanas con clientes corporativos, promoviendo la satisfacción y fidelización"}] | R20: [{"valor": "Impulsar proyectos innovadores en sustentabilidad y experiencia colaboradora", "texto_original": "Impulsar proyectos innovadores en sustentabilidad y experiencia colaboradora"}] | S20: 10 | U20: universitario | V20: Industrial | Y20: ["habilidades de liderazgo"] | AI20: ["Oportunidad de liderar la operación de una empresa en plena expansión", "Entorno de trabajo colaborativo, con fuerte cultura en sustentabilidad e innovación"] | AK20: 0 | AM20: demanda_real | AN20: alta | AO20: 0 | AP20: 10.0.0 | AQ20: 6
A21: 1118022146 | B21: → Oferta | C21: → Match | D21: Community manager | E21: Buenos Aires | F21: Tigre | G21: presencial | J21: Construcción | K21: Comercialización e importación de materiales para Construcción y Decoración | L21: 0 | M21: Marketing | N21: lead/manager | O21: 0 | P21: Construir y expandir las marcas del grupo fuera de Mercado Libre | Q21: [{"valor": "desarrollar e implementar iniciativas de marketing", "texto_original": "Desarrollar e implementar iniciativas de marketing"}, {"valor": "crear contenido para redes sociales", "texto_original": "Crear contenido para Instagram, Facebook y LinkedIn (producción, filmación, edición y redacción de copy)"}, {"valor": "responder mensajes en redes sociales", "texto_original": "Responder mensajes, comentarios y consultas en redes sociales"}, {"valor": "implementar campañas en Meta Ads y Google Ads", "texto_original": "Administrar campañas en Meta Ads y Google Ads"}, {"valor": "cargar y actualizar productos online", "texto_original": "Cargar y actualizar productos en TiendaNube u otras plataformas"}] | R21: [{"valor": "gestionar contactos y clientes con CRM", "texto_original": "Implementar un sistema de CRM activo para la gestión de clientes y prospectos"}, {"valor": "coordinar acciones con influencers", "texto_original": "Coordinar acciones con influencers, creadores de contenido y proveedores externos"}] | S21: 7 | U21: universitario | V21: Marketing, Comunicación, Publicidad, Branding o afines | X21: ["SEO", "Google Ads", "Meta Ads"] | Y21: ["creatividad", "atencion al detalle", "proactividad"] | Z21: ["TiendaNube", "Mercado Libre", "Shopify"] | AA21: ["CapCut", "Premiere", "Canva", "Photoshop / Illustrator"] | AD21: freelance | AI21: ["remuneracion competitiva", "oportunidad de crecer en una empresa con proyeccion regional"] | AK21: 0 | AM21: demanda_real | AN21: alta | AO21: 0 | AP21: 10.0.0 | AQ21: 5
A22: 1118025212 | B22: → Oferta | C22: → Match | D22: Representante Técnico/a Comercial | K22: agricultura | L22: 0 | M22: Ventas/Comercial | N22: junior | O22: 0 | P22: Comercialización de agro insumos y servicios | Q22: [{"valor": "asesoramiento técnico a clientes", "texto_original": "Asesoramiento técnico a clientes"}, {"valor": "desarrollo de nuevas oportunidades de negocio", "texto_original": "Desarrollo de nuevas oportunidades de negocio"}] | S22: 0 | U22: terciario | V22: carreras afines | W22: Ing. Agrónomo/a | Y22: ["vocación comercial", "orientación a resultados"] | AK22: 0 | AM22: demanda_real | AN22: media | AO22: 0 | AP22: 10.0.0 | AQ22: 5
A23: 1117984105 | B23: → Oferta | C23: → Match | D23: Venado Tuerto | E23: Santa Fe | F23: Venado Tuerto | G23: presencial | H23: Radicación en Venado Tuerto (Sta. Fé) | J23: Manufactura/Industria | K23: maquinaria agrícola | L23: 0 | M23: Ventas/Comercial | N23: lead/manager | O23: 1 | P23: Liderar equipo de ventas en concesionario oficial | R23: ["logro de objetivos comerciales", "liderazgo"] | S23: 35 | T23: 50 | U23: terciario | Y23: ["disposición para liderar en equipo", "proactivo y responsable"] | AI23: ["Buen ambiente y condiciones de trabajo"] | AK23: 0 | AM23: demanda_real | AN23: media | AO23: 1 | AP23: 10.0.0 | AQ23: 5
A24: 1117960588 | B24: → Oferta | C24: → Match | D24: Asistente de Dirección / Administrativo con experiencia en Publicidad y Medios | G24: hibrido | J24: Publicidad/Medios | L24: 0 | M24: Administracion/Finanzas | N24: junior | O24: 0 | P24: Asistir a la Dirección y coordinar tareas vinculadas a publicidad y medios | Q24: [{"valor": "Tareas administrativas generales", "texto_original": "Tareas administrativas generales"}, {"valor": "Atención telefónica y presencial de clientes y proveedores", "texto_original": "Atención telefónica y presencial de clientes y proveedores"}, {"valor": "Coordinación de llamados, correos y comunicaciones institucionales", "texto_original": "Coordinación de llamados, correos y comunicaciones institucionales"}, {"valor": "Apoyo en campañas publicitarias", "texto_original": "Apoyo en campañas publicitarias"}] | S24: 1 | X24: ["Office", "planillas", "excel avanzado"] | Y24: ["habilidades de comunicación", "atención al cliente"] | AA24: ["Office", "planillas", "excel avanzado"] | AD24: full_time | AI24: ["Excelente clima de trabajo", "posibilidades de desarrollo"] | AK24: 0 | AM24: demanda_real | AN24: alta | AO24: 0 | AP24: 10.0.0 | AQ24: 6
A25: 1118009739 | B25: → Oferta | C25: → Match | D25: Administrativa Comercio Exterior | E25: CABA | G25: hibrido | J25: Retail/Comercio | L25: 1 | M25: Administracion/Finanzas | N25: junior | O25: 0 | P25: Administrativo para área de Comex | Q25: [{"valor": "Gestión y carga de Facturación de Clientes (FC)", "texto_original": "Gestión y carga de Facturación de Clientes (FC)"}, {"valor": "Coordinación y ejecución del cierre de ciclos de pago", "texto_original": "Coordinación y ejecución del cierre de ciclos de pago"}] | S25: 0 | U25: terciario | V25: Comercio internacional | AD25: full_time | AE25: eventual | AI25: ["Cobertura médica correspondiente a convenio", "espacio de comedor"] | AJ25: 1 | AK25: 0 | AM25: demanda_real | AN25: alta | AO25: 0 | AP25: 10.0.0 | AQ25: 4
A26: 1118000814 | B26: → Oferta | C26: → Match | D26: Asistente Administrativo de Ventas | G26: presencial | L26: 0 | M26: Administracion/Finanzas | N26: junior | O26: 0 | P26: Brindar soporte administrativo y operativo al área de ventas | Q26: [{"valor": "cargar y actualizar pedidos de venta en el sistema interno", "texto_original": "Cargar y actualizar pedidos de venta en el sistema interno"}, {"valor": "elaborar reportes de ventas, márgenes, rotación y desempeño por producto o vendedor mediante Excel avanzado", "texto_original": "Elaborar reportes de ventas, márgenes, rotación y desempeño por producto o vendedor mediante Excel avanzado"}, {"valor": "controlar y coordinar entregas con el área de logística", "texto_original": "Controlar y coordinar entregas con el área de logística"}, {"valor": "mantener actualizada la base de datos de clientes, precios y promociones", "texto_original": "Mantener actualizada la base de datos de clientes, precios y promociones"}, {"valor": "realizar el seguimiento de cobranzas en coordinación con el área de administración", "texto_original": "Realizar el seguimiento de cobranzas en coordinación con el área de administración"}, {"valor": "asistir en la preparación de presentaciones comerciales e informes de gestión", "texto_original": "Asistir en la preparación de presentaciones comerciales e informes de gestión"}, {"valor": "colaborar en la implementación de acciones comerciales y campañas de venta", "texto_original": "Colaborar en la implementación de acciones comerciales y campañas de venta"}, {"valor": "gestionar documentación y archivos del área comercial", "texto_original": "Gestionar documentación y archivos del área comercial"}] | S26: 2 | U26: terciario | V26: Administración de Empresas, Comercialización o afines | X26: ["Excel avanzado"] | Y26: ["autonomía y proactividad", "orden y precisión administrativa", "orientación a resultados y al cliente interno", "capacidad analítica y atención al detalle", "trabajo en equipo y comunicación efectiva"] | Z26: ["sistemas de gestión comercial"] | AD26: full_time | AI26: ["Obra Social", "descuentos en productos", "día de cumpleaños"] | AJ26: 1 | AK26: 0 | AM26: demanda_real | AN26: alta | AO26: 0 | AP26: 10.0.0 | AQ26: 6
A27: 1118020225 | B27: → Oferta | C27: → Match | D27: Representante de atención al cliente | E27: Buenos Aires | F27: Munro | G27: hibrido | J27: Servicios Financieros | K27: servicios corporativos B2B y medios de pagos | L27: 0 | M27: Atencion al Cliente | N27: junior | O27: 0 | P27: Brindar un servicio de atención al cliente excepcional | Q27: [{"valor": "manejo de consultas, quejas y solicitudes a través de mails, llamadas telefónicas y mensajes de WhatsApp", "texto_original": "manejo de consultas, quejas y solicitudes a través de mails, llamadas telefónicas y mensajes de WhatsApp"}, {"valor": "Fidelizar al Cliente generando un vínculo duradero en el corto plazo", "texto_original": "Fidelizar al Cliente generando un vínculo duradero en el corto plazo"}, {"valor": "Detectar oportunidades de venta de otras soluciones en el periodo de implementación", "texto_original": "Detectar oportunidades de venta de otras soluciones en el periodo de implementación"}, {"valor": "Colaboración constante con otras áreas para entregar soluciones al cliente", "texto_original": "Colaboración constante con otras áreas para entregar soluciones al cliente"}, {"valor": "Proponer mejoras constantes en los procesos internos", "texto_original": "Proponer mejoras constantes en los procesos internos"}] | S27: 7 | U27: universitario | V27: Lic. en Administración, Comunicación, Comercialización y/o afines | X27: ["herramientas de CRM", "plataformas de mensajería como WhatsApp"] | Y27: ["vocación al cliente", "habilidades interpersonales y de comunicación excepcionales", "habilidades para resolver problemas"] | AA27: ["CRM", "WhatsApp"] | AB27: ingles | AC27: intermedio | AD27: full_time | AI27: ["Prepaga para grupo familiar", "Días habiles de vacaciones", "Día de cumpleaños libre", "Almuerzo Y más!"] | AJ27: 1 | AK27: 0 | AM27: demanda_real | AN27: alta | AO27: 0 | AP27: 10.0.0 | AQ27: 5
A28: 1118003709 | B28: → Oferta | C28: → Match | D28: CAJERO/ENCARGADO | E28: Buenos Aires | F28: Adrogue | G28: presencial | H28: zona o alrededores | J28: Alimentacion | L28: 0 | M28: Operaciones/Logistica | O28: 1 | P28: Manejar las transacciones diarias y coordinar al equipo del turno | Q28: [{"valor": "manejo de transacciones", "texto_original": "Manejando las transacciones diarias"}, {"valor": "arqueo de caja", "texto_original": "Realizar arqueos de caja al inicio y final del turno"}, {"valor": "atencion al cliente", "texto_original": "Brindar una óptima atención al cliente"}, {"valor": "coordinacion equipo", "texto_original": "Coordinar al equipo del turno para garantizar que las operaciones fluyan"}] | S28: 1 | AA28: ["Office", "Excel"] | AD28: full_time | AK28: 0 | AM28: demanda_real | AN28: alta | AO28: 0 | AP28: 10.0.0 | AQ28: 5
A29: 1118017586 | B29: → Oferta | C29: → Match | D29: Médica Clínica o Dermatóloga – Especialista en tratamientos estéticos inyectables | E29: Buenos Aires | F29: Quilmes | G29: presencial | J29: Salud/Farmaceutica | L29: 0 | M29: Salud | N29: semisenior | O29: 0 | P29: Realizar procedimientos inyectables y aplicar tratamientos con tecnología láser | Q29: [{"valor": "realizar procedimientos inyectables", "texto_original": "relleno de labios, ojeras, rinomodelación, Radiesse"}, {"valor": "aplicar tratamientos con tecnología láser", "texto_original": "Nordlys, CO₂"}] | S29: 1 | U29: universitario | W29: Médica Clínica o Dermatóloga | X29: ["tratamientos con tecnología láser"] | Y29: ["excelente trato interpersonal", "orientación al paciente"] | AA29: ["Ultraformer/HIFU"] | AD29: part_time | AI29: ["integración a un equipo de profesionales", "oportunidad de desarrollo profesional y crecimiento dentro de la clínica", "ambiente de trabajo profesional y ameno"] | AK29: 0 | AM29: demanda_real | AN29: alta | AO29: 0 | AP29: 10.0.0 | AQ29: 6
A30: 1118025956 | B30: → Oferta | C30: → Match | D30: Jardinero | G30: presencial | L30: 0 | M30: Operaciones/Logistica | N30: junior | O30: 0 | P30: Realizar el corte y mantenimiento del césped | Q30: [{"valor": "cuidado general de plantas y flores", "texto_original": "cuidado general de plantas y flores"}, {"valor": "mantener el orden y la limpieza de las áreas verdes", "texto_original": "mantener el orden y la limpieza de las áreas verdes"}] | S30: 1 | AD30: full_time | AK30: 1 | AM30: demanda_real | AN30: media | AO30: 0 | AP30: 10.0.0 | AQ30: 6
A31: 2164100 | B31: → Oferta | C31: → Match | D31: Mozo/Moza | E31: Mendoza | F31: Valle de Uco, Tunuyán | G31: presencial | H31: Tunuyán o zonas cercanas | J31: Turismo/Hospitalidad | L31: 0 | M31: Atencion al Cliente | N31: junior | O31: 0 | P31: Ser parte de un equipo que brinda experiencias de primer nivel a nuestros huéspedes | R31: ["servicio en salones", "atención al detalle"] | S31: 1 | Y31: ["vocación de servicio", "actitud cordial"] | AB31: ingles | AC31: avanzado | AD31: full_time | AI31: ["entorno de trabajo profesional y dinámico", "oportunidades de crecimiento"] | AK31: 0 | AM31: demanda_real | AN31: alta | AO31: 0 | AP31: 10.0.0 | AQ31: 5
A32: 2165052 | B32: → Oferta | C32: → Match | D32: Electricista Industrial | L32: 0 | M32: Operaciones/Logistica | N32: semisenior | O32: 0 | P32: Realizar el mantenimiento preventivo y correctivo de equipos e instalaciones eléctricas | Q32: [{"valor": "Interpretar planos unifilares eléctricos", "texto_original": "Interpretar planos unifilares eléctricos"}, {"valor": "Dimensionar instalaciones eléctricas y selectividades", "texto_original": "Dimensionar instalaciones eléctricas y selectividades"}, {"valor": "Montar canalizaciones eléctricas", "texto_original": "Montar canalizaciones eléctricas"}, {"valor": "Diseñar y armar tableros eléctricos de control y potencia", "texto_original": "Diseñar y armar tableros eléctricos de control y potencia"}] | S32: 1 | U32: secundario | X32: ["mantenimiento preventivo y correctivo", "interpretación de planos eléctricos", "dimensionamiento de instalaciones eléctricas", "montaje de canalizaciones eléctricas", "diseño y armado de tableros eléctricos"] | AK32: 0 | AM32: demanda_real | AN32: media | AO32: 0 | AP32: 10.0.0 | AQ32: 5
A33: 2165301 | B33: → Oferta | C33: → Match | D33: Supervisor/a Administración Autos usados | E33: Buenos Aires | F33: Tortuguitas | G33: presencial | J33: Automotriz | L33: 0 | M33: Administracion/Finanzas | N33: semisenior | O33: 1 | P33: Liderar equipos administrativos y asegurar el cumplimiento de plazos para la disponibilidad de las unidades | Q33: [{"valor": "optimizar los procesos para reducir costos operativos", "texto_original": "optimizar los procesos para reducir costos operativos"}, {"valor": "garantizar una administración ordenada y resultados medibles", "texto_original": "garantizar una administración ordenada y resultados medibles"}] | S33: 1 | U33: secundario | X33: ["manejo avanzado de paquete Office"] | Y33: ["habilidad en liderazgo y coordinación de equipos"] | AD33: full_time | AK33: 0 | AM33: demanda_real | AN33: alta | AO33: 0 | AP33: 10.0.0 | AQ33: 6
A34: 1116898892 | B34: → Oferta | C34: → Match | D34: Chofer - Repartidor | E34: Buenos Aires | F34: Benavidez | G34: presencial | J34: Alimentacion | L34: 0 | M34: Operaciones/Logistica | O34: 0 | P34: Realizar entregas de productos y mantener el vehículo en óptimas condiciones | Q34: [{"valor": "verificación de los pedidos", "texto_original": "Verificación de los pedidos para asegurar la correcta entrega según lo solicitado"}, {"valor": "mantener el vehículo en óptimas condiciones", "texto_original": "Mantener el vehiculo en óptimas condiciones, tanto a nivel mecánico como de limpieza"}, {"valor": "reportar cualquier inconveniente relacionado con el vehículo o las entregas", "texto_original": "Reportar cualquier inconveniente relacionado con el vehiculo o las entregas"}, {"valor": "colaborar con el equipo logístico para coordinar rutas y tiempos de entrega", "texto_original": "Colaborar con el equipo logístico para coordinar rutas y tiempos de entrega de manera eficiente"}] | S34: 2 | X34: ["mantenimiento y cuidado de vehículos"] | Y34: ["actitud responsable", "puntualidad", "capacidad para gestionar las entregas de manera eficiente y autónoma"] | AD34: full_time | AK34: 1 | AM34: demanda_real | AN34: alta | AO34: 0 | AP34: 10.0.0 | AQ34: 5
A35: 1118023904 | B35: → Oferta | C35: → Match | D35: Operario Picking | E35: Buenos Aires | F35: ["Escobar", "El Talar", "Pilar"] | G35: presencial | H35: Zona Norte de Buenos Aires | J35: Transporte/Logistica | L35: 0 | M35: Operaciones/Logistica | N35: junior | O35: 0 | P35: Operario y Pickeador en operaciones logísticas | Q35: [{"valor": "picking con RF", "texto_original": "* Picking con RF"}, {"valor": "carga y descarga de camiones", "texto_original": "* Carga y descarga de camiones."}, {"valor": "conteo de productos", "texto_original": "* Conteo de productos"}, {"valor": "armado de pedidos", "texto_original": "* Armado de pedidos"}] | S35: 20 | T35: 45 | U35: secundario | AA35: ["RF"] | AD35: full_time | AE35: eventual | AK35: 0 | AM35: demanda_real | AN35: media | AO35: 1 | AP35: 10.0.0 | AQ35: 5
A36: 1117980907 | B36: → Oferta | C36: → Match | D36: Operario de Almacén/Logística | E36: Buenos Aires | F36: Escobar | G36: presencial | H36: cerca de Escobar | J36: Manufactura/Industria | K36: Metalúrgica | L36: 0 | M36: Operaciones/Logistica | N36: junior | O36: 0 | P36: Operario de almacén /logística | Q36: [{"valor": "Recepción y verificación de mercadería", "texto_original": "Recepción y verificación de mercadería"}, {"valor": "Almacenamiento y organización de productos", "texto_original": "Almacenamiento y organización de productos"}, {"valor": "Preparación de pedidos y despacho de mercadería", "texto_original": "Preparación de pedidos y despacho de mercadería"}, {"valor": "Control de inventario y registro en sistema", "texto_original": "Control de Inventario"}] | S36: 1 | U36: secundario | AD36: full_time | AK36: 0 | AM36: demanda_real | AN36: alta | AO36: 0 | AP36: 10.0.0 | AQ36: 6
A37: 1117990944 | B37: → Oferta | C37: → Match | D37: Repositor/a Externo/a (Eventual) Moreno | E37: Buenos Aires | F37: Moreno | G37: presencial | H37: zonas cercanas | J37: Retail/Comercio | L37: 0 | M37: Operaciones/Logistica | N37: junior | O37: 0 | P37: Repositor externo en PDV | Q37: [{"valor": "Limpieza de góndola y control de fechas de vencimiento", "texto_original": "-Limpieza de góndola y control de fechas de vencimiento"}, {"valor": "Reposición de los productos asignados", "texto_original": "-Reposición de los productos asignados"}, {"valor": "Mantener abastecidos y en orden los freezers y las góndolas de los PDV", "texto_original": "-Mantener abastecidos y en orden los freezers y las góndolas de los PDV"}, {"valor": "Armado de exhibiciones primaria (góndola) según Planogramas", "texto_original": "-Armado de exhibiciones primaria (góndola) según Planogramas"}, {"valor": "Colocación y seguimiento del material POP", "texto_original": "-Colocación y seguimiento del material POP"}, {"valor": "Control de ofertas y precios, además de la colocación de carteles", "texto_original": "-Control de ofertas y precios, además de la colocación de carteles"}, {"valor": "Control quiebres y falsos stocks", "texto_original": "-Controlas quiebres y falsos stocks"}, {"valor": "Control de mermas y de Calidad", "texto_original": "-Control de mermas y de Calidad"}] | S37: 1 | U37: secundario | AD37: full_time | AE37: eventual | AK37: 0 | AM37: demanda_real | AN37: alta | AO37: 0 | AP37: 10.0.0 | AQ37: 6
A38: 1117961954 | B38: → Oferta | C38: → Match | D38: Asistente Administrativo General | L38: 0 | M38: Administracion/Finanzas | N38: junior | P38: Brindar soporte administrativo a varios departamentos | Q38: [{"valor": "Gestionar y organizar documentos y archivos", "texto_original": "Gestionar y organizar documentos y archivos"}, {"valor": "Coordinar reuniones y eventos", "texto_original": "Coordinar reuniones y eventos"}, {"valor": "Preparar informes y presentaciones", "texto_original": "Preparar informes y presentaciones"}, {"valor": "Realizar tareas de contabilidad básica", "texto_original": "Realizar tareas de contabilidad básica"}] | S38: 1 | X38: ["Microsoft Office Suite"] | Y38: ["proactiva", "organizada"] | AA38: ["Word", "Excel", "PowerPoint"] | AK38: 0 | AM38: demanda_real | AN38: media | AO38: 0 | AP38: 10.0.0 | AQ38: 6
A39: 1117982053 | B39: → Oferta | C39: → Match | D39: Desarrollador Angular Senior | G39: remoto | I39: 0 | J39: Tecnologia/Software | L39: 0 | M39: IT/Sistemas | N39: senior | O39: 1 | P39: Desarrollador Angular Senior | Q39: [{"valor": "desarrollar, mantener y escalar funcionalidades del CX Portal", "texto_original": "Desarrollar, mantener y escalar funcionalidades del CX Portal con enfoque en rendimiento, reutilización y sostenibilidad"}, {"valor": "liderar la integración de Module Federation y Lazy Loading", "texto_original": "Liderar la integración de Module Federation y la implementación de técnicas de Lazy Loading"}, {"valor": "guiar al equipo en la optimización de Webpack", "texto_original": "Guiar al equipo en la optimización de Webpack y mejora continua de la experiencia del usuario"}] | R39: [{"valor": "participar en el despliegue y monitoreo en AWS", "texto_original": null}, {"valor": "velar por la eficiencia técnica del sistema", "texto_original": null}] | S39: 4 | U39: terciario | X39: ["Angular", "Webpack"] | Z39: ["AWS", "CloudFront", "CloudFormation"] | AD39: full_time | AI39: ["flexibilidad", "regalos y descuentos", "diversion", "formacion y capacitaciones"] | AK39: 0 | AM39: demanda_real | AN39: alta | AO39: 0 | AP39: 10.0.0 | AQ39: 6
A40: 1118018461 | B40: → Oferta | C40: → Match | D40: Asesor/a de Admisiones | E40: CABA | G40: hibrido | J40: Educacion | L40: 0 | M40: Administracion/Finanzas | N40: junior | O40: 0 | P40: Acompañar a los postulantes en su proceso de admisión y asesorarlos en la elección de carrera | Q40: [{"valor": "asesoramiento personalizado", "texto_original": "acompañar a los postulantes en el proceso de elección de su carrera"}, {"valor": "charlas grupales sobre admisión y programas académicos", "texto_original": "dar charlas grupales sobre el proceso de admisión, los programas académicos y las oportunidades que ofrece la universidad"}, {"valor": "atención a consultas por mail, WhatsApp y teléfono", "texto_original": "responder consultas por mail, WhatsApp y teléfono; resolver inquietudes de potenciales alumnos y sus familias"}, {"valor": "gestión de actividades y eventos", "texto_original": "coordinar y participar en eventos para comunicar las carreras y oportunidades que brinda la universidad"}, {"valor": "viajes al interior del país", "texto_original": "viajar al interior del país para visitar escuelas, mantener contacto con autoridades educativas, dar charlas a estudiantes y generar vínculos con potenciales interesados"}, {"valor": "gestión administrativa en CRM de Admisiones", "texto_original": "actualizar el CRM de Admisiones, coordinar el curso de ingreso y procesar aplicaciones de postulantes"}] | S40: 0 | X40: ["paquete Office", "herramientas de Google"] | Y40: ["dinámica", "proactiva", "resolutiva", "vocación de servicio", "atenta a los detalles", "excelente comunicación oral y escrita"] | AD40: full_time | AK40: 0 | AM40: demanda_real | AN40: alta | AO40: 0 | AP40: 10.0.0 | AQ40: 4
A41: 1118018714 | B41: → Oferta | C41: → Match | D41: Diseñador Gráfico E-commerce | J41: Tecnologia/Software | L41: 0 | M41: Marketing | P41: Responsable de mejorar la presentación visual de los productos en plataformas de e-commerce | Q41: [{"valor": "Crear y editar contenido visual para publicaciones de productos", "texto_original": "Crear y editar contenido visual para publicaciones de productos en plataformas de e-commerce"}, {"valor": "Optimizar títulos y descripciones de productos", "texto_original": "Optimizar títulos y descripciones de productos para mejorar el SEO y la conversión"}, {"valor": "Asegurar que las imágenes sean de alta calidad", "texto_original": "Asegurar que las imágenes de los productos sean de alta calidad y representen fielmente el producto"}, {"valor": "Gestionar y actualizar publicaciones existentes", "texto_original": "Gestionar y actualizar publicaciones existentes para mantener la información precisa y relevante"}] | R41: [{"valor": "Colaborar con otros equipos en estrategias de marketing visual", "texto_original": "Colaborar con otros equipos para desarrollar estrategias de marketing visual efectivas"}] | S41: 1 | X41: ["Photoshop", "Illustrator"] | Y41: ["creativo"] | AA41: ["Photoshop", "Illustrator"] | AK41: 0 | AM41: demanda_real | AN41: alta | AO41: 0 | AP41: 10.0.0 | AQ41: 5
A42: 1118031991 | B42: → Oferta | C42: → Match | G42: remoto | J42: Retail/Comercio | L42: 0 | M42: Ventas/Comercial | N42: junior | O42: 0 | P42: Promocionar y vender productos de cocina de alta gama relacionados con la salud | Q42: [{"valor": "vender a clientes potenciales", "texto_original": "promocionar y vender nuestros productos/servicios"}] | S42: 1 | Y42: ["trabajo en equipo"] | AD42: full_time | AI42: ["flexibilidad"] | AK42: 0 | AM42: demanda_real | AN42: media | AO42: 0 | AP42: 10.0.0
A43: 1116884561 | B43: → Oferta | C43: → Match | E43: Buenos Aires | G43: presencial | J43: Retail/Comercio | L43: 1 | M43: Ventas/Comercial | N43: junior | P43: Atención/fidelización de la cartera de clientes actuales y captación de nuevos clientes para incrementar los revenues en la cartera existente | Q43: [{"valor": "atención/gestión de requerimientos/reclamos de los clientes", "texto_original": "Atención/gestión de requerimientos/reclamos de los clientes"}, {"valor": "promoción de productos y presentaciones con los clientes", "texto_original": "Promoción de productos y presentaciones con los clientes"}, {"valor": "monitoreo y anticipación de situaciones del mercado en cuanto a novedades/tendencia/problemáticas que impacten en un resultado positivo comercial", "texto_original": "Monitoreo y anticipación de situaciones del mercado en cuanto a novedades/tendencia/problemáticas que impacten en un resultado positivo comercial"}, {"valor": "cobranza mensual, conciliación de cuentas de clientes con el área financiera de la empresa", "texto_original": "Cobranza mensual, conciliación de cuentas de clientes con el área financiera de la empresa"}] | S43: 0 | T43: 2 | V43: al siguiente nivel | Y43: ["negociación", "planificación, organización y coordinación", "capacidad analítica", "trabajo en equipo y buenas relaciones interpersonales", "comunicación asertiva", "adaptación"] | AB43: ingles | AC43: basico | AD43: full_time | AI43: ["contratación inmediata y directa con la empresa", "prepaga"] | AJ43: 1 | AK43: 1 | AM43: demanda_real | AN43: alta | AO43: 0 | AP43: 10.0.0
A44: 1117995368 | B44: → Oferta | C44: → Match | D44: ASESOR TÉCNICO NUTRICIÓN ANIMAL RUMIANTES | E44: Buenos Aires | G44: presencial | H44: zonas centro del país (provincia de Buenos Aires, Santa Fe, Córdoba o Entre Ríos) | J44: Salud/Farmaceutica | K44: Nutrición Animal | L44: 0 | M44: Salud | N44: senior | O44: 0 | P44: Asesor Técnico con comprobada experiencia en rumiantes | Q44: [{"valor": "conocer en profundidad todos los productos para rumiantes", "texto_original": "para conocer en profundidad todos los productos para rumiantes, clientes y posibilidades de desarrollo futuro"}] | S44: 7 | U44: universitario | V44: ["Ingeniero Zootecnista", "Ingeniero Agrónomo", "Veterinario"] | Y44: ["disposición para viajar"] | AD44: full_time | AK44: 0 | AM44: demanda_real | AN44: alta | AO44: 0 | AP44: 10.0.0 | AQ44: 5
A45: 2170124 | B45: → Oferta | C45: → Match | E45: Buenos Aires | F45: Roque Pérez | G45: presencial | H45: Roque Pérez o zonas aledañas | I45: 0 | J45: Manufactura/Industria | K45: agroindustrial | L45: 0 | M45: Operaciones/Logistica | N45: junior | O45: 0 | P45: Analista de Cultivo | Q45: [{"valor": "control, registro y seguimiento de los cultivos", "texto_original": "Realizar el control, registro y seguimiento de los cultivos"}, {"valor": "identificar y gestionar problemas relacionados con malezas, insectos y enfermedades", "texto_original": "Identificar y gestionar problemas relacionados con malezas, insectos y enfermedades"}, {"valor": "garantizar el desarrollo óptimo del cultivo y maximizar los rendimientos esperados", "texto_original": "Garantizar el desarrollo óptimo del cultivo y maximizar los rendimientos esperados"}, {"valor": "asegurar la correcta ejecución de siembras, cosechas y pulverizaciones", "texto_original": "Asegurar la correcta ejecución de siembras, cosechas y pulverizaciones"}, {"valor": "realizar mediciones de suelos y niveles de agua", "texto_original": "Realizar mediciones de suelos y niveles de agua"}, {"valor": "controlar el correcto funcionamiento de las maquinarias", "texto_original": "Controlar el correcto funcionamiento de las maquinarias"}, {"valor": "colaborar en la gestión de sistemas de información geográfica, así como en la creación, actualización y mantenimiento de los mapas detallados de cosecha y siembra", "texto_original": "Colaborar en la gestión de sistemas de información geográfica, así como en la creación, actualización y mantenimiento de los mapas detallados de cosecha y siembra"}, {"valor": "desempeñar tareas administrativas varias, como generación de informes y reportes", "texto_original": "Desempeñar tareas administrativas varias, como generación de informes y reportes"}] | S45: 7 | U45: universitario | V45: secundario Técnico agropecuario | X45: ["SAP/Cencerro", "SIMA", "Paquete Office"] | AD45: full_time | AI45: ["Prepaga para vos y tu grupo familiar", "Días adicionales de vacaciones", "Posibilidad de acceso a alojamiento"] | AJ45: 1 | AK45: 1 | AM45: demanda_real | AN45: alta | AO45: 0 | AP45: 10.0.0
A46: 1117975249 | B46: → Oferta | C46: → Match | D46: Gerente General para Maderera | E46: Buenos Aires | F46: ["San Martín", "CABA", "Luján"] | G46: presencial | I46: 1 | J46: Manufactura/Industria | K46: maderera | L46: 0 | M46: Operaciones/Logistica | N46: lead/manager | O46: 1 | P46: Liderar y supervisar la gestión integral de la empresa | Q46: [{"valor": "supervisar el funcionamiento de las tres sucursales", "texto_original": "Supervisar el funcionamiento de las tres sucursales"}, {"valor": "coordinar y dirigir áreas de logística, depósitos y operaciones comerciales", "texto_original": "Coordinar y dirigir las áreas de logística, depósitos y operaciones comerciales"}, {"valor": "impulsar el cumplimiento de objetivos", "texto_original": "Liderar y acompañar a los equipos de trabajo, impulsando el cumplimiento de objetivos"}, {"valor": "resolver incidencias operativas", "texto_original": "Resolver incidencias operativas"}, {"valor": "implementar y controlar procesos de mejora continua", "texto_original": "Implementar y controlar procesos de mejora continua"}, {"valor": "analizar indicadores de gestión y elaborar reportes de resultados", "texto_original": "Analizar indicadores de gestión y elaborar reportes de resultados"}, {"valor": "velar por la rentabilidad y el cumplimiento de los estándares de calidad", "texto_original": "Velar por la rentabilidad y el cumplimiento de los estándares de calidad"}, {"valor": "representar a la empresa ante proveedores y clientes estratégicos", "texto_original": "Representar a la empresa ante proveedores y clientes estratégicos"}] | S46: 10 | Y46: ["visión estratégica", "capacidad de organización"] | AD46: full_time | AE46: indeterminado | AK46: 0 | AM46: demanda_real | AN46: alta | AO46: 0 | AP46: 10.0.0 | AQ46: 5
A47: 1118028777 | B47: → Oferta | C47: → Match | L47: 0 | M47: Ventas/Comercial | N47: junior | O47: 0 | P47: Gestionar y ampliar cartera de clientes | Q47: [{"valor": "promover y vender productos", "texto_original": "Promover y vender productos de la compañía"}, {"valor": "realizar seguimiento de ventas y cobranzas", "texto_original": "Realizar seguimiento de las ventas y cobranzas"}, {"valor": "cumplir con objetivos de venta", "texto_original": "Cumplir con los objetivos de venta establecidos"}] | S47: 1 | Y47: ["habilidades de comunicación", "negociación"] | AD47: full_time | AI47: ["oportunidad de crecimiento profesional", "excelente ambiente de trabajo"] | AK47: 0 | AM47: demanda_real | AN47: media | AO47: 0 | AP47: 10.0.0
A48: 1117977340 | B48: → Oferta | C48: → Match | E48: CABA | F48: Palermo | G48: hibrido | J48: Servicios Financieros | K48: contabilidad | L48: 0 | M48: Administracion/Finanzas | N48: junior | O48: 0 | P48: Dar asistencia a los socios y a la responsable de administración en tareas variadas | Q48: [{"valor": "Realizar las cobranzas del estudio", "texto_original": "Realizar las cobranzas del estudio (análisis de ingresos, solicitud de retenciones, llamados a los clientes para seguimiento de pagos, armado de informes de cobranzas)"}, {"valor": "Dar de alta de proveedores y facturas en Tango", "texto_original": "Dar de alta de proveedores y facturas en Tango."}, {"valor": "Suplir las licencias de la responsable de administración", "texto_original": "Suplir las licencias de la responsable de administración en tareas de pagos a proveedores, servicios e impuestos"}, {"valor": "Realizar certificaciones on line en el CPCE CABA", "texto_original": "Realizar certificaciones on line en el CPCE CABA"}, {"valor": "Recepción de personas y correspondencia", "texto_original": "Realizar la recepción de personas y correspondencia."}, {"valor": "Compras de oficina", "texto_original": "Realizar las compras de oficina (insumos de librería, cocina, limpieza) en función del stock"}, {"valor": "Soporte en administración de personal", "texto_original": "Dar soporte en administración de personal (turnos médicos y psicotécnicos, alta de obra social, alta bancaria, ART, búsqueda de documentación para legajo)"}, {"valor": "Postear novedades en RRSS y distribuir el newsletter mensual interno", "texto_original": "Postear novedades en RRSS y distribuir el newsletter mensual interno"}, {"valor": "Organización de festejos o reuniones internas", "texto_original": "Contribuir a la organización de festejos o reuniones internas (almuerzos, cumpleaños, capacitaciones, etc.)"}, {"valor": "Asistencia a los socios en temas generales", "texto_original": "Asistir a los socios en temas generales"}] | S48: 0 | X48: ["Tango"] | Y48: ["proactivo"] | AA48: ["Tango"] | AB48: ingles | AC48: intermedio | AD48: full_time | AI48: ["empleo formal"] | AK48: 0 | AM48: demanda_real | AN48: alta | AO48: 0 | AP48: 10.0.0
A49: 1118028048 | B49: → Oferta | C49: → Match | G49: presencial | J49: Retail/Comercio | L49: 0 | M49: Ventas/Comercial | N49: junior | O49: 0 | P49: Atender y asesorar a los clientes, ofreciendo un servicio personalizado y de alta calidad | Q49: [{"valor": "promocionar y vender productos", "texto_original": "Promocionar y vender productos"}, {"valor": "mantener el espacio de trabajo limpio y ordenado", "texto_original": "Mantener el espacio de trabajo limpio y ordenado"}, {"valor": "resolver consultas y reclamos de los clientes", "texto_original": "Resolver consultas y reclamos de los clientes"}] | S49: 1 | X49: ["POS"] | Y49: ["proactividad", "adaptabilidad", "sociabilidad natural", "empatía", "autoconfianza"] | AD49: full_time | AK49: 0 | AM49: demanda_real | AN49: alta | AO49: 0 | AP49: 10.0.0
A50: 1118009703 | B50: → Oferta | C50: → Match | D50: Asesor Comercial E Commerce - Manager de redes sociales | E50: CABA | G50: presencial | H50: cerca de CABA | J50: Servicios | K50: Servicios Corporativos | L50: 0 | M50: Ventas/Comercial | N50: lead/manager | O50: 0 | P50: Asesoramiento comercial y manejo de ventas | Q50: [{"valor": "asesoramiento comercial a prospectos y emprendedores", "texto_original": "asesoramiento comercial a prospectos y emprendedores"}, {"valor": "manejo de venta de máquinas automatizadas o tecnología de producción", "texto_original": "manejo de venta de máquinas automatizadas o tecnología de producción"}, {"valor": "creación y actualización de anuncios en e-commerce", "texto_original": "creación y actualización de anuncios en e-commerce"}, {"valor": "creación de diseños e iniciativas comerciales para redes sociales, crosselling y promociones", "texto_original": "creación de diseños e iniciativas comerciales para redes sociales, crosselling y promociones"}, {"valor": "armado de diseños personalizados para clientes o prospectos", "texto_original": "armado de diseños personalizados para clientes o prospectos"}, {"valor": "supervisión a la agencia de marketing digital en cuanto a funcionamiento de campañas (Meta y Google Adwords), mailing, creación de contenido y sitio web", "texto_original": "supervisión a la agencia de marketing digital en cuanto a funcionamiento de campañas (Meta y Google Adwords), mailing, creación de contenido y sitio web"}, {"valor": "manejo de CRM y sistemas de gestión", "texto_original": "manejo de CRM y sistemas de gestión"}] | S50: 10 | X50: ["Paquete Office", "CRM Hubspot", "Photoshop o afín", "Canva o afín"] | Y50: ["Manejo de prioridades, tiempos y seguimientos", "Manejo de presupuestos", "Toleración a la presión del resultado y medición por objetivos", "Adaptabilidad y flexibilidad", "Trabajo en equipo y colaboración"] | AA50: ["Mercado Libre", "Tienda web y Market Place", "Meta y Google Adwords"] | AD50: full_time | AI50: ["Entorno laboral dinámico y motivador", "Formar parte de un equipo sólido y con trayectoria en el mercado", "Formación y capacitaciones constantes"] | AK50: 0 | AM50: demanda_real | AN50: alta | AO50: 1 | AP50: 10.0.0 | AQ50: 5

Sheet 02_NLP_Extraccion (2)
A1: ID | B1: → Oferta | C1: → Match | D1: titulo_limpio | E1: provincia | F1: localidad | G1: modalidad | H1: zona_residencia_req | I1: requiere_movilidad_propia | J1: sector_empresa | K1: rubro_empresa | L1: es_tercerizado | M1: area_funcional | N1: nivel_seniority | O1: tiene_gente_cargo | P1: mision_rol | Q1: tareas_explicitas | R1: tareas_inferidas | S1: experiencia_min_anios | T1: experiencia_max_anios | U1: nivel_educativo | V1: carrera_especifica | W1: titulo_requerido | X1: skills_tecnicas_list | Y1: soft_skills_list | Z1: tecnologias_list | AA1: herramientas_list | AB1: idioma_principal | AC1: nivel_idioma_principal | AD1: jornada_laboral | AE1: tipo_contrato | AF1: salario_min | AG1: salario_max | AH1: moneda | AI1: beneficios_list | AJ1: tiene_cobertura_salud | AK1: licencia_conducir | AL1: tipo_licencia | AM1: tipo_oferta | AN1: calidad_texto | AO1: tiene_requisitos_discriminatorios | AP1: nlp_version | AQ1: nlp_confidence_score
A2: 1118026700 | B2: → Oferta | C2: → Match | D2: TRUE | E2: FALSO Capital Federal | F2: TRUE | G2: TRUE | H2: TRUE | I2: TRUE | J2: TRUE | K2: TRUE | L2: TRUE | M2: TRUE | N2: TRUE | O2: TRUE | P2: TRUE | Q2: TRUE | R2: TRUE | S2: TRUE | T2: TRUE | U2: TRUE | V2: TRUE | W2: TRUE | X2: FALSO ["conocimiento EXCLUYENTE en mecánica y repuestos de autos","paquete office", "canales de venta online", "computación en general"] | Y2: TRUE | Z2: FALSO ["manejo básico o intermedio de paquete oficce","computación en general"] | AA2: TRUE | AB2: TRUE | AC2: TRUE | AD2: TRUE | AE2: TRUE | AF2: TRUE | AG2: TRUE | AH2: TRUE | AI2: TRUE | AJ2: TRUE | AK2: TRUE | AL2: TRUE | AM2: TRUE | AN2: TRUE | AO2: TRUE | AP2: 10.0.0 | AQ2: 6 | AT2: ["paquete office", "canales de venta online", "computación en general"]
A3: 1118026729 | B3: → Oferta | C3: → Match | D3: TRUE | E3: FALSO Capital Federal | F3: FALSE | G3: TRUE | H3: TRUE | I3: TRUE | J3: TRUE | K3: TRUE | L3: TRUE | M3: TRUE | N3: TRUE | O3: TRUE | P3: TRUE | Q3: TRUE | R3: TRUE | S3: TRUE | T3: TRUE | U3: TRUE | V3: TRUE | W3: TRUE | X3: TRUE | Y3: TRUE | Z3: TRUE | AA3: TRUE | AB3: TRUE | AC3: TRUE | AD3: TRUE | AE3: TRUE | AF3: TRUE | AG3: TRUE | AH3: TRUE | AI3: TRUE | AJ3: TRUE | AK3: TRUE | AL3: TRUE | AM3: TRUE | AN3: TRUE | AO3: TRUE | AP3: 10.0.0 | AQ3: 6
A4: 1118027243 | B4: → Oferta | C4: → Match | D4: TRUE | E4: TRUE | F4: TRUE | G4: TRUE | H4: TRUE | I4: TRUE | J4: TRUE | K4: TRUE | L4: TRUE | M4: TRUE | N4: FALSE | O4: TRUE | P4: FALSO ["Abogado/a para el Departamento de Impuestos de Estudio Jurídico de primera línea"] | Q4: TRUE | R4: TRUE | S4: TRUE | T4: TRUE | U4: TRUE | V4: TRUE | W4: TRUE | X4: TRUE | Y4: TRUE | Z4: TRUE | AA4: TRUE | AB4: TRUE | AC4: TRUE | AD4: TRUE | AE4: TRUE | AF4: TRUE | AG4: TRUE | AH4: TRUE | AI4: TRUE | AJ4: TRUE | AK4: TRUE | AL4: TRUE | AM4: demanda_real | AN4: alta | AO4: 0 | AP4: 10.0.0 | AQ4: 6
A5: 1118027261 | B5: → Oferta | C5: → Match | D5: TRUE | E5: TRUE | F5: TRUE | G5: TRUE | H5: TRUE | I5: TRUE | J5: TRUE | K5: TRUE | L5: TRUE | M5: TRUE | N5: TRUE | O5: TRUE | P5: TRUE | Q5: TRUE | R5: TRUE | S5: TRUE | T5: TRUE | U5: TRUE | V5: TRUE | W5: TRUE | X5: TRUE | Y5: TRUE | Z5: TRUE | AA5: TRUE | AB5: TRUE | AC5: TRUE | AD5: TRUE | AE5: TRUE | AF5: TRUE | AG5: TRUE | AH5: TRUE | AI5: TRUE | AJ5: TRUE | AK5: TRUE | AL5: TRUE | AM5: demanda_real | AN5: alta | AO5: 0 | AP5: 10.0.0 | AQ5: 6
A6: 1118027276 | B6: → Oferta | C6: → Match | D6: TRUE | E6: TRUE | F6: TRUE | G6: TRUE | H6: TRUE | I6: TRUE | J6: TRUE | K6: FALSO Rubro Electrico industrial | L6: TRUE | M6: TRUE | N6: TRUE | O6: TRUE | P6: FALSO ["captar y desarrollar cuentas industriales medianas y grandes, impulsando ventas técnicas consultivas de productos y servicios críticos de energía (UPS, baterías, estabilizadores, rectificadores, grupos electrógenos) y obras eléctricas industriales y de puesta a tierra. El rol combina prospección activa (hunter) con seguimiento y expansión de cuentas (farmer), dentro de una gestión comercial estructurada con CRM"] | Q6: TRUE | R6: TRUE | S6: TRUE | T6: TRUE | U6: TRUE | V6: TRUE | W6: TRUE | X6: FALSO ["Más de 3 años de experiencia comercial comprobable en venta técnica B2B", "Experiencia en industrias y conocimiento de sus dinámicas de compra", "Perfil hunter, con energía y autonomía para salir a buscar negocio", "Buen manejo de CRM (ideal si usó Táctica Soft o similar)", "Capacidad de redacción técnica y presentación a clientes","Conocimientos básicos de sistemas eléctricos, energía y obras eléctricas y de PAT Formación técnica (electromecánica, electrónica, electricidad, etc.)","Se valorará contar con experiencia en empresas de servicios técnicos o en instalaciones/obras eléctricas, así como experiencia en la gestión de negocios a largo plazo"] | Y6: TRUE | Z6: TRUE | AA6: TRUE | AB6: TRUE | AC6: TRUE | AD6: TRUE | AE6: TRUE | AF6: TRUE | AG6: TRUE | AH6: TRUE | AI6: TRUE | AJ6: TRUE | AK6: TRUE | AL6: TRUE | AM6: demanda_real | AN6: alta | AO6: 0 | AP6: 10.0.0 | AQ6: 6
A7: 1118027662 | B7: → Oferta | C7: → Match | D7: TRUE | E7: TRUE | F7: TRUE | G7: TRUE | H7: TRUE | I7: TRUE | J7: TRUE | K7: TRUE | L7: TRUE | M7: TRUE | N7: FALSE | O7: TRUE | P7: TRUE | Q7: TRUE | R7: TRUE | S7: TRUE | T7: TRUE | U7: TRUE | V7: TRUE | W7: TRUE | X7: TRUE | Y7: TRUE | Z7: TRUE | AA7: TRUE | AB7: TRUE | AC7: TRUE | AD7: TRUE | AE7: TRUE | AF7: TRUE | AG7: TRUE | AH7: TRUE | AI7: TRUE | AJ7: TRUE | AK7: TRUE | AL7: TRUE | AM7: demanda_real | AN7: alta | AO7: 0 | AP7: 10.0.0 | AQ7: 4
A8: 1118027834 | B8: → Oferta | C8: → Match | D8: TRUE | E8: TRUE | F8: FALSO Lomas de Zamora | G8: TRUE | H8: TRUE | I8: TRUE | J8: FALSO Metalurgica | K8: TRUE | L8: TRUE | M8: TRUE | N8: TRUE | O8: TRUE | P8: TRUE | Q8: TRUE | R8: TRUE | S8: TRUE | T8: TRUE | U8: TRUE | V8: TRUE | W8: TRUE | X8: FALSO ["Experiencia en atención al cliente o ventas digitales", "herramientas informáticas", "sistema CRM"] | Y8: TRUE | Z8: TRUE | AA8: TRUE | AB8: TRUE | AC8: TRUE | AD8: TRUE | AE8: TRUE | AF8: TRUE | AG8: TRUE | AH8: TRUE | AI8: TRUE | AJ8: TRUE | AK8: TRUE | AL8: TRUE | AM8: demanda_real | AN8: alta | AO8: 0 | AP8: 10.0.0 | AQ8: 5
A9: 1118027941 | B9: → Oferta | C9: → Match | D9: TRUE | E9: FALSO Buenos Aires | F9: FALSO Lomas del Mirador | G9: FALSE | H9: FALSE | I9: FALSE | J9: TRUE | K9: TRUE | L9: TRUE | M9: Diseño y desarrollo | N9: FALSE | O9: TRUE | P9: FALSO Realización de planos de piezas propias y relevamiento de piezas varias | Q9: TRUE | R9: TRUE | S9: TRUE | T9: TRUE | U9: TRUE | V9: TRUE | W9: TRUE | X9: TRUE | Y9: TRUE | Z9: TRUE | AA9: TRUE | AB9: TRUE | AC9: TRUE | AD9: TRUE | AE9: TRUE | AF9: TRUE | AG9: TRUE | AH9: TRUE | AI9: TRUE | AJ9: TRUE | AK9: TRUE | AL9: TRUE | AM9: demanda_real | AN9: media | AO9: 0 | AP9: 10.0.0 | AQ9: 5
A10: 1118028027 | B10: → Oferta | C10: → Match | D10: OPERADOR DE AUTOELEVADORES | E10: Buenos Aires | F10: Villa Luzuriaga | G10: presencial | J10: Transporte/Logistica | L10: 0 | M10: Operaciones/Logistica | N10: junior | O10: 0 | P10: Operador de autoelevadores | R10: ["manejo de autoelevadores", "trabajo en logistica"] | S10: 0 | U10: secundario | AD10: full_time | AK10: 1 | AL10: O | AM10: demanda_real | AN10: media | AO10: 0 | AP10: 10.0.0 | AQ10: 5
A11: 1118028038 | B11: → Oferta | C11: → Match | D11: Ejecutiva/o Comercial de Cuentas - GBA Norte | E11: Buenos Aires | F11: GBA Norte | G11: presencial | H11: Capital Federal o GBA Norte | I11: 1 | J11: Tecnologia/Software | K11: soluciones gráficas y documentales | L11: 0 | M11: Ventas/Comercial | N11: junior | O11: 0 | P11: Desarrollar el segmento corporativo en directa y para su red de Distribuidores a nivel nacional | Q11: [{"valor": "visitas a las cuentas", "texto_original": "Disponibilidad para visitas a las cuentas"}, {"valor": "preparación de propuestas competitivas", "texto_original": "Capacidad analítica de relevamiento en cada cuenta y detección de oportunidades"}] | R11: [{"valor": "presentar informes a la Gerencia", "texto_original": "Capacidad de Organización y planificación presentando informes a la Gerencia"}] | S11: 1 | U11: secundario | X11: ["MS Office"] | Y11: ["trabajo en equipo", "comunicacion"] | AA11: ["Tango o equivalente"] | AD11: full_time | AI11: ["viáticos contra comprobantes"] | AK11: 1 | AL11: B1 | AM11: demanda_real | AN11: alta | AO11: 0 | AP11: 10.0.0 | AQ11: 6
A12: 1118028201 | B12: → Oferta | C12: → Match | D12: 671SI Operarios ind. ALIMENTICIA c/ Tit. secundario - pres 31/10 de 10 a 1130 NUEVA Suc. SAN ISIDRO | E12: Buenos Aires | F12: San Isidro | G12: presencial | H12: Tortuguitas / GARIN | J12: Alimentacion | L12: 1 | M12: Produccion/Manufactura | N12: junior | O12: 0 | P12: Asistir en la producción y manipulación de alimentos | Q12: [{"valor": "fraccionamiento y envasado", "texto_original": "Fraccionamiento y envasado de productos alimenticios"}, {"valor": "empaque, llenado, cierre y precintado", "texto_original": "Empaque de los mismos, llenado, cierre y precintado de envases"}, {"valor": "etiquetado y control de calidad", "texto_original": "Etiquetado y control de calidad de los productos envasados"}, {"valor": "preparación de pedidos", "texto_original": "Preparación de pedidos"}, {"valor": "mantenimiento del orden y limpieza", "texto_original": "Mantenimiento del orden y limpieza del área de trabajo"}] | S12: 1 | U12: secundario | X12: ["BPM"] | AD12: full_time | AE12: eventual | AI12: ["buen clima laboral y equipo colaborativo"] | AK12: 0 | AM12: demanda_real | AN12: alta | AO12: 0 | AP12: 10.0.0 | AQ12: 6
A13: 1118028376 | B13: → Oferta | C13: → Match | D13: Analista administrativo/a | E13: CABA | F13: Nuñez | G13: hibrido | J13: Servicios Financieros | L13: 1 | M13: Administracion/Finanzas | N13: junior | O13: 0 | P13: Analizar y controlar los costos operativos de importación/exportación | Q13: [{"valor": "Realizar tareas administrativas, contables, financieras", "texto_original": "Realizar tareas administrativas, contables, financieras de las actividades comercio internacional"}, {"valor": "Colaborar con equipos interdisciplinarios para optimizar la eficiencia de las operaciones comerciales", "texto_original": "Colaborar con equipos interdisciplinarios para optimizar la eficiencia de las operaciones comerciales (Finanzas, Contabilidad, Impuestos)"}] | S13: 1 | U13: universitario | V13: universitario de carreras como Administración | X13: ["Excel"] | AA13: ["MS Office"] | AB13: ingles | AC13: intermedio | AD13: full_time | AI13: ["Medicina Prepaga Osde", "Reintegro de gastos de conectividad", "Reintegro de gastos por refrigerio"] | AJ13: 1 | AK13: 0 | AM13: demanda_real | AN13: alta | AO13: 0 | AP13: 10.0.0 | AQ13: 6
A14: 1118028657 | B14: → Oferta | C14: → Match | D14: Recepcionista | F14: Puerto Madero | G14: presencial | L14: 0 | M14: Atencion al Cliente | N14: junior | O14: 0 | P14: Atención personalizada a clientes y proveedores | Q14: [{"valor": "atención personalizada", "texto_original": "Atención personalizada a clientes y proveedores"}, {"valor": "manejo de documentación", "texto_original": "Manejo de documentación"}, {"valor": "tareas administrativas", "texto_original": "Tareas administrativas"}] | S14: 0 | AD14: full_time | AE14: eventual | AK14: 0 | AM14: demanda_real | AN14: alta | AO14: 0 | AP14: 10.0.0 | AQ14: 5
A15: 1118028681 | B15: → Oferta | C15: → Match | D15: ADMINISTRATIVA/O | E15: Buenos Aires | F15: Canning | G15: presencial | H15: Canning o zonas aledañas | I15: 1 | J15: Alimentacion | L15: 0 | M15: Administracion/Finanzas | N15: semisenior | O15: 0 | P15: Responsable del ingreso de mercadería al sistema, actualizar costos y precios de venta de los productos en el sistema, actualizar los precios de los productos en diferentes plataformas e-commerce, pago a proveedores, generar pedidos a proveedores, liquidación de sueldos | Q15: [{"valor": "ingreso de mercadería al sistema", "texto_original": "Responsable del ingreso de mercadería al sistema"}, {"valor": "actualizar costos y precios de venta en el sistema", "texto_original": "actualizar costos y precios de venta de los productos en el sistema"}, {"valor": "actualizar precios en plataformas e-commerce", "texto_original": "actualizar los precios de los productos en diferentes plataformas e-commerce"}, {"valor": "pago a proveedores", "texto_original": "pago a proveedores"}, {"valor": "generar pedidos a proveedores", "texto_original": "generar pedidos a proveedores"}, {"valor": "liquidación de sueldos", "texto_original": "liquidación de sueldos"}] | S15: 5 | X15: ["Paquete Office"] | AD15: full_time | AI15: ["excelentes condiciones de contratación"] | AK15: 0 | AM15: demanda_real | AN15: alta | AO15: 0 | AP15: 10.0.0 | AQ15: 6
A16: 1118028828 | B16: → Oferta | C16: → Match | D16: Búsqueda Laboral: Modelista – Vicente López (Florida Oeste) | E16: Buenos Aires | F16: Vicente López | G16: presencial | H16: AMBA, preferentemente cercana a Vicente López | L16: 0 | M16: Produccion/Manufactura | N16: semisenior | O16: 0 | P16: Desarrollar la moldería, prototipo y muestras de los productos de nuestras colecciones | Q16: [{"valor": "desarrollar moldería según la definición del diseño", "texto_original": "Desarrollar moldería según la definición del diseño"}, {"valor": "participar en las pruebas de calce junto al equipo de Producto", "texto_original": "Participar en las pruebas de calce junto al equipo de Producto"}, {"valor": "realizar ajustes necesarios", "texto_original": "realizando los ajustes necesarios"}, {"valor": "desarrollar progresiones de la moldería aprobada", "texto_original": "Desarrollar progresiones de la moldería aprobada"}, {"valor": "especificar avíos según género y prototipo", "texto_original": "Especificar avíos (entretelas, hilos, hombreras, etc.) según género y prototipo"}, {"valor": "realizar pruebas de comportamiento de géneros y registrar resultados", "texto_original": "Realizar pruebas de comportamiento de géneros y registrar resultados"}, {"valor": "entregar progresiones, prototipos, tablas de medidas y fichas técnicas a Producción en tiempo y forma", "texto_original": "Entregar progresiones, prototipos, tablas de medidas y fichas técnicas a Producción en tiempo y forma"}, {"valor": "colaborar en el armado del muestrario para el área Comercial", "texto_original": "Colaborar en el armado del muestrario para el área Comercial"}] | S16: 3 | U16: terciario | W16: Modelista | X16: ["Lectra"] | Y16: ["trabajo en equipo"] | AD16: full_time | AK16: 0 | AM16: demanda_real | AN16: alta | AO16: 0 | AP16: 10.0.0 | AQ16: 5
A17: 1118028833 | B17: → Oferta | C17: → Match | D17: Asesor Comercial Plan de Ahorro - Volkswagen | G17: presencial | J17: Automotriz | L17: 0 | M17: Ventas/Comercial | N17: junior | O17: 0 | P17: Asesor de ventas en concesionario automotriz | Q17: [{"valor": "optimización de los datos que se brindan para la concreción de la venta", "texto_original": "optimización de los datos que se brindan para la concreción de la venta"}, {"valor": "detección de oportunidades de nuevos negocios", "texto_original": "detección de oportunidades de nuevos negocios"}, {"valor": "cumplimiento de objetivos comerciales", "texto_original": "cumplimiento de objetivos comerciales"}] | S17: 0 | U17: secundario | Y17: ["iniciativa", "orientación al resultado", "excelencia en lo que hacemos", "orientación al cliente", "trabajo en equipo"] | AD17: full_time | AI17: ["descuento en Sport Club", "50% en todos los talleres", "15% en Repuestos", "12 cuotas S/Interés Bridgestone/Firestone 30%", "Seguros de la Caja", "Planes Adjudicados", "Descuentos en Malcriado (Shopping Tom)", "Descuentos en Samsung", "Descuentos en Bimbo"] | AK17: 0 | AM17: demanda_real | AN17: alta | AO17: 1 | AP17: 10.0.0 | AQ17: 4
A18: 1118028887 | B18: → Oferta | C18: → Match | D18: Account Executive (Hunter) | E18: Capital Federal | F18: Capital Federal | G18: hibrido | J18: Tecnologia/Software | L18: 0 | M18: Ventas/Comercial | N18: junior | O18: 0 | P18: Prospección y captación de nuevos clientes | Q18: [{"valor": "identificar oportunidades de negocio", "texto_original": "identificar oportunidades de negocio"}, {"valor": "elaborar propuestas comerciales", "texto_original": "elaborar propuestas comerciales"}, {"valor": "mantener una constante comunicación con los clientes", "texto_original": "mantener una constante comunicación con los clientes"}] | S18: 0 | T18: 2 | U18: universitario | Y18: ["mentalidad orientada a resultados", "habilidades de negociación"] | AD18: full_time | AK18: 0 | AM18: demanda_real | AN18: alta | AO18: 0 | AP18: 10.0.0 | AQ18: 5
A19: 1118028891 | B19: → Oferta | C19: → Match | D19: auxiliar contable | E19: Buenos Aires | F19: Munro | G19: hibrido | I19: 0 | L19: 0 | M19: Administracion/Finanzas | N19: junior | O19: 0 | P19: Administrativo Contable | Q19: [{"valor": "Gestión integral de caja diaria y fondos fijos", "texto_original": "Gestión integral de caja diaria y fondos fijos"}, {"valor": "Administración de cobranzas, pagos y depósitos bancarios", "texto_original": "Administración de cobranzas, pagos y depósitos bancarios"}, {"valor": "Control y registro de facturas, proveedores y padrones", "texto_original": "Control y registro de facturas, proveedores y padrones"}, {"valor": "Análisis de cuentas contables para cierres y balances", "texto_original": "Análisis de cuentas contables para cierres y balances"}, {"valor": "Emisión de pagos, notas de débito y planillas de descuentos", "texto_original": "Emisión de pagos, notas de débito y planillas de descuentos"}, {"valor": "Conciliaciones bancarias", "texto_original": "Conciliaciones bancarias"}, {"valor": "Manejo de cheques (depósito, rechazos, devoluciones)", "texto_original": "Manejo de cheques (depósito, rechazos, devoluciones)"}] | S19: 2 | T19: 2 | U19: universitario | V19: Contabilidad o un campo de | Y19: ["proactivo", "iniciativa"] | AD19: full_time | AI19: ["Bono anual por objetivos", "Celular"] | AK19: 0 | AM19: demanda_real | AN19: alta | AO19: 0 | AP19: 10.0.0 | AQ19: 6
A20: 2162667 | B20: → Oferta | C20: → Match | D20: Gerente de Operaciones | L20: 0 | M20: Operaciones/Logistica | N20: lead/manager | O20: 1 | P20: Dirigir la gestión operativa de todas las áreas de servicio | Q20: [{"valor": "Definir, implementar y supervisar estrategias operativas", "texto_original": "Definir, implementar y supervisar estrategias operativas"}, {"valor": "Dirigir equipos de coordinadores/as y supervisores/as", "texto_original": "Dirigir equipos de coordinadores/as y supervisores/as"}, {"valor": "Asegurar el cumplimiento de normas de calidad, higiene y seguridad en todas las operaciones", "texto_original": "Asegurar el cumplimiento de normas de calidad, higiene y seguridad en todas las operaciones"}, {"valor": "Monitorear indicadores clave (KPIs) de desempeño y liderar planes de mejora continua", "texto_original": "Monitorear indicadores clave (KPIs) de desempeño y liderar planes de mejora continua"}, {"valor": "Gestionar presupuestos operativos y recursos con foco en rentabilidad y sostenibilidad", "texto_original": "Gestionar presupuestos operativos y recursos con foco en rentabilidad y sostenibilidad"}, {"valor": "Mantener relaciones cercanas con clientes corporativos, promoviendo la satisfacción y fidelización", "texto_original": "Mantener relaciones cercanas con clientes corporativos, promoviendo la satisfacción y fidelización"}] | R20: [{"valor": "Impulsar proyectos innovadores en sustentabilidad y experiencia colaboradora", "texto_original": "Impulsar proyectos innovadores en sustentabilidad y experiencia colaboradora"}] | S20: 10 | U20: universitario | V20: Industrial | Y20: ["habilidades de liderazgo"] | AI20: ["Oportunidad de liderar la operación de una empresa en plena expansión", "Entorno de trabajo colaborativo, con fuerte cultura en sustentabilidad e innovación"] | AK20: 0 | AM20: demanda_real | AN20: alta | AO20: 0 | AP20: 10.0.0 | AQ20: 6
A21: 1118022146 | B21: → Oferta | C21: → Match | D21: Community manager | E21: Buenos Aires | F21: Tigre | G21: presencial | J21: Construcción | K21: Comercialización e importación de materiales para Construcción y Decoración | L21: 0 | M21: Marketing | N21: lead/manager | O21: 0 | P21: Construir y expandir las marcas del grupo fuera de Mercado Libre | Q21: [{"valor": "desarrollar e implementar iniciativas de marketing", "texto_original": "Desarrollar e implementar iniciativas de marketing"}, {"valor": "crear contenido para redes sociales", "texto_original": "Crear contenido para Instagram, Facebook y LinkedIn (producción, filmación, edición y redacción de copy)"}, {"valor": "responder mensajes en redes sociales", "texto_original": "Responder mensajes, comentarios y consultas en redes sociales"}, {"valor": "implementar campañas en Meta Ads y Google Ads", "texto_original": "Administrar campañas en Meta Ads y Google Ads"}, {"valor": "cargar y actualizar productos online", "texto_original": "Cargar y actualizar productos en TiendaNube u otras plataformas"}] | R21: [{"valor": "gestionar contactos y clientes con CRM", "texto_original": "Implementar un sistema de CRM activo para la gestión de clientes y prospectos"}, {"valor": "coordinar acciones con influencers", "texto_original": "Coordinar acciones con influencers, creadores de contenido y proveedores externos"}] | S21: 7 | U21: universitario | V21: Marketing, Comunicación, Publicidad, Branding o afines | X21: ["SEO", "Google Ads", "Meta Ads"] | Y21: ["creatividad", "atencion al detalle", "proactividad"] | Z21: ["TiendaNube", "Mercado Libre", "Shopify"] | AA21: ["CapCut", "Premiere", "Canva", "Photoshop / Illustrator"] | AD21: freelance | AI21: ["remuneracion competitiva", "oportunidad de crecer en una empresa con proyeccion regional"] | AK21: 0 | AM21: demanda_real | AN21: alta | AO21: 0 | AP21: 10.0.0 | AQ21: 5
A22: 1118025212 | B22: → Oferta | C22: → Match | D22: Representante Técnico/a Comercial | K22: agricultura | L22: 0 | M22: Ventas/Comercial | N22: junior | O22: 0 | P22: Comercialización de agro insumos y servicios | Q22: [{"valor": "asesoramiento técnico a clientes", "texto_original": "Asesoramiento técnico a clientes"}, {"valor": "desarrollo de nuevas oportunidades de negocio", "texto_original": "Desarrollo de nuevas oportunidades de negocio"}] | S22: 0 | U22: terciario | V22: carreras afines | W22: Ing. Agrónomo/a | Y22: ["vocación comercial", "orientación a resultados"] | AK22: 0 | AM22: demanda_real | AN22: media | AO22: 0 | AP22: 10.0.0 | AQ22: 5
A23: 1117984105 | B23: → Oferta | C23: → Match | D23: Venado Tuerto | E23: Santa Fe | F23: Venado Tuerto | G23: presencial | H23: Radicación en Venado Tuerto (Sta. Fé) | J23: Manufactura/Industria | K23: maquinaria agrícola | L23: 0 | M23: Ventas/Comercial | N23: lead/manager | O23: 1 | P23: Liderar equipo de ventas en concesionario oficial | R23: ["logro de objetivos comerciales", "liderazgo"] | S23: 35 | T23: 50 | U23: terciario | Y23: ["disposición para liderar en equipo", "proactivo y responsable"] | AI23: ["Buen ambiente y condiciones de trabajo"] | AK23: 0 | AM23: demanda_real | AN23: media | AO23: 1 | AP23: 10.0.0 | AQ23: 5
A24: 1117960588 | B24: → Oferta | C24: → Match | D24: Asistente de Dirección / Administrativo con experiencia en Publicidad y Medios | G24: hibrido | J24: Publicidad/Medios | L24: 0 | M24: Administracion/Finanzas | N24: junior | O24: 0 | P24: Asistir a la Dirección y coordinar tareas vinculadas a publicidad y medios | Q24: [{"valor": "Tareas administrativas generales", "texto_original": "Tareas administrativas generales"}, {"valor": "Atención telefónica y presencial de clientes y proveedores", "texto_original": "Atención telefónica y presencial de clientes y proveedores"}, {"valor": "Coordinación de llamados, correos y comunicaciones institucionales", "texto_original": "Coordinación de llamados, correos y comunicaciones institucionales"}, {"valor": "Apoyo en campañas publicitarias", "texto_original": "Apoyo en campañas publicitarias"}] | S24: 1 | X24: ["Office", "planillas", "excel avanzado"] | Y24: ["habilidades de comunicación", "atención al cliente"] | AA24: ["Office", "planillas", "excel avanzado"] | AD24: full_time | AI24: ["Excelente clima de trabajo", "posibilidades de desarrollo"] | AK24: 0 | AM24: demanda_real | AN24: alta | AO24: 0 | AP24: 10.0.0 | AQ24: 6
A25: 1118009739 | B25: → Oferta | C25: → Match | D25: Administrativa Comercio Exterior | E25: CABA | G25: hibrido | J25: Retail/Comercio | L25: 1 | M25: Administracion/Finanzas | N25: junior | O25: 0 | P25: Administrativo para área de Comex | Q25: [{"valor": "Gestión y carga de Facturación de Clientes (FC)", "texto_original": "Gestión y carga de Facturación de Clientes (FC)"}, {"valor": "Coordinación y ejecución del cierre de ciclos de pago", "texto_original": "Coordinación y ejecución del cierre de ciclos de pago"}] | S25: 0 | U25: terciario | V25: Comercio internacional | AD25: full_time | AE25: eventual | AI25: ["Cobertura médica correspondiente a convenio", "espacio de comedor"] | AJ25: 1 | AK25: 0 | AM25: demanda_real | AN25: alta | AO25: 0 | AP25: 10.0.0 | AQ25: 4
A26: 1118000814 | B26: → Oferta | C26: → Match | D26: Asistente Administrativo de Ventas | G26: presencial | L26: 0 | M26: Administracion/Finanzas | N26: junior | O26: 0 | P26: Brindar soporte administrativo y operativo al área de ventas | Q26: [{"valor": "cargar y actualizar pedidos de venta en el sistema interno", "texto_original": "Cargar y actualizar pedidos de venta en el sistema interno"}, {"valor": "elaborar reportes de ventas, márgenes, rotación y desempeño por producto o vendedor mediante Excel avanzado", "texto_original": "Elaborar reportes de ventas, márgenes, rotación y desempeño por producto o vendedor mediante Excel avanzado"}, {"valor": "controlar y coordinar entregas con el área de logística", "texto_original": "Controlar y coordinar entregas con el área de logística"}, {"valor": "mantener actualizada la base de datos de clientes, precios y promociones", "texto_original": "Mantener actualizada la base de datos de clientes, precios y promociones"}, {"valor": "realizar el seguimiento de cobranzas en coordinación con el área de administración", "texto_original": "Realizar el seguimiento de cobranzas en coordinación con el área de administración"}, {"valor": "asistir en la preparación de presentaciones comerciales e informes de gestión", "texto_original": "Asistir en la preparación de presentaciones comerciales e informes de gestión"}, {"valor": "colaborar en la implementación de acciones comerciales y campañas de venta", "texto_original": "Colaborar en la implementación de acciones comerciales y campañas de venta"}, {"valor": "gestionar documentación y archivos del área comercial", "texto_original": "Gestionar documentación y archivos del área comercial"}] | S26: 2 | U26: terciario | V26: Administración de Empresas, Comercialización o afines | X26: ["Excel avanzado"] | Y26: ["autonomía y proactividad", "orden y precisión administrativa", "orientación a resultados y al cliente interno", "capacidad analítica y atención al detalle", "trabajo en equipo y comunicación efectiva"] | Z26: ["sistemas de gestión comercial"] | AD26: full_time | AI26: ["Obra Social", "descuentos en productos", "día de cumpleaños"] | AJ26: 1 | AK26: 0 | AM26: demanda_real | AN26: alta | AO26: 0 | AP26: 10.0.0 | AQ26: 6
A27: 1118020225 | B27: → Oferta | C27: → Match | D27: Representante de atención al cliente | E27: Buenos Aires | F27: Munro | G27: hibrido | J27: Servicios Financieros | K27: servicios corporativos B2B y medios de pagos | L27: 0 | M27: Atencion al Cliente | N27: junior | O27: 0 | P27: Brindar un servicio de atención al cliente excepcional | Q27: [{"valor": "manejo de consultas, quejas y solicitudes a través de mails, llamadas telefónicas y mensajes de WhatsApp", "texto_original": "manejo de consultas, quejas y solicitudes a través de mails, llamadas telefónicas y mensajes de WhatsApp"}, {"valor": "Fidelizar al Cliente generando un vínculo duradero en el corto plazo", "texto_original": "Fidelizar al Cliente generando un vínculo duradero en el corto plazo"}, {"valor": "Detectar oportunidades de venta de otras soluciones en el periodo de implementación", "texto_original": "Detectar oportunidades de venta de otras soluciones en el periodo de implementación"}, {"valor": "Colaboración constante con otras áreas para entregar soluciones al cliente", "texto_original": "Colaboración constante con otras áreas para entregar soluciones al cliente"}, {"valor": "Proponer mejoras constantes en los procesos internos", "texto_original": "Proponer mejoras constantes en los procesos internos"}] | S27: 7 | U27: universitario | V27: Lic. en Administración, Comunicación, Comercialización y/o afines | X27: ["herramientas de CRM", "plataformas de mensajería como WhatsApp"] | Y27: ["vocación al cliente", "habilidades interpersonales y de comunicación excepcionales", "habilidades para resolver problemas"] | AA27: ["CRM", "WhatsApp"] | AB27: ingles | AC27: intermedio | AD27: full_time | AI27: ["Prepaga para grupo familiar", "Días habiles de vacaciones", "Día de cumpleaños libre", "Almuerzo Y más!"] | AJ27: 1 | AK27: 0 | AM27: demanda_real | AN27: alta | AO27: 0 | AP27: 10.0.0 | AQ27: 5
A28: 1118003709 | B28: → Oferta | C28: → Match | D28: CAJERO/ENCARGADO | E28: Buenos Aires | F28: Adrogue | G28: presencial | H28: zona o alrededores | J28: Alimentacion | L28: 0 | M28: Operaciones/Logistica | O28: 1 | P28: Manejar las transacciones diarias y coordinar al equipo del turno | Q28: [{"valor": "manejo de transacciones", "texto_original": "Manejando las transacciones diarias"}, {"valor": "arqueo de caja", "texto_original": "Realizar arqueos de caja al inicio y final del turno"}, {"valor": "atencion al cliente", "texto_original": "Brindar una óptima atención al cliente"}, {"valor": "coordinacion equipo", "texto_original": "Coordinar al equipo del turno para garantizar que las operaciones fluyan"}] | S28: 1 | AA28: ["Office", "Excel"] | AD28: full_time | AK28: 0 | AM28: demanda_real | AN28: alta | AO28: 0 | AP28: 10.0.0 | AQ28: 5
A29: 1118017586 | B29: → Oferta | C29: → Match | D29: Médica Clínica o Dermatóloga – Especialista en tratamientos estéticos inyectables | E29: Buenos Aires | F29: Quilmes | G29: presencial | J29: Salud/Farmaceutica | L29: 0 | M29: Salud | N29: semisenior | O29: 0 | P29: Realizar procedimientos inyectables y aplicar tratamientos con tecnología láser | Q29: [{"valor": "realizar procedimientos inyectables", "texto_original": "relleno de labios, ojeras, rinomodelación, Radiesse"}, {"valor": "aplicar tratamientos con tecnología láser", "texto_original": "Nordlys, CO₂"}] | S29: 1 | U29: universitario | W29: Médica Clínica o Dermatóloga | X29: ["tratamientos con tecnología láser"] | Y29: ["excelente trato interpersonal", "orientación al paciente"] | AA29: ["Ultraformer/HIFU"] | AD29: part_time | AI29: ["integración a un equipo de profesionales", "oportunidad de desarrollo profesional y crecimiento dentro de la clínica", "ambiente de trabajo profesional y ameno"] | AK29: 0 | AM29: demanda_real | AN29: alta | AO29: 0 | AP29: 10.0.0 | AQ29: 6
A30: 1118025956 | B30: → Oferta | C30: → Match | D30: Jardinero | G30: presencial | L30: 0 | M30: Operaciones/Logistica | N30: junior | O30: 0 | P30: Realizar el corte y mantenimiento del césped | Q30: [{"valor": "cuidado general de plantas y flores", "texto_original": "cuidado general de plantas y flores"}, {"valor": "mantener el orden y la limpieza de las áreas verdes", "texto_original": "mantener el orden y la limpieza de las áreas verdes"}] | S30: 1 | AD30: full_time | AK30: 1 | AM30: demanda_real | AN30: media | AO30: 0 | AP30: 10.0.0 | AQ30: 6
A31: 2164100 | B31: → Oferta | C31: → Match | D31: Mozo/Moza | E31: Mendoza | F31: Valle de Uco, Tunuyán | G31: presencial | H31: Tunuyán o zonas cercanas | J31: Turismo/Hospitalidad | L31: 0 | M31: Atencion al Cliente | N31: junior | O31: 0 | P31: Ser parte de un equipo que brinda experiencias de primer nivel a nuestros huéspedes | R31: ["servicio en salones", "atención al detalle"] | S31: 1 | Y31: ["vocación de servicio", "actitud cordial"] | AB31: ingles | AC31: avanzado | AD31: full_time | AI31: ["entorno de trabajo profesional y dinámico", "oportunidades de crecimiento"] | AK31: 0 | AM31: demanda_real | AN31: alta | AO31: 0 | AP31: 10.0.0 | AQ31: 5
A32: 2165052 | B32: → Oferta | C32: → Match | D32: Electricista Industrial | L32: 0 | M32: Operaciones/Logistica | N32: semisenior | O32: 0 | P32: Realizar el mantenimiento preventivo y correctivo de equipos e instalaciones eléctricas | Q32: [{"valor": "Interpretar planos unifilares eléctricos", "texto_original": "Interpretar planos unifilares eléctricos"}, {"valor": "Dimensionar instalaciones eléctricas y selectividades", "texto_original": "Dimensionar instalaciones eléctricas y selectividades"}, {"valor": "Montar canalizaciones eléctricas", "texto_original": "Montar canalizaciones eléctricas"}, {"valor": "Diseñar y armar tableros eléctricos de control y potencia", "texto_original": "Diseñar y armar tableros eléctricos de control y potencia"}] | S32: 1 | U32: secundario | X32: ["mantenimiento preventivo y correctivo", "interpretación de planos eléctricos", "dimensionamiento de instalaciones eléctricas", "montaje de canalizaciones eléctricas", "diseño y armado de tableros eléctricos"] | AK32: 0 | AM32: demanda_real | AN32: media | AO32: 0 | AP32: 10.0.0 | AQ32: 5
A33: 2165301 | B33: → Oferta | C33: → Match | D33: Supervisor/a Administración Autos usados | E33: Buenos Aires | F33: Tortuguitas | G33: presencial | J33: Automotriz | L33: 0 | M33: Administracion/Finanzas | N33: semisenior | O33: 1 | P33: Liderar equipos administrativos y asegurar el cumplimiento de plazos para la disponibilidad de las unidades | Q33: [{"valor": "optimizar los procesos para reducir costos operativos", "texto_original": "optimizar los procesos para reducir costos operativos"}, {"valor": "garantizar una administración ordenada y resultados medibles", "texto_original": "garantizar una administración ordenada y resultados medibles"}] | S33: 1 | U33: secundario | X33: ["manejo avanzado de paquete Office"] | Y33: ["habilidad en liderazgo y coordinación de equipos"] | AD33: full_time | AK33: 0 | AM33: demanda_real | AN33: alta | AO33: 0 | AP33: 10.0.0 | AQ33: 6
A34: 1116898892 | B34: → Oferta | C34: → Match | D34: Chofer - Repartidor | E34: Buenos Aires | F34: Benavidez | G34: presencial | J34: Alimentacion | L34: 0 | M34: Operaciones/Logistica | O34: 0 | P34: Realizar entregas de productos y mantener el vehículo en óptimas condiciones | Q34: [{"valor": "verificación de los pedidos", "texto_original": "Verificación de los pedidos para asegurar la correcta entrega según lo solicitado"}, {"valor": "mantener el vehículo en óptimas condiciones", "texto_original": "Mantener el vehiculo en óptimas condiciones, tanto a nivel mecánico como de limpieza"}, {"valor": "reportar cualquier inconveniente relacionado con el vehículo o las entregas", "texto_original": "Reportar cualquier inconveniente relacionado con el vehiculo o las entregas"}, {"valor": "colaborar con el equipo logístico para coordinar rutas y tiempos de entrega", "texto_original": "Colaborar con el equipo logístico para coordinar rutas y tiempos de entrega de manera eficiente"}] | S34: 2 | X34: ["mantenimiento y cuidado de vehículos"] | Y34: ["actitud responsable", "puntualidad", "capacidad para gestionar las entregas de manera eficiente y autónoma"] | AD34: full_time | AK34: 1 | AM34: demanda_real | AN34: alta | AO34: 0 | AP34: 10.0.0 | AQ34: 5
A35: 1118023904 | B35: → Oferta | C35: → Match | D35: Operario Picking | E35: Buenos Aires | F35: ["Escobar", "El Talar", "Pilar"] | G35: presencial | H35: Zona Norte de Buenos Aires | J35: Transporte/Logistica | L35: 0 | M35: Operaciones/Logistica | N35: junior | O35: 0 | P35: Operario y Pickeador en operaciones logísticas | Q35: [{"valor": "picking con RF", "texto_original": "* Picking con RF"}, {"valor": "carga y descarga de camiones", "texto_original": "* Carga y descarga de camiones."}, {"valor": "conteo de productos", "texto_original": "* Conteo de productos"}, {"valor": "armado de pedidos", "texto_original": "* Armado de pedidos"}] | S35: 20 | T35: 45 | U35: secundario | AA35: ["RF"] | AD35: full_time | AE35: eventual | AK35: 0 | AM35: demanda_real | AN35: media | AO35: 1 | AP35: 10.0.0 | AQ35: 5
A36: 1117980907 | B36: → Oferta | C36: → Match | D36: Operario de Almacén/Logística | E36: Buenos Aires | F36: Escobar | G36: presencial | H36: cerca de Escobar | J36: Manufactura/Industria | K36: Metalúrgica | L36: 0 | M36: Operaciones/Logistica | N36: junior | O36: 0 | P36: Operario de almacén /logística | Q36: [{"valor": "Recepción y verificación de mercadería", "texto_original": "Recepción y verificación de mercadería"}, {"valor": "Almacenamiento y organización de productos", "texto_original": "Almacenamiento y organización de productos"}, {"valor": "Preparación de pedidos y despacho de mercadería", "texto_original": "Preparación de pedidos y despacho de mercadería"}, {"valor": "Control de inventario y registro en sistema", "texto_original": "Control de Inventario"}] | S36: 1 | U36: secundario | AD36: full_time | AK36: 0 | AM36: demanda_real | AN36: alta | AO36: 0 | AP36: 10.0.0 | AQ36: 6
A37: 1117990944 | B37: → Oferta | C37: → Match | D37: Repositor/a Externo/a (Eventual) Moreno | E37: Buenos Aires | F37: Moreno | G37: presencial | H37: zonas cercanas | J37: Retail/Comercio | L37: 0 | M37: Operaciones/Logistica | N37: junior | O37: 0 | P37: Repositor externo en PDV | Q37: [{"valor": "Limpieza de góndola y control de fechas de vencimiento", "texto_original": "-Limpieza de góndola y control de fechas de vencimiento"}, {"valor": "Reposición de los productos asignados", "texto_original": "-Reposición de los productos asignados"}, {"valor": "Mantener abastecidos y en orden los freezers y las góndolas de los PDV", "texto_original": "-Mantener abastecidos y en orden los freezers y las góndolas de los PDV"}, {"valor": "Armado de exhibiciones primaria (góndola) según Planogramas", "texto_original": "-Armado de exhibiciones primaria (góndola) según Planogramas"}, {"valor": "Colocación y seguimiento del material POP", "texto_original": "-Colocación y seguimiento del material POP"}, {"valor": "Control de ofertas y precios, además de la colocación de carteles", "texto_original": "-Control de ofertas y precios, además de la colocación de carteles"}, {"valor": "Control quiebres y falsos stocks", "texto_original": "-Controlas quiebres y falsos stocks"}, {"valor": "Control de mermas y de Calidad", "texto_original": "-Control de mermas y de Calidad"}] | S37: 1 | U37: secundario | AD37: full_time | AE37: eventual | AK37: 0 | AM37: demanda_real | AN37: alta | AO37: 0 | AP37: 10.0.0 | AQ37: 6
A38: 1117961954 | B38: → Oferta | C38: → Match | D38: Asistente Administrativo General | L38: 0 | M38: Administracion/Finanzas | N38: junior | P38: Brindar soporte administrativo a varios departamentos | Q38: [{"valor": "Gestionar y organizar documentos y archivos", "texto_original": "Gestionar y organizar documentos y archivos"}, {"valor": "Coordinar reuniones y eventos", "texto_original": "Coordinar reuniones y eventos"}, {"valor": "Preparar informes y presentaciones", "texto_original": "Preparar informes y presentaciones"}, {"valor": "Realizar tareas de contabilidad básica", "texto_original": "Realizar tareas de contabilidad básica"}] | S38: 1 | X38: ["Microsoft Office Suite"] | Y38: ["proactiva", "organizada"] | AA38: ["Word", "Excel", "PowerPoint"] | AK38: 0 | AM38: demanda_real | AN38: media | AO38: 0 | AP38: 10.0.0 | AQ38: 6
A39: 1117982053 | B39: → Oferta | C39: → Match | D39: Desarrollador Angular Senior | G39: remoto | I39: 0 | J39: Tecnologia/Software | L39: 0 | M39: IT/Sistemas | N39: senior | O39: 1 | P39: Desarrollador Angular Senior | Q39: [{"valor": "desarrollar, mantener y escalar funcionalidades del CX Portal", "texto_original": "Desarrollar, mantener y escalar funcionalidades del CX Portal con enfoque en rendimiento, reutilización y sostenibilidad"}, {"valor": "liderar la integración de Module Federation y Lazy Loading", "texto_original": "Liderar la integración de Module Federation y la implementación de técnicas de Lazy Loading"}, {"valor": "guiar al equipo en la optimización de Webpack", "texto_original": "Guiar al equipo en la optimización de Webpack y mejora continua de la experiencia del usuario"}] | R39: [{"valor": "participar en el despliegue y monitoreo en AWS", "texto_original": null}, {"valor": "velar por la eficiencia técnica del sistema", "texto_original": null}] | S39: 4 | U39: terciario | X39: ["Angular", "Webpack"] | Z39: ["AWS", "CloudFront", "CloudFormation"] | AD39: full_time | AI39: ["flexibilidad", "regalos y descuentos", "diversion", "formacion y capacitaciones"] | AK39: 0 | AM39: demanda_real | AN39: alta | AO39: 0 | AP39: 10.0.0 | AQ39: 6
A40: 1118018461 | B40: → Oferta | C40: → Match | D40: Asesor/a de Admisiones | E40: CABA | G40: hibrido | J40: Educacion | L40: 0 | M40: Administracion/Finanzas | N40: junior | O40: 0 | P40: Acompañar a los postulantes en su proceso de admisión y asesorarlos en la elección de carrera | Q40: [{"valor": "asesoramiento personalizado", "texto_original": "acompañar a los postulantes en el proceso de elección de su carrera"}, {"valor": "charlas grupales sobre admisión y programas académicos", "texto_original": "dar charlas grupales sobre el proceso de admisión, los programas académicos y las oportunidades que ofrece la universidad"}, {"valor": "atención a consultas por mail, WhatsApp y teléfono", "texto_original": "responder consultas por mail, WhatsApp y teléfono; resolver inquietudes de potenciales alumnos y sus familias"}, {"valor": "gestión de actividades y eventos", "texto_original": "coordinar y participar en eventos para comunicar las carreras y oportunidades que brinda la universidad"}, {"valor": "viajes al interior del país", "texto_original": "viajar al interior del país para visitar escuelas, mantener contacto con autoridades educativas, dar charlas a estudiantes y generar vínculos con potenciales interesados"}, {"valor": "gestión administrativa en CRM de Admisiones", "texto_original": "actualizar el CRM de Admisiones, coordinar el curso de ingreso y procesar aplicaciones de postulantes"}] | S40: 0 | X40: ["paquete Office", "herramientas de Google"] | Y40: ["dinámica", "proactiva", "resolutiva", "vocación de servicio", "atenta a los detalles", "excelente comunicación oral y escrita"] | AD40: full_time | AK40: 0 | AM40: demanda_real | AN40: alta | AO40: 0 | AP40: 10.0.0 | AQ40: 4
A41: 1118018714 | B41: → Oferta | C41: → Match | D41: Diseñador Gráfico E-commerce | J41: Tecnologia/Software | L41: 0 | M41: Marketing | P41: Responsable de mejorar la presentación visual de los productos en plataformas de e-commerce | Q41: [{"valor": "Crear y editar contenido visual para publicaciones de productos", "texto_original": "Crear y editar contenido visual para publicaciones de productos en plataformas de e-commerce"}, {"valor": "Optimizar títulos y descripciones de productos", "texto_original": "Optimizar títulos y descripciones de productos para mejorar el SEO y la conversión"}, {"valor": "Asegurar que las imágenes sean de alta calidad", "texto_original": "Asegurar que las imágenes de los productos sean de alta calidad y representen fielmente el producto"}, {"valor": "Gestionar y actualizar publicaciones existentes", "texto_original": "Gestionar y actualizar publicaciones existentes para mantener la información precisa y relevante"}] | R41: [{"valor": "Colaborar con otros equipos en estrategias de marketing visual", "texto_original": "Colaborar con otros equipos para desarrollar estrategias de marketing visual efectivas"}] | S41: 1 | X41: ["Photoshop", "Illustrator"] | Y41: ["creativo"] | AA41: ["Photoshop", "Illustrator"] | AK41: 0 | AM41: demanda_real | AN41: alta | AO41: 0 | AP41: 10.0.0 | AQ41: 5
A42: 1118031991 | B42: → Oferta | C42: → Match | G42: remoto | J42: Retail/Comercio | L42: 0 | M42: Ventas/Comercial | N42: junior | O42: 0 | P42: Promocionar y vender productos de cocina de alta gama relacionados con la salud | Q42: [{"valor": "vender a clientes potenciales", "texto_original": "promocionar y vender nuestros productos/servicios"}] | S42: 1 | Y42: ["trabajo en equipo"] | AD42: full_time | AI42: ["flexibilidad"] | AK42: 0 | AM42: demanda_real | AN42: media | AO42: 0 | AP42: 10.0.0
A43: 1116884561 | B43: → Oferta | C43: → Match | E43: Buenos Aires | G43: presencial | J43: Retail/Comercio | L43: 1 | M43: Ventas/Comercial | N43: junior | P43: Atención/fidelización de la cartera de clientes actuales y captación de nuevos clientes para incrementar los revenues en la cartera existente | Q43: [{"valor": "atención/gestión de requerimientos/reclamos de los clientes", "texto_original": "Atención/gestión de requerimientos/reclamos de los clientes"}, {"valor": "promoción de productos y presentaciones con los clientes", "texto_original": "Promoción de productos y presentaciones con los clientes"}, {"valor": "monitoreo y anticipación de situaciones del mercado en cuanto a novedades/tendencia/problemáticas que impacten en un resultado positivo comercial", "texto_original": "Monitoreo y anticipación de situaciones del mercado en cuanto a novedades/tendencia/problemáticas que impacten en un resultado positivo comercial"}, {"valor": "cobranza mensual, conciliación de cuentas de clientes con el área financiera de la empresa", "texto_original": "Cobranza mensual, conciliación de cuentas de clientes con el área financiera de la empresa"}] | S43: 0 | T43: 2 | V43: al siguiente nivel | Y43: ["negociación", "planificación, organización y coordinación", "capacidad analítica", "trabajo en equipo y buenas relaciones interpersonales", "comunicación asertiva", "adaptación"] | AB43: ingles | AC43: basico | AD43: full_time | AI43: ["contratación inmediata y directa con la empresa", "prepaga"] | AJ43: 1 | AK43: 1 | AM43: demanda_real | AN43: alta | AO43: 0 | AP43: 10.0.0
A44: 1117995368 | B44: → Oferta | C44: → Match | D44: ASESOR TÉCNICO NUTRICIÓN ANIMAL RUMIANTES | E44: Buenos Aires | G44: presencial | H44: zonas centro del país (provincia de Buenos Aires, Santa Fe, Córdoba o Entre Ríos) | J44: Salud/Farmaceutica | K44: Nutrición Animal | L44: 0 | M44: Salud | N44: senior | O44: 0 | P44: Asesor Técnico con comprobada experiencia en rumiantes | Q44: [{"valor": "conocer en profundidad todos los productos para rumiantes", "texto_original": "para conocer en profundidad todos los productos para rumiantes, clientes y posibilidades de desarrollo futuro"}] | S44: 7 | U44: universitario | V44: ["Ingeniero Zootecnista", "Ingeniero Agrónomo", "Veterinario"] | Y44: ["disposición para viajar"] | AD44: full_time | AK44: 0 | AM44: demanda_real | AN44: alta | AO44: 0 | AP44: 10.0.0 | AQ44: 5
A45: 2170124 | B45: → Oferta | C45: → Match | E45: Buenos Aires | F45: Roque Pérez | G45: presencial | H45: Roque Pérez o zonas aledañas | I45: 0 | J45: Manufactura/Industria | K45: agroindustrial | L45: 0 | M45: Operaciones/Logistica | N45: junior | O45: 0 | P45: Analista de Cultivo | Q45: [{"valor": "control, registro y seguimiento de los cultivos", "texto_original": "Realizar el control, registro y seguimiento de los cultivos"}, {"valor": "identificar y gestionar problemas relacionados con malezas, insectos y enfermedades", "texto_original": "Identificar y gestionar problemas relacionados con malezas, insectos y enfermedades"}, {"valor": "garantizar el desarrollo óptimo del cultivo y maximizar los rendimientos esperados", "texto_original": "Garantizar el desarrollo óptimo del cultivo y maximizar los rendimientos esperados"}, {"valor": "asegurar la correcta ejecución de siembras, cosechas y pulverizaciones", "texto_original": "Asegurar la correcta ejecución de siembras, cosechas y pulverizaciones"}, {"valor": "realizar mediciones de suelos y niveles de agua", "texto_original": "Realizar mediciones de suelos y niveles de agua"}, {"valor": "controlar el correcto funcionamiento de las maquinarias", "texto_original": "Controlar el correcto funcionamiento de las maquinarias"}, {"valor": "colaborar en la gestión de sistemas de información geográfica, así como en la creación, actualización y mantenimiento de los mapas detallados de cosecha y siembra", "texto_original": "Colaborar en la gestión de sistemas de información geográfica, así como en la creación, actualización y mantenimiento de los mapas detallados de cosecha y siembra"}, {"valor": "desempeñar tareas administrativas varias, como generación de informes y reportes", "texto_original": "Desempeñar tareas administrativas varias, como generación de informes y reportes"}] | S45: 7 | U45: universitario | V45: secundario Técnico agropecuario | X45: ["SAP/Cencerro", "SIMA", "Paquete Office"] | AD45: full_time | AI45: ["Prepaga para vos y tu grupo familiar", "Días adicionales de vacaciones", "Posibilidad de acceso a alojamiento"] | AJ45: 1 | AK45: 1 | AM45: demanda_real | AN45: alta | AO45: 0 | AP45: 10.0.0
A46: 1117975249 | B46: → Oferta | C46: → Match | D46: Gerente General para Maderera | E46: Buenos Aires | F46: ["San Martín", "CABA", "Luján"] | G46: presencial | I46: 1 | J46: Manufactura/Industria | K46: maderera | L46: 0 | M46: Operaciones/Logistica | N46: lead/manager | O46: 1 | P46: Liderar y supervisar la gestión integral de la empresa | Q46: [{"valor": "supervisar el funcionamiento de las tres sucursales", "texto_original": "Supervisar el funcionamiento de las tres sucursales"}, {"valor": "coordinar y dirigir áreas de logística, depósitos y operaciones comerciales", "texto_original": "Coordinar y dirigir las áreas de logística, depósitos y operaciones comerciales"}, {"valor": "impulsar el cumplimiento de objetivos", "texto_original": "Liderar y acompañar a los equipos de trabajo, impulsando el cumplimiento de objetivos"}, {"valor": "resolver incidencias operativas", "texto_original": "Resolver incidencias operativas"}, {"valor": "implementar y controlar procesos de mejora continua", "texto_original": "Implementar y controlar procesos de mejora continua"}, {"valor": "analizar indicadores de gestión y elaborar reportes de resultados", "texto_original": "Analizar indicadores de gestión y elaborar reportes de resultados"}, {"valor": "velar por la rentabilidad y el cumplimiento de los estándares de calidad", "texto_original": "Velar por la rentabilidad y el cumplimiento de los estándares de calidad"}, {"valor": "representar a la empresa ante proveedores y clientes estratégicos", "texto_original": "Representar a la empresa ante proveedores y clientes estratégicos"}] | S46: 10 | Y46: ["visión estratégica", "capacidad de organización"] | AD46: full_time | AE46: indeterminado | AK46: 0 | AM46: demanda_real | AN46: alta | AO46: 0 | AP46: 10.0.0 | AQ46: 5
A47: 1118028777 | B47: → Oferta | C47: → Match | L47: 0 | M47: Ventas/Comercial | N47: junior | O47: 0 | P47: Gestionar y ampliar cartera de clientes | Q47: [{"valor": "promover y vender productos", "texto_original": "Promover y vender productos de la compañía"}, {"valor": "realizar seguimiento de ventas y cobranzas", "texto_original": "Realizar seguimiento de las ventas y cobranzas"}, {"valor": "cumplir con objetivos de venta", "texto_original": "Cumplir con los objetivos de venta establecidos"}] | S47: 1 | Y47: ["habilidades de comunicación", "negociación"] | AD47: full_time | AI47: ["oportunidad de crecimiento profesional", "excelente ambiente de trabajo"] | AK47: 0 | AM47: demanda_real | AN47: media | AO47: 0 | AP47: 10.0.0
A48: 1117977340 | B48: → Oferta | C48: → Match | E48: CABA | F48: Palermo | G48: hibrido | J48: Servicios Financieros | K48: contabilidad | L48: 0 | M48: Administracion/Finanzas | N48: junior | O48: 0 | P48: Dar asistencia a los socios y a la responsable de administración en tareas variadas | Q48: [{"valor": "Realizar las cobranzas del estudio", "texto_original": "Realizar las cobranzas del estudio (análisis de ingresos, solicitud de retenciones, llamados a los clientes para seguimiento de pagos, armado de informes de cobranzas)"}, {"valor": "Dar de alta de proveedores y facturas en Tango", "texto_original": "Dar de alta de proveedores y facturas en Tango."}, {"valor": "Suplir las licencias de la responsable de administración", "texto_original": "Suplir las licencias de la responsable de administración en tareas de pagos a proveedores, servicios e impuestos"}, {"valor": "Realizar certificaciones on line en el CPCE CABA", "texto_original": "Realizar certificaciones on line en el CPCE CABA"}, {"valor": "Recepción de personas y correspondencia", "texto_original": "Realizar la recepción de personas y correspondencia."}, {"valor": "Compras de oficina", "texto_original": "Realizar las compras de oficina (insumos de librería, cocina, limpieza) en función del stock"}, {"valor": "Soporte en administración de personal", "texto_original": "Dar soporte en administración de personal (turnos médicos y psicotécnicos, alta de obra social, alta bancaria, ART, búsqueda de documentación para legajo)"}, {"valor": "Postear novedades en RRSS y distribuir el newsletter mensual interno", "texto_original": "Postear novedades en RRSS y distribuir el newsletter mensual interno"}, {"valor": "Organización de festejos o reuniones internas", "texto_original": "Contribuir a la organización de festejos o reuniones internas (almuerzos, cumpleaños, capacitaciones, etc.)"}, {"valor": "Asistencia a los socios en temas generales", "texto_original": "Asistir a los socios en temas generales"}] | S48: 0 | X48: ["Tango"] | Y48: ["proactivo"] | AA48: ["Tango"] | AB48: ingles | AC48: intermedio | AD48: full_time | AI48: ["empleo formal"] | AK48: 0 | AM48: demanda_real | AN48: alta | AO48: 0 | AP48: 10.0.0
A49: 1118028048 | B49: → Oferta | C49: → Match | G49: presencial | J49: Retail/Comercio | L49: 0 | M49: Ventas/Comercial | N49: junior | O49: 0 | P49: Atender y asesorar a los clientes, ofreciendo un servicio personalizado y de alta calidad | Q49: [{"valor": "promocionar y vender productos", "texto_original": "Promocionar y vender productos"}, {"valor": "mantener el espacio de trabajo limpio y ordenado", "texto_original": "Mantener el espacio de trabajo limpio y ordenado"}, {"valor": "resolver consultas y reclamos de los clientes", "texto_original": "Resolver consultas y reclamos de los clientes"}] | S49: 1 | X49: ["POS"] | Y49: ["proactividad", "adaptabilidad", "sociabilidad natural", "empatía", "autoconfianza"] | AD49: full_time | AK49: 0 | AM49: demanda_real | AN49: alta | AO49: 0 | AP49: 10.0.0
A50: 1118009703 | B50: → Oferta | C50: → Match | D50: Asesor Comercial E Commerce - Manager de redes sociales | E50: CABA | G50: presencial | H50: cerca de CABA | J50: Servicios | K50: Servicios Corporativos | L50: 0 | M50: Ventas/Comercial | N50: lead/manager | O50: 0 | P50: Asesoramiento comercial y manejo de ventas | Q50: [{"valor": "asesoramiento comercial a prospectos y emprendedores", "texto_original": "asesoramiento comercial a prospectos y emprendedores"}, {"valor": "manejo de venta de máquinas automatizadas o tecnología de producción", "texto_original": "manejo de venta de máquinas automatizadas o tecnología de producción"}, {"valor": "creación y actualización de anuncios en e-commerce", "texto_original": "creación y actualización de anuncios en e-commerce"}, {"valor": "creación de diseños e iniciativas comerciales para redes sociales, crosselling y promociones", "texto_original": "creación de diseños e iniciativas comerciales para redes sociales, crosselling y promociones"}, {"valor": "armado de diseños personalizados para clientes o prospectos", "texto_original": "armado de diseños personalizados para clientes o prospectos"}, {"valor": "supervisión a la agencia de marketing digital en cuanto a funcionamiento de campañas (Meta y Google Adwords), mailing, creación de contenido y sitio web", "texto_original": "supervisión a la agencia de marketing digital en cuanto a funcionamiento de campañas (Meta y Google Adwords), mailing, creación de contenido y sitio web"}, {"valor": "manejo de CRM y sistemas de gestión", "texto_original": "manejo de CRM y sistemas de gestión"}] | S50: 10 | X50: ["Paquete Office", "CRM Hubspot", "Photoshop o afín", "Canva o afín"] | Y50: ["Manejo de prioridades, tiempos y seguimientos", "Manejo de presupuestos", "Toleración a la presión del resultado y medición por objetivos", "Adaptabilidad y flexibilidad", "Trabajo en equipo y colaboración"] | AA50: ["Mercado Libre", "Tienda web y Market Place", "Meta y Google Adwords"] | AD50: full_time | AI50: ["Entorno laboral dinámico y motivador", "Formar parte de un equipo sólido y con trayectoria en el mercado", "Formación y capacitaciones constantes"] | AK50: 0 | AM50: demanda_real | AN50: alta | AO50: 1 | AP50: 10.0.0 | AQ50: 5

Sheet 03_Matching_ESCO
A1: ID | B1: → Oferta | C1: → NLP | D1: Título | E1: ESCO Label | F1: ESCO URI | G1: ISCO Code | H1: ISCO Label | I1: Score | J1: Método | K1: Gold OK | L1: Comentario Gold | M1: Evaluación | N1: ESCO Propuesto
A2: 1118026700 | B2: → Oferta | C2: → NLP | D2: VENDEDOR DE REPUESTOS AUTOMOTOR | E2: Vendedor de piezas de repuesto de automóviles/vendedora de piezas de repuesto de automóviles | F2: http://data.europa.eu/esco/occupation/099a901f-91a7-4d26-af2e-f385247dcf20 | G2: 5223 | H2: Asistentes de venta de tiendas y almacenes | I2: 0.677 | J2: v8.1_esco_multicriterio_validado | K2: OK | L2: Match correcto. Vendedor de repuestos -> vendedor de piezas de repuesto de automoviles. | M2: TRUE
A3: 1118026729 | B3: → Oferta | C3: → NLP | D3: Responsable de Deposito | E3: Encargado de relaciones públicas/encargada de relaciones públicas | F3: http://data.europa.eu/esco/occupation/c0489e22-6a1b-4e52-974a-eb71bbb42134 | G3: 2432 | H3: Profesionales de relaciones públicas | I3: 0.712 | J3: v8.1_esco_multicriterio_validado | K3: OK | L3: Match correcto. Responsable de deposito -> encargado de almacen / deposito. | M3: FALSE | N3: jefe de almacén/jefa de almacén
A4: 1118027243 | B4: → Oferta | C4: → NLP | D4: Abogado/a - Impuestos | E4: Abogado/abogada | F4: http://data.europa.eu/esco/occupation/974d4eab-fbee-4c52-b16e-73bdd8c25b53 | G4: 2611 | H4: Abogados | I4: 0.644 | J4: v8.1_esco_multicriterio_validado | K4: OK | L4: Match correcto. Abogado/a de impuestos -> ocupacion general abogado/abogada. | M4: TRUE
A5: 1118027261 | B5: → Oferta | C5: → NLP | D5: Supervisor de Limpieza | E5: Supervisor de servicio de limpieza/supervisora de servicio de limpieza | F5: http://data.europa.eu/esco/occupation/fae51298-03a8-4df4-829a-685dddc1580e | G5: 5151 | H5: Supervisores de mantenimiento y limpieza en oficinas, hoteles y otros establecimientos | I5: 0.707 | J5: v8.1_esco_multicriterio_validado | K5: OK | L5: Match correcto. Supervisor de limpieza -> supervisor de servicio de limpieza. | M5: TRUE
A6: 1118027276 | B6: → Oferta | C6: → NLP | D6: Ejecutivo de Cuentas SSR/SR - Presencial | E6: Técnico de contadores eléctricos/técnica de contadores eléctricos | F6: http://data.europa.eu/esco/occupation/fddb7bd8-f176-4dc8-9d12-32b6072452c9 | G6: 7411 | H6: Electricistas de obras y afines | I6: 0.592 | J6: v8.1_esco_multicriterio_validado | K6: OK | L6: v8.4: Ejecutivo de cuentas -> representante tecnico de ventas (familia correcta: ventas). Antes: tecnico de contadores electricos. | M6: FALSE | N6: Ingeniero de ventas/ingeniera de ventas
A7: 1118027662 | B7: → Oferta | C7: → NLP | D7: Farmacéutico/a para farmacias en Rio Cuarto | E7: Farmacéutico/farmacéutica | F7: http://data.europa.eu/esco/occupation/7c132147-428b-4ea3-87e1-70f7abb691ce | G7: 2262 | H7: Farmacéuticos | I7: 0.95 | J7: v8.3_diccionario_argentino_validated | K7: OK | L7: v8.5: Farmacéutico/a -> Farmacéutico/farmacéutica (ISCO 2262). CORRECTO - match exacto. | M7: TRUE
A8: 1118027834 | B8: → Oferta | C8: → NLP | D8: Vendedora Digital / Atención al Cliente | E8: Vendedor especializado/vendedora especializada | F8: http://data.europa.eu/esco/occupation/547b304b-9a72-4717-9b24-b7046df5f64e | G8: 5223 | H8: Asistentes de venta de tiendas y almacenes | I8: 0.98 | J8: v8.1_esco_multicriterio_validado | K8: OK | L8: v8.3: Corregido. Vendedora digital -> vendedor/vendedora (antes: director de comercializacion - nivel jerarquico excesivo). | M8: TRUE
A9: 1118027941 | B9: → Oferta | C9: → NLP | D9: Dibujante Tecnico | E9: Técnico medio en contabilidad/técnica media en contabilidad | F9: http://data.europa.eu/esco/occupation/bfe142b9-a049-4d41-89c4-fd2f34ac56b6 | G9: 3313 | H9: Tenedores de libros | I9: 0.701 | J9: v8.1_esco_multicriterio_validado | K9: OK | L9: Match correcto. Dibujante tecnico -> dibujante tecnico. | M9: FALSE | N9: Delineantes y dibujantes técnicos
A10: 1118028027 | B10: → Oferta | C10: → NLP | D10: OPERADOR DE AUTOELEVADORES | E10: Operador de maquinaria agrícola/operadora de maquinaria agrícola | F10: http://data.europa.eu/esco/occupation/1b8c75a9-407b-4554-a7d6-df391672c6b1 | G10: 8341 | H10: Operadores de maquinaria agrícola y forestal móvil | I10: 0.909 | J10: v8.1_esco_multicriterio_validado | K10: OK | L10: Match correcto. Operador de autoelevadores -> operador de carretilla elevadora. | M10: FALSE | N10: Operadores de autoelevadoras
A11: 1118028038 | B11: → Oferta | C11: → NLP | D11: Ejecutiva/o Comercial de Cuentas - GBA Norte | E11: Representante comercial | F11: http://data.europa.eu/esco/occupation/14031d4a-6e99-442f-b4fe-18262b6432b2 | G11: 3322 | H11: Representantes comerciales | I11: 0.95 | J11: v8.3_diccionario_argentino_validated | K11: OK | L11: v8.5: Ejecutiva/o Comercial Cuentas -> Representante comercial (ISCO 3322). Bypass diccionario. | M11: TRUE
A12: 1118028201 | B12: → Oferta | C12: → NLP | D12: 671SI Operarios ind. ALIMENTICIA c/ Tit. secundario - pres 31/10 de 10 a 1130 NUEVA Suc. SAN ISIDRO | E12: Operario de producción de alimentos/operaria de producción de alimentos | F12: http://data.europa.eu/esco/occupation/e3dc66de-99c7-4607-a82b-7244036d316d | G12: 8160 | H12: Operadores de máquinas para elaborar alimentos y productos afines | I12: 0.653 | J12: v8.1_esco_multicriterio_validado | K12: OK | L12: Match correcto. Operarios industria alimenticia -> operario de produccion de alimentos. | M12: TRUE
A13: 1118028376 | B13: → Oferta | C13: → NLP | D13: Analista administrativo/a | E13: Empleado administrativo de compañía de seguros/empleada administrativa de compañía de seguros | F13: http://data.europa.eu/esco/occupation/9a39a143-d93c-4093-ba3b-47fb67ade318 | G13: 4312 | H13: Empleados de servicios estadísticos, financieros y de seguros | I13: 0.745 | J13: v8.1_esco_multicriterio_validado | K13: OK | L13: v8.4: Analista administrativo -> empleado administrativo (CORRECTO). Antes: analista de negocios. | M13: FALSE | N13: Auxiliares contables y financieros
A14: 1118028657 | B14: → Oferta | C14: → NLP | D14: Recepcionista zona CABA (Eventual) | E14: Recepcionista | F14: http://data.europa.eu/esco/occupation/f7b04542-d8c7-42db-8475-e63b507cce82 | G14: 4226 | H14: Recepcionistas (general) | I14: 0.665 | J14: v8.1_esco_multicriterio_validado | K14: OK | L14: Match correcto. Recepcionista -> recepcionista. | M14: TRUE
A15: 1118028681 | B15: → Oferta | C15: → NLP | D15: ADMINISTRATIVA/O | E15: Empleado de oficina/empleada de oficina | F15: http://data.europa.eu/esco/occupation/6c999fc7-c6b7-4ef3-a4b9-af124a1783a2 | G15: 4110 | H15: Oficinistas generales | I15: 0.737 | J15: v8.1_esco_multicriterio_validado | K15: OK | L15: Match correcto. Administrativa/o -> empleado administrativo. | M15: TRUE
A16: 1118028828 | B16: → Oferta | C16: → NLP | D16: Búsqueda Laboral: Modelista – Vicente López (Florida Oeste) | E16: Diseñador de modelos para moldes/diseñadora de modelos para moldes | F16: http://data.europa.eu/esco/occupation/2a8d6b4c-661d-4620-8f68-2c99e78f512e | G16: 7222 | H16: Herramentistas y afines | I16: 0.616 | J16: v8.1_esco_multicriterio_validado | K16: OK | L16: Match correcto. Modelista textil -> disenador de modelos para moldes (patronista). | M16: TRUE
A17: 1118028833 | B17: → Oferta | C17: → NLP | D17: Asesor Comercial Plan de Ahorro - Volkswagen | E17: Representante comercial | F17: http://data.europa.eu/esco/occupation/14031d4a-6e99-442f-b4fe-18262b6432b2 | G17: 3322 | H17: Representantes comerciales | I17: 0.782 | J17: v8.1_esco_multicriterio_validado | K17: OK | L17: v8.4: Asesor comercial plan ahorro -> comercial de alquiler de camiones (familia comercial correcta). Antes: agente de alquiler de coches. | M17: TRUE
A18: 1118028887 | B18: → Oferta | C18: → NLP | D18: Account Executive (Hunter) | E18: Agente de empleo | F18: http://data.europa.eu/esco/occupation/42a96d07-1e1d-49ae-9399-c1f4be27ddea | G18: 3333 | H18: Agentes de empleo y contratistas de mano de obra | I18: 0.566 | J18: v8.1_esco_multicriterio_validado | K18: OK | L18: v8.4: Account Executive (Hunter) -> asistente de departamento de ventas (familia ventas correcta). Antes: agente de empleo (RRHH). | M18: TRUE
A19: 1118028891 | B19: → Oferta | C19: → NLP | D19: auxiliar contable | E19: Administrativo contable/administrativa contable | F19: http://data.europa.eu/esco/occupation/c3aae59e-1441-4b3e-bdd1-6da50dc7cf42 | G19: 3313 | H19: Tenedores de libros | I19: 0.667 | J19: v8.1_esco_multicriterio_validado | K19: OK | L19: Match correcto. Auxiliar contable -> administrativo contable. | M19: TRUE
A20: 2162667 | B20: → Oferta | C20: → NLP | D20: Gerente de Operaciones - Gastronomía corporativa y Facility management | E20: Gerente de explotación minera | F20: http://data.europa.eu/esco/occupation/23993e79-a0a0-4155-9f62-68e14ee65dab | G20: 3121 | H20: Supervisores en ingeniería de minas | I20: 0.738 | J20: v8.1_esco_multicriterio_validado | K20: OK | L20: Match correcto. Gerente de operaciones = Director de operaciones. | M20: FALSE | N20: Gerentes de restaurantes
A21: 1118022146 | B21: → Oferta | C21: → NLP | D21: Community manager | E21: Gestor de la información para las redes sociales/gestora de la información para las redes sociales | F21: http://data.europa.eu/esco/occupation/137b1d11-c4bc-4016-89ba-45345d4c71f0 | G21: 2432 | H21: Profesionales de relaciones públicas | I21: 0.95 | J21: v8.3_diccionario_argentino_validated | K21: OK | L21: v8.4 CORREGIDO: Community Manager -> Gestor de la informacion para las redes sociales (ISCO 2432). Bypass diccionario argentino. | M21: TRUE
A22: 1118025212 | B22: → Oferta | C22: → NLP | D22: Representante Técnico/a Comercial | E22: Representante técnico de ventas de maquinaria y equipo agrícolas/representante técnica de ventas de maquinaria y equipo agrícolas | F22: http://data.europa.eu/esco/occupation/2d6a1cc1-cd13-42c5-a2b1-f0183bd0d253 | G22: 2433 | H22: Profesionales de ventas técnicas y médicas (excluyendo la TIC) | I22: 0.767 | J22: v8.1_esco_multicriterio_validado | K22: OK | L22: Match correcto. Familia de ventas tecnicas correcta. | M22: TRUE
A23: 1117984105 | B23: → Oferta | C23: → NLP | D23: Venado Tuerto -Gerente de Ventas importante Concesionario Oficial Maquinaria Agr{icola | E23: Representante técnico de ventas de maquinaria y equipo agrícolas/representante técnica de ventas de maquinaria y equipo agrícolas | F23: http://data.europa.eu/esco/occupation/2d6a1cc1-cd13-42c5-a2b1-f0183bd0d253 | G23: 2433 | H23: Profesionales de ventas técnicas y médicas (excluyendo la TIC) | I23: 0.638 | J23: v8.4_multicriterio_nivel_validated | K23: OK | L23: Gerente de Ventas no es Representante. Nivel jerarquico excesivo hacia abajo. | M23: FALSE | N23: Gerentes de comercios al por mayor y al por menor
A24: 1117960588 | B24: → Oferta | C24: → NLP | D24: Asistente de Dirección / Administrativo con experiencia en Publicidad y Medios | E24: Empleado administrativo/empleada administrativa | F24: http://data.europa.eu/esco/occupation/044d78cc-f62f-4532-83a5-8e04f2889652 | G24: 3343 | H24: Secretarios administrativos y ejecutivos | I24: 0.95 | J24: v8.3_diccionario_argentino_validated | K24: OK | L24: v8.5: Asistente de Dirección -> Empleado administrativo (ISCO 3343). CORRECTO - score 0.892. | M24: TRUE
A25: 1118009739 | B25: → Oferta | C25: → NLP | D25: Administrativa Comercio Exterior (req199380) Eventual | E25: Empleado de oficina/empleada de oficina | F25: http://data.europa.eu/esco/occupation/6c999fc7-c6b7-4ef3-a4b9-af124a1783a2 | G25: 4110 | H25: Oficinistas generales | I25: 0.737 | J25: v8.1_esco_multicriterio_validado | K25: OK | L25: Match correcto. Ocupacion general administrativa. | M25: FALSE | N25: Oficinistas generales
A26: 1118000814 | B26: → Oferta | C26: → NLP | D26: Asistente Administrativo de Ventas | E26: Asistente de dirección | F26: http://data.europa.eu/esco/occupation/2a04a1df-a3b9-403e-a245-e7f93fdddd44 | G26: 3343 | H26: Secretarios administrativos y ejecutivos | I26: 0.768 | J26: v8.1_esco_multicriterio_validado | K26: OK | L26: Match exacto. | M26: FALSE | N26: Asistente de departamento de ventas
A27: 1118020225 | B27: → Oferta | C27: → NLP | D27: Representante de atención al cliente | E27: Agente de atención al cliente por chat | F27: http://data.europa.eu/esco/occupation/fde97584-d8e3-413e-a662-511c9055357e | G27: 4222 | H27: Empleados de centros de llamadas | I27: 0.599 | J27: v8.1_esco_multicriterio_validado | K27: OK | L27: Match aceptable. Familia de atencion al cliente correcta. | M27: FALSE | N27: Gestor de la atención al cliente/gestora de la atención al cliente
A28: 1118003709 | B28: → Oferta | C28: → NLP | D28: CAJERO/ENCARGADO | E28: Cajero/cajera | F28: http://data.europa.eu/esco/occupation/2b871272-bd61-4206-bd1a-0b96d7023098 | G28: 5230 | H28: Cajeros y expendedores de billetes | I28: 0.649 | J28: v8.1_esco_multicriterio_validado | K28: OK | L28: Match correcto. | M28: TRUE
A29: 1118017586 | B29: → Oferta | C29: → NLP | D29: Médica Clínica o Dermatóloga – Especialista en tratamientos estéticos inyectables | E29: Médico generalista/médica generalista | F29: http://data.europa.eu/esco/occupation/71f09c8b-a172-408c-b9e7-32e580e39ff6 | G29: 2211 | H29: Médicos generales | I29: 0.779 | J29: v8.4_multicriterio_nivel_validated | K29: OK | L29: v8.5: Médica Clínica/Dermatóloga -> Médico generalista (ISCO 2211). CORRECTO - ambos son médicos. | M29: TRUE
A30: 1118025956 | B30: → Oferta | C30: → NLP | D30: Jardinero | E30: Jardinero paisajista/jardinera paisajista | F30: http://data.europa.eu/esco/occupation/e7970c7a-7769-4002-87d3-0a8ea94fdd6f | G30: 6113 | H30: Agricultores y trabajadores calificados de huertas, invernaderos, viveros y jardines | I30: 0.684 | J30: v8.1_esco_multicriterio_validado | K30: OK | L30: Match correcto. | M30: TRUE
A31: 2164100 | B31: → Oferta | C31: → NLP | D31: Mozo/Moza | E31: Camarero/camarera | F31: http://data.europa.eu/esco/occupation/d5db9d5c-2ebf-4a54-a79a-1b7e7ff70471 | G31: 5131 | H31: Camareros de mesas | I31: 0.701 | J31: v8.1_esco_multicriterio_validado | K31: OK | L31: v8.2 CORREGIDO: Mozo -> Camarero/camarera (busqueda hibrida funciono). Antes: vinedos/agricultura. | M31: TRUE
A32: 2165052 | B32: → Oferta | C32: → NLP | D32: Electricista Industrial | E32: Electricista de obras | F32: http://data.europa.eu/esco/occupation/33960bab-4423-4808-af6c-ec2b485dba41 | G32: 7411 | H32: Electricistas de obras y afines | I32: 0.765 | J32: v8.1_esco_multicriterio_validado | K32: OK | L32: Match exacto. | M32: FALSE | N32: Electricista industrial
A33: 2165301 | B33: → Oferta | C33: → NLP | D33: Supervisor/a Administración Autos usados | E33: Director de departamento de administración/directora de departamento de administración | F33: http://data.europa.eu/esco/occupation/6e6839b6-099c-4802-906e-7f2c8203ee69 | G33: 3341 | H33: Supervisores de secretaría | I33: 0.95 | J33: v8.3_diccionario_argentino_validated | K33: OK | L33: v8.5: Supervisor/a Administración -> Director departamento administración (ISCO 3341). Bypass diccionario. | M33: FALSE
A34: 1116898892 | B34: → Oferta | C34: → NLP | D34: Chofer - Repartidor | E34: Conductor de vehículo de reparto/conductora de vehículo de reparto | F34: http://data.europa.eu/esco/occupation/0c408028-c48f-4df8-ba5d-c3d3be15f5a2 | G34: 8322 | H34: Conductores de automóviles, taxis y camionetas | I34: 0.654 | J34: v8.1_esco_multicriterio_validado | K34: OK | L34: Match exacto. | M34: TRUE
A35: 1118023904 | B35: → Oferta | C35: → NLP | D35: Operario Picking Zona Norte | E35: Reponedor/reponedora | F35: http://data.europa.eu/esco/occupation/d35f9e79-5778-43b4-8667-0e3ba1fcb19a | G35: 9334 | H35: Reponedores de estanterías | I35: 0.95 | J35: v8.3_diccionario_argentino_validated | K35: OK | L35: v8.4 CORREGIDO: Operario Picking -> Reponedor/reponedora (ISCO 9334). Bypass diccionario argentino. | M35: FALSE | N35: Responsable de pedidos de almacén
A36: 1117980907 | B36: → Oferta | C36: → NLP | D36: Operario de Almacén/Logística Z/Escobar | E36: Operario de logística de almacén/operaria de logística de almacén | F36: http://data.europa.eu/esco/occupation/808becc8-5a4e-4e71-a043-c2ea32b56ae3 | G36: 9333 | H36: Peones de carga | I36: 0.807 | J36: v8.1_esco_multicriterio_validado | K36: OK | L36: Match exacto. | M36: TRUE
A37: 1117990944 | B37: → Oferta | C37: → NLP | D37: Repositor/a Externo/a (Eventual) Moreno | E37: Reponedor/reponedora | F37: http://data.europa.eu/esco/occupation/d35f9e79-5778-43b4-8667-0e3ba1fcb19a | G37: 9334 | H37: Reponedores de estanterías | I37: 0.95 | J37: v8.3_diccionario_argentino_validated | K37: OK | L37: v8.3: CORREGIDO. Repositor -> Reponedor/reponedora (ISCO 9334). Bypass diccionario argentino resuelve homonimia lexica. | M37: TRUE
A38: 1117961954 | B38: → Oferta | C38: → NLP | D38: Asistente Administrativo General | E38: Empleado administrativo/empleada administrativa | F38: http://data.europa.eu/esco/occupation/044d78cc-f62f-4532-83a5-8e04f2889652 | G38: 3343 | H38: Secretarios administrativos y ejecutivos | I38: 0.769 | J38: v8.4_multicriterio_nivel_validated | K38: OK | L38: v8.5: Asistente Administrativo General -> Empleado administrativo (ISCO 3343). CORRECTO - score 0.780. | M38: TRUE
A39: 1117982053 | B39: → Oferta | C39: → NLP | D39: Desarrollador Angular Senior | E39: Desarrollador web/desarrolladora web | F39: http://data.europa.eu/esco/occupation/c40a2919-48a9-40ea-b506-1f34f693496d | G39: 2513 | H39: Desarrolladores web y multimedios | I39: 0.59 | J39: v8.1_esco_multicriterio_validado | K39: OK | L39: Match correcto. Angular es framework web. | M39: TRUE
A40: 1118018461 | B40: → Oferta | C40: → NLP | D40: Asesor/a de Admisiones | E40: Asesor jurídico/asesora jurídica | F40: http://data.europa.eu/esco/occupation/31854d78-3615-43a4-aa3a-c597ecb20ceb | G40: 2619 | H40: Profesionales en derecho no clasificados bajo otros epígrafes | I40: 0.792 | J40: v8.1_esco_multicriterio_validado | K40: OK | L40: Match correcto. Familia educacion. | M40: FALSE | N40: Asesor académico/asesora académica
A41: 1118018714 | B41: → Oferta | C41: → NLP | D41: Diseñador Gráfico E-commerce | E41: Dibujante de guiones gráficos | F41: http://data.europa.eu/esco/occupation/ae66ca51-e762-48b4-bd46-071dc87cb30d | G41: 2651 | H41: Artistas de artes plásticas | I41: 0.741 | J41: v8.1_esco_multicriterio_validado | K41: OK | L41: Match correcto. | M41: FALSE | N41: Diseñador gráfico/diseñadora gráfica
A42: 1118031991 | B42: → Oferta | C42: → NLP | D42: ASESOR DE VENTAS DIRECTAS | E42: Vendedor/vendedora | F42: http://data.europa.eu/esco/occupation/9ba74e8a-c40c-4228-9998-eb3c7a5c11df | G42: 5223 | H42: Asistentes de venta de tiendas y almacenes | I42: 0.95 | J42: v8.3_diccionario_argentino_validated | K42: OK | L42: v8.5: Asesor de Ventas Directas -> Vendedor/vendedora (ISCO 5223). Bypass diccionario. | M42: TRUE
A43: 1116884561 | B43: → Oferta | C43: → NLP | D43: Representante Comercial (Consumo Masivo / Grandes Cuentas) | E43: Representante comercial | F43: http://data.europa.eu/esco/occupation/14031d4a-6e99-442f-b4fe-18262b6432b2 | G43: 3322 | H43: Representantes comerciales | I43: 0.639 | J43: v8.1_esco_multicriterio_validado | K43: OK | L43: Match correcto. | M43: TRUE
A44: 1117995368 | B44: → Oferta | C44: → NLP | D44: ASESOR TÉCNICO NUTRICIÓN ANIMAL RUMIANTES | E44: Asesor de orientación profesional/asesora de orientación profesional | F44: http://data.europa.eu/esco/occupation/5d0cc30d-068a-424c-8463-f42872a7149e | G44: 2423 | H44: Especialistas en políticas y servicios de personal y afines | I44: 0.839 | J44: v8.1_esco_multicriterio_validado | K44: OK | L44: Match correcto. | M44: FALSE | N44: Nutricionista animal
A45: 2170124 | B45: → Oferta | C45: → NLP | D45: Analista de Cultivo - Roque Pérez - BA | E45: Ingeniero agrícola/ingeniera agrícola | F45: http://data.europa.eu/esco/occupation/4d5bd738-9202-4fd7-bd8c-7dbe914048de | G45: 2144 | H45: Ingenieros mecánicos | I45: 0.95 | J45: v8.3_diccionario_argentino_validated | K45: OK | L45: v8.4 CORREGIDO: Analista de Cultivo -> Ingeniero agricola/ingeniera agricola (ISCO 2144). Bypass diccionario argentino. | M45: FALSE | N45: Técnico agrícola/técnica agrícola
A46: 1117975249 | B46: → Oferta | C46: → NLP | D46: Gerente General para Maderera (PYME) | E46: Gerente de maderera | F46: http://data.europa.eu/esco/occupation/b633af32-c8c0-4481-9971-7932ea4b16b5 | G46: 1219 | H46: Directores de administración y servicios no clasificados bajo otros epígrafes | I46: 0.688 | J46: v8.1_esco_multicriterio_validado | K46: OK | L46: Match correcto. | M46: TRUE
A47: 1118028777 | B47: → Oferta | C47: → NLP | D47: Vendedor con Experiencia (Corredor) | E47: Vendedor/vendedora | F47: http://data.europa.eu/esco/occupation/9ba74e8a-c40c-4228-9998-eb3c7a5c11df | G47: 5223 | H47: Asistentes de venta de tiendas y almacenes | I47: 0.632 | J47: v8.1_esco_multicriterio_validado | K47: OK | L47: Match correcto. | M47: TRUE
A48: 1117977340 | B48: → Oferta | C48: → NLP | D48: RECEPCIONISTA ADMINISTRATIVO | E48: Empleado administrativo de compañía de seguros/empleada administrativa de compañía de seguros | F48: http://data.europa.eu/esco/occupation/9a39a143-d93c-4093-ba3b-47fb67ade318 | G48: 4312 | H48: Empleados de servicios estadísticos, financieros y de seguros | I48: 0.745 | J48: v8.1_esco_multicriterio_validado | K48: OK | L48: Match correcto. | M48: FALSE | N48: Recepcionista
A49: 1118028048 | B49: → Oferta | C49: → NLP | D49: Asesor/a de Ventas y Atención al Cliente | E49: Vendedor/vendedora | F49: http://data.europa.eu/esco/occupation/9ba74e8a-c40c-4228-9998-eb3c7a5c11df | G49: 5223 | H49: Asistentes de venta de tiendas y almacenes | I49: 0.95 | J49: v8.3_diccionario_argentino_validated | K49: OK | L49: v8.5: Asesor/a de Ventas -> Vendedor/vendedora (ISCO 5223). Bypass diccionario. | M49: TRUE
A50: 1118009703 | B50: → Oferta | C50: → NLP | D50: Asesor Comercial E Commerce - Manager de redes sociales | E50: Asistente de departamento de ventas | F50: http://data.europa.eu/esco/occupation/5c1eba1e-7820-4287-9746-4c5906320100 | G50: 4311 | H50: Empleados de contabilidad y cálculo de costos | I50: 0.683 | J50: v8.1_esco_multicriterio_validado | K50: OK | L50: Match correcto. E-commerce es ventas en red. | M50: TRUE

Sheet 04_Resumen
A1: RESUMEN - Gold Set Matching MOL
A2: Fecha generación: | B2: 2025-12-10
A4: MÉTRICAS PRINCIPALES
A5: Total ofertas Gold Set | B5: 49
A6: Matching correctos | B6: 49
A7: Precisión Matching | B7: 100.0%
A8: Versión Matching | B8: v2.1.1 BGE-M3
A10: COBERTURA NLP POR CAMPO
A11: titulo_limpio | B11: 43/49 | C11: 87.8%
A12: provincia | B12: 33/49 | C12: 67.3%
A13: area_funcional | B13: 48/49 | C13: 98.0%
A14: nivel_seniority | B14: 43/49 | C14: 87.8%
A15: experiencia_min_anios | B15: 48/49 | C15: 98.0%
A16: nivel_educativo | B16: 29/49 | C16: 59.2%
A17: skills_tecnicas_list | B17: 27/49 | C17: 55.1%
A18: jornada_laboral | B18: 41/49 | C18: 83.7%
A19: tipo_contrato | B19: 7/49 | C19: 14.3%
A22: DISTRIBUCIÓN POR ÁREA FUNCIONAL
A23: Operaciones/Logistica | B23: 14
A24: Ventas/Comercial | B24: 12
A25: Administracion/Finanzas | B25: 10
A26: Salud | B26: 3
A27: Atencion al Cliente | B27: 3
A28: Produccion/Manufactura | B28: 2
A29: Marketing | B29: 2
A30: Legal | B30: 1
A31: IT/Sistemas | B31: 1

Sheet 05_Feedback_NLP
A1: ID | B1: Campo | C1: Valor Actual NLP | D1: Valor Esperado | E1: Evidencia en Texto Original | F1: Tipo Error | G1: Sugerencia para Prompt/Regex
A2: 1118026700 | B2: provincia | C2: (vacío) | D2: Capital Federal | E2: Columna E: 'Capital Federal, Buenos Aires' | F2: campo_estructurado_ignorado | G2: Leer provincia/localidad desde campos estructurados de la oferta (columnas D-E), no solo del texto libre
A3: 1118026700 | B3: localidad | C3: (vacío) | D3: Capital Federal | E3: Columna E: 'Capital Federal, Buenos Aires' | F3: campo_estructurado_ignorado | G3: Parsear 'Localidad, Provincia' del campo Ubicación. Formato común: 'Ciudad, Provincia'
A4: 1118026700 | B4: modalidad | C4: (vacío) | D4: presencial | E4: comedor en planta', 'áreas del taller' → implica trabajo físico en sitio | F4: inferencia_faltante | G4: Inferir presencial cuando: menciona instalaciones físicas (comedor, planta, taller), no menciona remoto/híbrido
A5: 1118026700 | B5: area_funcional | C5: (vacío) | D5: Ventas/Comercial | E5: VENDEDOR', 'AMBICION DE VENTAS', 'canales de venta online' | F5: clasificacion_faltante | G5: Palabras clave: vendedor, ventas, comercial, asesor comercial → area_funcional = Ventas/Comercial
A6: 1118026700 | B6: nivel_seniority | C6: (vacío) | D6: semisenior | E6: EXPERIENCIA COMPROBABLE' (excluyente) | F6: inferencia_faltante | G6: Si pide experiencia comprobable/excluyente sin especificar años → semisenior. Si dice 'sin experiencia' o 'primer empleo' → junior
A7: 1118026700 | B7: experiencia_min_anios | C7: (vacío) | D7: 1 | E7: CON EXPERIENCIA COMPROBABLE' sugiere mínimo 1 año | F7: inferencia_faltante | G7: Cuando dice 'experiencia comprobable' sin número → asumir mínimo 1 año. Buscar patrones: 'X años', 'mínimo X', 'al menos X'
A8: 1118026700 | B8: tiene_gente_cargo | C8: (vacío) | D8: 0 | E8: No menciona supervisión, equipo a cargo, ni liderazgo | F8: default_faltante | G8: Default = 0. Solo = 1 si menciona: 'a cargo de', 'supervisar', 'liderar equipo', 'personal a cargo'
A9: 1118026700 | B9: tareas_explicitas | C9: (vacío) | D9: [{"valor": "venta de repuestos automotor", "texto_original": "VENDEDOR AUTOMOTOR"}, {"valor": "comunicación con áreas del taller", "texto_original": "excelente comunicación con las distintas áreas del taller"}, {"valor": "atención al cliente", "texto_original": "brindarle una experiencia de lujo al cliente"}] | E9: Texto describe funciones aunque no usa bullet points | F9: extraccion_incompleta | G9: No depender solo de listas con bullets. Extraer tareas de frases como: 'será responsable de', 'sus funciones incluyen', verbos de acción en contexto laboral
A10: 1118026700 | B10: rubro_empresa | C10: (vacío) | D10: post venta automotriz | E10: Somos un post venta de reconocidas marcas líderes' | F10: extraccion_faltante | G10: Buscar frases: 'somos una empresa de', 'dedicados a', 'especialistas en' para identificar rubro
A11: 1118026700 | B11: jornada_laboral | C11: (vacío) | D11: full-time | E11: comedor en planta' sugiere jornada completa | F11: inferencia_faltante | G11: Inferir full-time si: menciona comedor, horario completo, o no especifica part-time. Default = full-time para ofertas que no aclaran
A12: 1118026700 | B12: requiere_movilidad_propia | C12: (vacío) | D12: 0 | E12: No menciona auto propio, movilidad, licencia de conducir | F12: default_faltante | G12: Default = 0. Solo = 1 si menciona: 'movilidad propia', 'auto propio', 'licencia de conducir', 'vehículo'
A14: RESUMEN DE PATRONES DE ERROR
A15: Tipo Error | B15: Descripción y Acción Correctiva
A16: campo_estructurado_ignorado | B16: El NLP no está leyendo campos ya estructurados de la oferta (Ubicación, Empresa). ACCIÓN: Priorizar extracción de campos estructurados antes del texto libre.
A17: inferencia_faltante | B17: El NLP no infiere información implícita del contexto. ACCIÓN: Agregar reglas de inferencia basadas en indicadores contextuales.
A18: clasificacion_faltante | B18: El NLP no clasifica campos categóricos evidentes. ACCIÓN: Implementar diccionario de palabras clave → categoría.
A19: extraccion_incompleta | B19: El NLP extrae parcialmente cuando el formato no es lista/bullets. ACCIÓN: Usar NLP semántico, no solo regex de listas.
A20: extraccion_faltante | B20: El NLP no extrae información presente en el texto. ACCIÓN: Ampliar patrones de búsqueda.
A21: default_faltante | B21: El NLP no asigna valores default cuando corresponde. ACCIÓN: Definir defaults para campos booleanos/numéricos.

Sheet 06_Resumen_Errores
A1: ANÁLISIS DE COBERTURA NLP - 49 OFERTAS
A3: Campo | B3: Correctos | C3: Vacíos | D3: Errores | E3: % Gap | F3: Prioridad
A4: provincia | B4: 31 | C4: 16 | D4: 2 | E4: 0.367 | F4: 🔴 ALTA
A5: localidad | B5: 25 | C5: 22 | D5: 2 | E5: 0.49 | F5: 🔴 ALTA
A6: modalidad | B6: 41 | C6: 7 | D6: 1 | E6: 0.163 | F6: 🟡 MEDIA
A7: area_funcional | B7: 47 | C7: 1 | D7: 1 | E7: 0.041 | F7: 🟢 BAJA
A8: nivel_seniority | B8: 43 | C8: 6 | D8: 0 | E8: 0.122 | F8: 🟡 MEDIA
A9: experiencia_min_anios | B9: 46 | C9: 1 | D9: 2 | E9: 0.061 | F9: 🟢 BAJA
A11: ERRORES CRÍTICOS DETECTADOS
A13: ID | B13: Tipo Error | C13: Campo Afectado | D13: Descripción
A14: 1118027243 | B14: valores_booleanos | C14: provincia, localidad, modalidad, area_funcional | D14: Todos los campos retornan TRUE en lugar del valor de texto
A15: 1118026729 | B15: valores_booleanos | C15: provincia, localidad | D15: provincia='FALSO\nCapital Federal', localidad=FALSE
A16: 1117984105 | B16: parseo_numerico | C16: experiencia_min_anios | D16: Extrae 35 años cuando debería ser 2 (confunde rango edad 35-50 con experiencia)
A17: 1118023904 | B17: parseo_numerico | C17: experiencia_min_anios | D17: Extrae 20 años (confunde rango edad 20-45 con experiencia)
A18: 1118026700 | B18: campo_estructurado_ignorado | C18: provincia, localidad, modalidad, area_funcional | D18: No lee campos ya estructurados de la oferta original
A20: IDs CON CAMPOS VACÍOS (PRINCIPALES)
A22: Campo | B22: IDs afectados (16 vacios provincia, 22 localidad)
A23: provincia (16 vacíos) | B23: 1118026700, 1118027941, 1118028657, 1118028833, 2162667, 1118025212, 1117960588, 1118000814, 1118025956, 2165052, 1117961954, 1117982053, 1118018714, 1118031991, 1118028777, 1118028048
A24: localidad (22 vacíos) | B24: 1118026700, 1118027941, 1118028833, 2162667, 1118025212, 1117960588, 1118009739, 1118000814, 1118025956, 2165052, 1118023904, 1117961954, 1117982053, 1118018461, 1118018714, 1118031991, 1116884561, 1117995368, 1117975249, 1118028777, 1118028048, 1118009703

Sheet 07_Reglas_Mejora
A1: REGLAS DE MEJORA PARA NLP - PROMPT/REGEX
A3: Prioridad | B3: Categoría | C3: Problema | D3: Regla de Mejora | E3: Implementación Sugerida
A4: 🔴 1 | B4: CAMPOS ESTRUCTURADOS | C4: provincia y localidad vacíos en 36-49% de casos | D4: PRIORIZAR extracción de campos estructurados de la oferta ANTES de analizar texto libre | E4: Parsear columna 'Ubicación' con formato 'Localidad, Provincia'. Usar regex: ^(.+),\s*(.+)$ para separar
A5: 🔴 2 | B5: VALORES BOOLEANOS | C5: Algunos campos retornan TRUE/FALSE en lugar de texto | D5: VALIDAR tipo de dato antes de asignar. Si es booleano, marcar como error y reintentar | E5: if isinstance(valor, bool): raise ValueError('Campo debe ser string'). Revisar lógica de parsing JSON
A6: 🔴 3 | B6: EXPERIENCIA vs EDAD | C6: Confunde rangos de edad (35-50 años) con experiencia requerida | D6: Distinguir contexto: 'Edad mínima/máxima' vs 'experiencia mínima' | E6: Regex negativo: NO extraer números precedidos de 'edad', 'años de edad'. SÓLO extraer si dice 'experiencia de X años' o 'X años de experiencia'
A7: 🟡 4 | B7: MODALIDAD INFERIDA | C7: 16% de ofertas sin modalidad detectada | D7: Inferir modalidad del CONTEXTO cuando no es explícita | E7: Si menciona: 'comedor en planta', 'taller', 'sucursal', 'presencial obligatorio' → presencial. Si no menciona remoto/híbrido → default presencial
A8: 🟡 5 | B8: SENIORITY INFERIDO | C8: 12% de ofertas sin nivel de seniority | D8: Inferir seniority de indicadores contextuales | E8: junior: 'sin experiencia', 'primer empleo', '0-1 año'. semisenior: 'experiencia comprobable', '2-4 años'. senior: '5+ años', 'líder'. lead/manager: 'gerente', 'director', 'a cargo de equipo'
A9: 🟡 6 | B9: AREA FUNCIONAL | C9: 4% de ofertas sin área funcional clasificada | D9: Usar diccionario de palabras clave → categoría | E9: vendedor|ventas|comercial → Ventas. admin|contable|finanzas → Admin. operario|logística|almacén → Operaciones. desarrollador|programador|IT → IT/Sistemas
A10: 🟢 7 | B10: TAREAS EXPLICITAS | C10: No extrae tareas cuando no hay bullet points | D10: No depender SOLO de listas con bullets. Buscar verbos de acción en contexto | E10: Patrones: 'será responsable de', 'sus funciones incluyen', 'deberá', 'tendrá a cargo'. Extraer frases con verbos infinitivos
A11: 🟢 8 | B11: DEFAULTS FALTANTES | C11: Campos booleanos/numéricos sin valor default | D11: Asignar valores DEFAULT cuando no hay información | E11: tiene_gente_cargo: default=0. requiere_movilidad_propia: default=0. jornada_laboral: default='full_time'. modalidad: default='presencial'
A12: 🟢 9 | B12: RUBRO EMPRESA | C12: Muchas ofertas sin rubro identificado | D12: Buscar frases descriptivas de la empresa | E12: Patrones: 'somos una empresa de', 'dedicados a', 'líder en', 'especialistas en'. Extraer sustantivo siguiente
A13: 🟢 10 | B13: VALIDACIÓN CRUZADA | C13: No hay validación de coherencia entre campos | D13: Validar que los valores extraídos sean coherentes entre sí | E13: Si experiencia=35 y seniority='junior' → ERROR. Si area='IT' y titulo='jardinero' → revisar. Implementar reglas de validación post-extracción
A14: 🟢 11 | B14: NORMALIZACIÓN UBICACIÓN | C14: Variantes de nombres (CABA vs Capital Federal vs Buenos Aires) | D14: Normalizar nombres de provincias y localidades | E14: Diccionario: {'CABA': 'Capital Federal', 'Bs As': 'Buenos Aires', 'Cba': 'Córdoba'}. Aplicar antes de guardar
A15: 🟢 12 | B15: EXPERIENCIA IMPLÍCITA | C15: No detecta 'experiencia comprobable' sin número | D15: Asignar valor mínimo cuando menciona experiencia sin especificar | E15: experiencia comprobable' sin número → experiencia_min=1. 'amplia experiencia' → experiencia_min=3. 'sin experiencia' → experiencia_min=0
A17: EJEMPLOS DE REGEX SUGERIDOS
A19: Campo | B19: Regex Pattern | C19: Ejemplo Match
A20: ubicacion_split | B20: ^(.+),\s*(.+)$ | C20: Capital Federal, Buenos Aires' → ['Capital Federal', 'Buenos Aires']
A21: experiencia_anios | B21: (?:experiencia|exp\.?)\s*(?:de\s+)?(?:mínima?\s+)?(?:de\s+)?(\d+)\s*(?:a(?:ños?)?|años?) | C21: experiencia mínima de 2 años' → 2
A22: experiencia_negativo | B22: (?<!edad\s)(?<!años\sde\s)(\d+)\s*años.*experiencia | C22: Evita capturar 'edad mínima 35 años'
A23: modalidad | B23: (?:modalidad|trabajo)\s*[:\-]?\s*(presencial|remoto|híbrido|hibrida|home\s*office) | C23: Modalidad: Híbrida' → 'híbrido'
A24: seniority_keywords | B24: (junior|sr\.?|ssr\.?|semi[-\s]?senior|senior|lead|manager|gerente|jefe|director) | C24: Ejecutivo SSR/SR' → 'semisenior'
A25: tiene_gente_cargo | B25: (?:a\s+cargo\s+de|supervisar|liderar|coordinar)\s*(?:equipo|personal|personas) | C25: personal a cargo' → tiene_gente_cargo=1
A26: licencia_conducir | B26: (?:licencia|registro|carnet)\s*(?:de\s+)?(?:conducir|manejo) | C26: licencia de conducir vigente' → licencia_conducir=1
A27: movilidad_propia | B27: (?:movilidad|auto|vehículo)\s*propi[oa] | C27: movilidad propia excluyente' → requiere_movilidad_propia=1

Sheet 08_Feedback_Matching
A1: FEEDBACK MATCHING ESCO - 18 CASOS CON ERROR
A3: ID | B3: Título Oferta | C3: ESCO Actual (ERROR) | D3: ESCO Propuesto (CORRECTO) | E3: Score | F3: Tipo Error | G3: Señales NLP Ignoradas | H3: Causa Raíz | I3: Regla Correctiva | J3: Prioridad
A4: 1118027941 | B4: Dibujante Tecnico | C4: Técnico medio en contabilidad (ISCO 3313) | D4: Delineantes y dibujantes técnicos | E4: 0.701 | F4: DOMINIO_INCORRECTO | G4: skills: AutoCAD, Solidworks | sector: metalurgia | tareas: realización de planos | H4: Matching por título ignora skills técnicas. 'Técnico' se asocia erróneamente con contabilidad | I4: Si skills contiene [AutoCAD, Solidworks, CAD, planos] → forzar familia ISCO 311x (Delineantes) | J4: 🔴 CRÍTICA
A5: 1118028027 | B5: OPERADOR DE AUTOELEVADORES | C5: Operador de maquinaria agrícola (ISCO 8341) | D5: Operadores de autoelevadoras | E5: 0.909 | F5: DOMINIO_INCORRECTO | G5: sector: Transporte/Logistica | tareas: manejo autoelevadores | licencia: tipo O | H5: Autoelevador ≠ maquinaria agrícola. Embeddings confunden 'maquinaria' | I5: Diccionario: autoelevador|montacargas|forklift → ISCO 8344 (Operadores de carretillas) | J5: 🔴 CRÍTICA
A6: 1118018714 | B6: Diseñador Gráfico E-commerce | C6: Dibujante de guiones gráficos (ISCO 2651) | D6: Diseñador gráfico/diseñadora gráfica | E6: 0.741 | F6: DOMINIO_INCORRECTO | G6: skills: Photoshop, Illustrator | area: Marketing | tareas: contenido visual e-commerce | H6: Diseñador gráfico ≠ Dibujante de guiones (storyboard). Confusión semántica | I6: Si skills contiene [Photoshop, Illustrator, diseño gráfico] → ISCO 2166 (Diseñadores gráficos) | J6: 🔴 CRÍTICA
A7: 1117995368 | B7: ASESOR TÉCNICO NUTRICIÓN ANIMAL RUMIANTES | C7: Asesor de orientación profesional (ISCO 2423) | D7: Nutricionista animal | E7: 0.839 | F7: DOMINIO_INCORRECTO | G7: sector: Nutrición Animal | rubro: rumiantes | formación: Veterinario/Zootecnista | H7: Asesor' genera match con 'orientación profesional' ignorando 'nutrición animal' | I7: Si título contiene 'nutrición animal' → ISCO 3240 (Técnicos veterinarios) | J7: 🔴 CRÍTICA
A8: 2162667 | B8: Gerente de Operaciones - Gastronomía | C8: Gerente de explotación minera (ISCO 3121) | D8: Gerentes de restaurantes | E8: 0.738 | F8: SECTOR_IGNORADO | G8: título: Gastronomía corporativa | tareas: calidad, higiene, KPIs gastronomía | H8: Gerente de Operaciones' matchea con minería ignorando el sector gastronómico | I8: Si título contiene [gastronomía, restaurante, catering] → ISCO 1412 (Gerentes restaurantes) | J8: 🔴 CRÍTICA
A9: 1117984105 | B9: Gerente de Ventas Concesionario Maquinaria | C9: Representante técnico de ventas (ISCO 2433) | D9: Gerentes de comercios al por mayor | E9: 0.638 | F9: NIVEL_JERARQUICO | G9: seniority: lead/manager | tiene_gente_cargo: 1 | tareas: liderar equipo | H9: GERENTE bajado a REPRESENTANTE. Nivel jerárquico ignorado completamente | I9: Si seniority=lead/manager Y tiene_gente_cargo=1 → priorizar ISCO 1xxx (Directores/Gerentes) | J9: 🔴 CRÍTICA
A10: 1118018461 | B10: Asesor/a de Admisiones | C10: Asesor jurídico/asesora jurídica (ISCO 2619) | D10: Asesor académico/asesora académica | E10: 0.792 | F10: HOMONIMIA | G10: sector: Educacion | tareas: admisión universidad, charlas, CRM | H10: Asesor' es polisémico. Sin contexto de sector, matchea con jurídico | I10: Si sector=Educacion Y título contiene 'admisión' → ISCO 2359 (Profesionales educación) | J10: 🟡 ALTA
A11: 1118026729 | B11: Responsable de Deposito | C11: Encargado de relaciones públicas (ISCO 2432) | D11: Jefe de almacén/jefa de almacén | E11: 0.712 | F11: DOMINIO_INCORRECTO | G11: area: Operaciones/Logistica | tareas: inventarios, stocks, depósito | H11: Responsable' matchea con RRPP. Ignora completamente 'depósito' y tareas logísticas | I11: Si tareas contienen [inventario, stock, depósito, almacén] → ISCO 4321 (Empleados almacén) | J11: 🟡 ALTA
A12: 1118027276 | B12: Ejecutivo de Cuentas SSR/SR | C12: Técnico de contadores eléctricos (ISCO 7411) | D12: Ingeniero de ventas | E12: 0.592 | F12: DOMINIO_INCORRECTO | G12: area: Ventas/Comercial | tareas: prospección clientes, CRM, propuestas comerciales | H12: Score bajo (0.59) indica incertidumbre. Match absurdo con electricidad | I12: Si area=Ventas/Comercial Y tareas contienen [prospección, CRM, comercial] → ISCO 3322 | J12: 🟡 ALTA
A13: 1118028376 | B13: Analista administrativo/a | C13: Empleado administrativo de seguros (ISCO 4312) | D13: Auxiliares contables y financieros | E13: 0.745 | F13: ESPECIFICIDAD | G13: tareas: comex, importación/exportación | sector: Servicios Financieros | H13: Clasificación muy específica (seguros) cuando es admin general con foco comex | I13: Si tareas contienen [importación, exportación, comex] → ISCO 3331 (Agentes aduanas) | J13: 🟡 ALTA
A14: 2165052 | B14: Electricista Industrial | C14: Electricista de obras (ISCO 7411) | D14: Electricista industrial | E14: 0.765 | F14: ESPECIFICIDAD | G14: tareas: tableros eléctricos control y potencia, mantenimiento industrial | H14: Electricista de OBRAS ≠ Electricista INDUSTRIAL. Falta granularidad | I14: Si título contiene 'industrial' Y tareas tienen [tableros, control, potencia] → ISCO 7412 | J14: 🟡 ALTA
A15: 1118000814 | B15: Asistente Administrativo de Ventas | C15: Asistente de dirección (ISCO 3343) | D15: Asistente de departamento de ventas | E15: 0.768 | F15: ESPECIFICIDAD | G15: area: Admin/Finanzas | tareas: pedidos venta, reportes ventas, cobranzas | H15: Asistente de DIRECCIÓN ≠ Asistente de VENTAS. Ignora el contexto comercial | I15: Si título contiene 'ventas' Y area=Admin → ISCO 4311 (Auxiliares contables) | J15: 🟢 MEDIA
... A21: 2165301 | B21: Supervisor/a Administración Autos usados | C21: Director departamento administración (ISCO 3341) | D21: (sin propuesta) | E21: 0.95 | F21: MATCH_ACEPTABLE | G21: seniority: semisenior | tiene_gente_cargo: 1 | sector: Automotriz | H21: Supervisor ≈ Director depto. Score alto (0.95). Posible falso negativo en evaluación | I21: Revisar criterio de evaluación humana - puede ser match aceptable | J21: 🟢 BAJA
A24: ANÁLISIS DE PATRONES DE ERROR
A26: Tipo Error | B26: Cantidad | C26: Descripción
A27: DOMINIO_INCORRECTO | B27: 6 | C27: El matching asigna una ocupación de un dominio completamente diferente (ej: Dibujante → Contable)
A28: ESPECIFICIDAD | B28: 5 | C28: El match es de la familia correcta pero demasiado específico o genérico
A29: NIVEL_JERARQUICO | B29: 3 | C29: El nivel jerárquico no coincide (ej: Gerente matcheado como Representante)
A30: SECTOR_IGNORADO | B30: 1 | C30: El sector de la empresa/industria no se consideró en el matching
A31: HOMONIMIA | B31: 1 | C31: Palabras polisémicas generan matches incorrectos (ej: 'Asesor' → jurídico vs académico)
A32: ROL_PRIMARIO | B32: 1 | C32: En títulos compuestos, no se prioriza el rol principal
A33: MATCH_ACEPTABLE | B33: 1 | C33: Posible falso negativo en la evaluación humana
A36: PROPUESTA DE MEJORA DEL PIPELINE DE MATCHING
A38: PIPELINE ACTUAL | B38: PIPELINE PROPUESTO
A39: 1. titulo_limpio | B39: 1. titulo_limpio + mision_rol + tareas_explicitas
A40: 2. Embedding → ESCO labels | B40: 2. Embedding → Top 10 candidatos ESCO
A41: 3. Seleccionar mejor score | B41: 3. FILTRAR candidatos por: sector_empresa, area_funcional, nivel_seniority
A42: 4. (no hay validación) | B42: 4. RE-RANKEAR con skills_tecnicas_list (peso alto para skills discriminantes)
B43: 5. VALIDAR coherencia: nivel_educativo vs ISCO (2xxx requiere universitario)
A46: REGLAS DE NEGOCIO PARA IMPLEMENTAR
A48: # | B48: Regla | C48: Condición | D48: Acción
A49: R1 | B49: Skills CAD/Diseño | C49: skills_tecnicas contiene [AutoCAD, Solidworks, CAD, planos, Revit] | D49: Forzar ISCO 311x (Delineantes) o 216x (Diseñadores)
A50: R2 | B50: Skills Diseño Gráfico | C50: skills_tecnicas contiene [Photoshop, Illustrator, InDesign, Figma] | D50: Forzar ISCO 2166 (Diseñadores gráficos)
A51: R3 | B51: Autoelevador/Montacargas | C51: titulo contiene [autoelevador, montacargas, forklift, carretilla] | D51: Forzar ISCO 8344 (Operadores carretillas elevadoras)
A52: R4 | B52: Nivel Gerencial | C52: seniority=lead/manager Y tiene_gente_cargo=1 | D52: Priorizar ISCO 1xxx (Directores y gerentes)
A53: R5 | B53: Formación vs ISCO | C53: nivel_educativo=secundario Y candidato ISCO 2xxx | D53: Descartar candidato (2xxx requiere universitario)
A54: R6 | B54: Sector Gastronomía | C54: titulo/tareas contiene [gastronomía, restaurante, catering, chef] | D54: Priorizar ISCO 141x (Gerentes hoteles/restaurantes)
A55: R7 | B55: Sector Educación | C55: sector=Educacion Y titulo contiene [admisión, académico, docente] | D55: Priorizar ISCO 23xx (Profesionales educación)
A56: R8 | B56: Nutrición Animal | C56: titulo/rubro contiene [nutrición animal, veterinario, zootecnia] | D56: Forzar ISCO 324x (Técnicos veterinarios)
A57: R9 | B57: Tareas Logísticas | C57: tareas contiene [inventario, stock, almacén, depósito, picking] | D57: Priorizar ISCO 432x (Empleados almacén) o 933x (Peones)
A58: R10 | B58: Electricista Industrial | C58: titulo contiene 'industrial' Y tareas tienen [tableros, potencia, control] | D58: ISCO 7412 (Electricistas industriales) no 7411 (obras)
A59: R11 | B59: Título Compuesto | C59: titulo tiene formato 'ROL1 / ROL2' o 'ROL1 - ROL2' | D59: Priorizar primera palabra/rol del título
A60: R12 | B60: Score Bajo + Dominio | C60: score < 0.65 Y area_funcional no coincide con candidato | D60: Rechazar match, buscar en segunda pasada con más contexto
A63: CONCLUSIÓN: RESPONSABILIDAD DEL ERROR
A65: Componente | B65: % Responsabilidad | C65: Explicación
A66: MATCHING (pipeline) | B66: 0.7 | C66: El matching usa SOLO el título, ignorando skills, sector, tareas y nivel educativo que el NLP sí extraía correctamente
A67: NLP (extracción) | B67: 0.2 | C67: Algunos campos vacíos (ubicación) y area_funcional a veces mal clasificada (ej: Dibujante → Operaciones en vez de Ingeniería)
A68: ESCO (taxonomía) | B68: 0.1 | C68: Algunas ocupaciones argentinas no tienen equivalente exacto en ESCO europeo (ej: 'autoelevador' vs 'carretilla')

Sheet 09_Feedback_Skills_NLP
A1: FEEDBACK EXTRACCIÓN DE SKILLS - ANÁLISIS DE GAPS
A3: HALLAZGO PRINCIPAL
A4: Las skills que el NLP SÍ extrae son CORRECTAS (extraídas literalmente del texto, no inferidas).
A5: El problema es de COBERTURA: el NLP NO EXTRAE muchas skills que están explícitas en el texto original.
A7: COBERTURA ACTUAL
A8: Campo | B8: Cobertura | C8: Gap
A9: skills_tecnicas_list | B9: 27/49 (55.1%) | C9: 22 ofertas sin datos
A10: soft_skills_list | B10: 32/49 (65.3%) | C10: 17 ofertas sin datos
A12: CASOS CON SKILLS NO EXTRAÍDAS (20 de 49 ofertas)
A14: ID | B14: Título | C14: Skills Faltantes (en texto original) | D14: Tipo de Gap | E14: Problema Identificado
A15: 1118027243 | B15: Abogado/a - Impuestos | C15: Inglés (dominio oral y escrito) | D15: IDIOMAS_FALTANTES | E15: Idiomas no se extraen como skill técnica
A16: 1118027662 | B16: Farmacéutico/a | C16: dispensa medicamentos, trazabilidad, control stock farmacéutico | D16: SKILLS_OPERATIVAS | E16: Skills específicas del rubro farmacéutico no reconocidas
A17: 1118028027 | B17: Operador Autoelevadores | C17: manejo autoelevadores, carnet habilitante | D17: TECNOLOGIAS | E17: Skill principal del puesto no extraída - no reconoce 'autoelevador'
A18: 1118028657 | B18: Recepcionista | C18: atención telefónica, manejo documentación | D18: SKILLS_OPERATIVAS | E18: Skills básicas de recepción no extraídas
A19: 1118028833 | B19: Asesor Comercial | C19: venta telefónica, planes de ahorro, negociación (técnica) | D19: HERRAMIENTAS | E19: Técnicas de venta no reconocidas como skills
A20: 1118028891 | B20: Auxiliar Contable | C20: conciliaciones bancarias, manejo cheques, cierres balances | D20: SKILLS_OPERATIVAS | E20: Skills contables específicas no extraídas
A21: 2162667 | B21: Gerente de Operaciones | C21: KPIs, gestión de procesos, normas calidad/seguridad | D21: SKILLS_OPERATIVAS | E21: Skills gerenciales no reconocidas
A22: 1118025212 | B22: Representante Técnico Comercial | C22: conocimientos agronómicos, agro insumos | D22: TECNOLOGIAS | E22: Conocimiento sectorial agro no extraído
A23: 1117984105 | B23: Gerente de Ventas Maquinaria | C23: maquinaria agrícola (conocimiento) | D23: TECNOLOGIAS | E23: Conocimiento de producto no extraído
A24: 1118009739 | B24: Administrativa Comex | C24: facturación, comercio exterior, ciclos de pago | D24: SKILLS_OPERATIVAS | E24: Skills de comercio exterior no extraídas
A25: 1118003709 | B25: Cajero/Encargado | C25: Rappi, Pedidos Ya, Excel, arqueos caja, sistema gestión | D25: HERRAMIENTAS | E25: Plataformas delivery y herramientas no reconocidas
A26: 1118025956 | B26: Jardinero | C26: jardinería, corte césped, cuidado plantas, limpieza vidrios | D26: SKILLS_OPERATIVAS | E26: Skills del oficio no extraídas
... A34: 1117975249 | B34: Gerente General | C34: gestión sucursales, indicadores gestión, logística | D34: SKILLS_OPERATIVAS | E34: Skills gerenciales no reconocidas
A36: CASO CRÍTICO: ID 1117982053 - Desarrollador Angular Senior
A38: Tecnología en Texto | B38: Extraída? | C38: Comentario
A39: Angular | B39: ✅ SÍ | C39: Framework principal - reconocido
A40: Webpack | B40: ✅ SÍ | C40: Bundler - reconocido
A41: AWS | B41: ❌ NO | C41: Cloud provider NO en diccionario
A42: TypeScript | B42: ❌ NO | C42: Lenguaje NO reconocido
A43: NodeJS | B43: ❌ NO | C43: Runtime NO reconocido
A44: CloudFront | B44: ❌ NO | C44: Servicio AWS NO reconocido
A45: CloudFormation | B45: ❌ NO | C45: Servicio AWS NO reconocido
A46: Module Federation | B46: ❌ NO | C46: Técnica Webpack NO reconocida
A47: Lazy Loading | B47: ❌ NO | C47: Patrón NO reconocido
A48: React, Vue, Svelte | B48: ❌ NO | C48: Frameworks alternativos NO reconocidos
A49: RESULTADO | B49: 2/12 (16.7%) | C49: Cobertura MUY BAJA para oferta IT
A52: PATRONES DE FALLA IDENTIFICADOS
A54: # | B54: Patrón de Falla | C54: Ejemplos | D54: Solución Propuesta para el Pipeline
A55: P1 | B55: TECNOLOGÍAS CLOUD NO RECONOCIDAS | C55: AWS, CloudFront, CloudFormation, Azure, GCP | D55: Agregar diccionario de servicios cloud: aws_services = ['EC2', 'S3', 'Lambda', 'CloudFront', 'CloudFormation', 'RDS', ...]
A56: P2 | B56: FRAMEWORKS/LIBRERÍAS SECUNDARIAS IGNORADAS | C56: React, Vue, Svelte, TypeScript, NodeJS | D56: Extraer TODAS las tecnologías mencionadas usando lista exhaustiva de frameworks/lenguajes, no solo el del título
A57: P3 | B57: IDIOMAS NO EXTRAÍDOS COMO SKILL | C57: Inglés, Portugués en requisitos | D57: Crear regex para idiomas: r'(ingl[eé]s|portugu[eé]s|franc[eé]s|alem[aá]n)\s*(avanzado|intermedio|básico)?'
A58: P4 | B58: PLATAFORMAS DELIVERY/ECOMMERCE NO RECONOCIDAS | C58: Rappi, Pedidos Ya, Mercado Libre, TiendaNube | D58: Diccionario plataformas LATAM: ['Rappi', 'PedidosYa', 'Mercado Libre', 'TiendaNube', 'Shopify', ...]
A59: P5 | B59: SKILLS OPERATIVAS DE OFICIOS NO EXTRAÍDAS | C59: jardinería, picking, arqueo caja, dispensa | D59: Diccionarios por RUBRO: retail_skills, farmacia_skills, logistica_skills, gastronomia_skills
A60: P6 | B60: CERTIFICACIONES/HABILITACIONES IGNORADAS | C60: carnet autoelevador, matrícula profesional, libreta sanitaria | D60: Campo separado 'certificaciones_requeridas' con regex: r'(carnet|matrícula|habilitación|libreta)\s+\w+'
A61: P7 | B61: SOFT SKILLS VACÍAS EN TEXTOS TÉCNICOS | C61: Ofertas IT sin soft skills extraídas | D61: Buscar soft skills en TODO el texto, no solo en sección 'requisitos'. Usar NER para detectar competencias
A64: DICCIONARIOS SUGERIDOS PARA IMPLEMENTAR
A66: Diccionario | B66: Contenido Sugerido
A67: cloud_services | B67: AWS, EC2, S3, Lambda, CloudFront, CloudFormation, RDS, DynamoDB, Azure, GCP, Firebase, Heroku, DigitalOcean
A68: frontend_frameworks | B68: React, Angular, Vue, Svelte, Next.js, Nuxt, Gatsby, Remix, Astro, SolidJS
A69: backend_frameworks | B69: NodeJS, Express, NestJS, Django, Flask, FastAPI, Spring Boot, .NET, Laravel, Rails
A70: lenguajes_programacion | B70: TypeScript, JavaScript, Python, Java, C#, Go, Rust, PHP, Ruby, Kotlin, Swift
A71: plataformas_latam | B71: Rappi, PedidosYa, Mercado Libre, TiendaNube, Shopify, WooCommerce, VTEX, Magento
A72: herramientas_oficina | B72: Tango, SAP, Oracle, Salesforce, HubSpot, Monday, Notion, Slack, Teams, Zoom
A73: skills_logistica | B73: picking, RF, WMS, autoelevador, montacargas, forklift, inventario, stock, almacén, depósito
A74: skills_retail | B74: planograma, POP, góndola, reposición, vencimientos, merma, quiebre, PDV
A75: skills_contables | B75: conciliación bancaria, arqueo, balance, asiento contable, libro diario, mayor, AFIP
A76: certificaciones | B76: carnet autoelevador, matrícula profesional, libreta sanitaria, habilitación, licencia conducir
A79: IMPACTO EN EL MATCHING ESCO
A81: Si el NLP extrajera estas skills, el Matching podría:
A82: ✅ | B82: Filtrar candidatos ESCO por skills discriminantes (AutoCAD → solo ocupaciones de diseño)
A83: ✅ | B83: Distinguir Electricista Industrial vs Obras por skills específicas (tableros potencia vs cableado)
A84: ✅ | B84: Identificar nivel jerárquico por skills gerenciales (KPIs, gestión procesos → Gerente)
A85: ✅ | B85: Detectar sector/rubro por skills operativas (picking, RF → Logística, no Retail)
A86: ✅ | B86: Evitar matches absurdos como Dibujante Técnico → Contable (AutoCAD nunca matchearía contabilidad)

Sheet 10_Matching_Skills_ESCO
A1: Skill Original (NLP) | B1: Tipo | C1: Categoría Agrupada | D1: ESCO Skill (Español) | E1: ESCO Skill (English) | F1: ESCO URI | G1: ESCO Grupo L1 | H1: ESCO Grupo L2 | I1: Es Digital | J1: Frecuencia
A2: paquete office | B2: Técnica | C2: Software Ofimático | D2: utilizar software de hojas de cálculo | E2: use spreadsheet software | F2: http://data.europa.eu/esco/skill/1973c966-f236-40c9-b2d4-5d71a89019be | G2: S5 - Trabajar con ordenadores | H2: S5.5 - Análisis datos digitales | I2: Sí | J2: 8
A3: office | B3: Técnica | C3: Software Ofimático | D3: utilizar software ofimático | E3: use office software | F3: http://data.europa.eu/esco/skill/1973c966-office | G3: S5 - Trabajar con ordenadores | H3: S5.5 - Análisis datos digitales | I3: Sí | J3: 3
A4: ms office | B4: Técnica | C4: Software Ofimático | D4: utilizar software ofimático | E4: use office software | F4: http://data.europa.eu/esco/skill/1973c966-office | G4: S5 - Trabajar con ordenadores | H4: S5.5 - Análisis datos digitales | I4: Sí | J4: 2
A5: microsoft office suite | B5: Técnica | C5: Software Ofimático | D5: utilizar software ofimático | E5: use office software | F5: http://data.europa.eu/esco/skill/1973c966-office | G5: S5 - Trabajar con ordenadores | H5: S5.5 - Análisis datos digitales | I5: Sí | J5: 1
A6: manejo avanzado de paquete office | B6: Técnica | C6: Software Ofimático | D6: utilizar software ofimático | E6: use office software | F6: http://data.europa.eu/esco/skill/1973c966-office | G6: S5 - Trabajar con ordenadores | H6: S5.5 - Análisis datos digitales | I6: Sí | J6: 1
A7: excel | B7: Técnica | C7: Hojas de Cálculo | D7: utilizar software de hojas de cálculo | E7: use spreadsheet software | F7: http://data.europa.eu/esco/skill/1973c966-f236-40c9-b2d4-5d71a89019be | G7: S5 - Trabajar con ordenadores | H7: S5.5 - Análisis datos digitales | I7: Sí | J7: 4
A8: excel avanzado | B8: Técnica | C8: Hojas de Cálculo | D8: utilizar software de hojas de cálculo | E8: use spreadsheet software | F8: http://data.europa.eu/esco/skill/1973c966-f236-40c9-b2d4-5d71a89019be | G8: S5 - Trabajar con ordenadores | H8: S5.5 - Análisis datos digitales | I8: Sí | J8: 2
A9: planillas | B9: Técnica | C9: Hojas de Cálculo | D9: utilizar software de hojas de cálculo | E9: use spreadsheet software | F9: http://data.europa.eu/esco/skill/1973c966-f236-40c9-b2d4-5d71a89019be | G9: S5 - Trabajar con ordenadores | H9: S5.5 - Análisis datos digitales | I9: Sí | J9: 1
A10: herramientas informáticas | B10: Técnica | C10: Informática General | D10: utilizar herramientas informáticas | E10: use computer equipment | F10: http://data.europa.eu/esco/skill/computer-equipment | G10: S5 - Trabajar con ordenadores | H10: S5.0 - Uso general | I10: Sí | J10: 1
A11: computación en general | B11: Técnica | C11: Informática General | D11: utilizar herramientas informáticas | E11: use computer equipment | F11: http://data.europa.eu/esco/skill/computer-equipment | G11: S5 - Trabajar con ordenadores | H11: S5.0 - Uso general | I11: Sí | J11: 1
A12: herramientas de google | B12: Técnica | C12: Informática General | D12: utilizar herramientas informáticas | E12: use computer equipment | F12: http://data.europa.eu/esco/skill/computer-equipment | G12: S5 - Trabajar con ordenadores | H12: S5.0 - Uso general | I12: Sí | J12: 1
A13: crm | B13: Técnica | C13: Sistemas CRM | D13: utilizar software CRM | E13: use customer relationship management software | F13: http://data.europa.eu/esco/skill/crm-software | G13: S5 - Trabajar con ordenadores | H13: S5.8 - Software específico | I13: Sí | J13: 3
... A136: disposición para viajar | B136: Soft Skill | C136: Disponibilidad | D136: disponibilidad para viajar | E136: willingness to travel | F136: http://data.europa.eu/esco/skill/travel | G136: T - Transversales | H136: T6.1 - Disponibilidad | I136: No | J136: 1
A139: RESUMEN AGREGADO POR CATEGORÍA ESCO
A141: Categoría Agrupada | B141: Skills Mapeadas | C141: Frecuencia Total | D141: % Demanda | E141: Prioridad Formación
A142: Software Ofimático (Office, Excel) | B142: 8 | C142: =SUMIF($C$2:$C$136,"Software Ofimático",$J$2:$J$136)+SUMIF($C$2:$C$136,"Hojas de Cálculo",$J$2:$J$136) -> 24 | D142: =C142/SUM($C$142:$C$161) -> 0.16216216 | E142: 🔴 ALTA
A143: Iniciativa/Proactividad | B143: 7 | C143: =SUMIF($C$2:$C$136,"Iniciativa",$J$2:$J$136) -> 11 | D143: =C143/SUM($C$142:$C$161) -> 0.074324324 | E143: 🔴 ALTA
A144: Comunicación | B144: 6 | C144: =SUMIF($C$2:$C$136,"Comunicación",$J$2:$J$136) -> 11 | D144: =C144/SUM($C$142:$C$161) -> 0.074324324 | E144: 🔴 ALTA
A145: Colaboración (Trabajo en equipo) | B145: 4 | C145: =SUMIF($C$2:$C$136,"Colaboración",$J$2:$J$136) -> 9 | D145: =C145/SUM($C$142:$C$161) -> 0.060810811 | E145: 🔴 ALTA
A146: Sistemas CRM | B146: 6 | C146: =SUMIF($C$2:$C$136,"Sistemas CRM",$J$2:$J$136) -> 7 | D146: =C146/SUM($C$142:$C$161) -> 0.047297297 | E146: 🟠 MEDIA
A147: Diseño Gráfico (Photoshop, Illustrator) | B147: 5 | C147: =SUMIF($C$2:$C$136,"Diseño Gráfico",$J$2:$J$136) -> 8 | D147: =C147/SUM($C$142:$C$161) -> 0.054054054 | E147: 🟠 MEDIA
A148: Orientación a Resultados | B148: 5 | C148: =SUMIF($C$2:$C$136,"Orientación a Resultados",$J$2:$J$136) -> 6 | D148: =C148/SUM($C$142:$C$161) -> 0.040540541 | E148: 🟠 MEDIA
A149: Orientación al Cliente | B149: 7 | C149: =SUMIF($C$2:$C$136,"Orientación al Cliente",$J$2:$J$136) -> 8 | D149: =C149/SUM($C$142:$C$161) -> 0.054054054 | E149: 🟠 MEDIA
A150: Liderazgo | B150: 5 | C150: =SUMIF($C$2:$C$136,"Liderazgo",$J$2:$J$136) -> 5 | D150: =C150/SUM($C$142:$C$161) -> 0.033783784 | E150: 🟠 MEDIA
A151: ERP/Gestión (SAP, Tango) | B151: 4 | C151: =SUMIF($C$2:$C$136,"ERP/Gestión",$J$2:$J$136) -> 5 | D151: =C151/SUM($C$142:$C$161) -> 0.033783784 | E151: 🟠 MEDIA
A152: Diseño CAD (AutoCAD, Solidworks) | B152: 2 | C152: =SUMIF($C$2:$C$136,"Diseño CAD",$J$2:$J$136) -> 4 | D152: =C152/SUM($C$142:$C$161) -> 0.027027027 | E152: 🟢 BAJA
A153: Marketing Digital (SEO, Ads) | B153: 4 | C153: =SUMIF($C$2:$C$136,"Marketing Digital",$J$2:$J$136) -> 4 | D153: =C153/SUM($C$142:$C$161) -> 0.027027027 | E153: 🟢 BAJA
A154: E-commerce | B154: 5 | C154: =SUMIF($C$2:$C$136,"E-commerce",$J$2:$J$136) -> 6 | D154: =C154/SUM($C$142:$C$161) -> 0.040540541 | E154: 🟢 BAJA
A155: Pensamiento Analítico | B155: 5 | C155: =SUMIF($C$2:$C$136,"Pensamiento Analítico",$J$2:$J$136) -> 5 | D155: =C155/SUM($C$142:$C$161) -> 0.033783784 | E155: 🟢 BAJA
A156: Organización/Gestión Tiempo | B156: 6 | C156: =SUMIF($C$2:$C$136,"Organización",$J$2:$J$136) -> 7 | D156: =C156/SUM($C$142:$C$161) -> 0.047297297 | E156: 🟢 BAJA
